Workbook
Name ID: Subcontractors!$A$1
Name ID: #REF!
Name InteracEmail: #REF!
Name Name: Table4[[#Headers],[Name]]
Name Name: #REF!
Name PhoneNumber: Table4[[#Headers],[Phone Number]]
Name PhoneNumber: #REF!
Name PhysicalAddress: Table4[[#Headers],[Physical Address]]
Name PhysicalAddress: #REF!
Name Worker_Name: Table4[[#Headers],[Name]]
Name Worker_Name: #REF!
Name WorkerAlias: Table4[[#Headers],[Alias]]
Name WorkerAlias: #REF!
Name WorkerComment: Subcontractors!$G$1
Name WorkerComment: #REF!
Name WorkerName: Table4[[#Headers],[Name]]
Name WorkerName: #REF!

Sheet DRAFT
A2: 46032 | C2: Date | D2: Hyatt | E2: Hrs | G2: Date | H2: Burlington | I2: Hrs | K2: Date | L2: Oshawa | M2: Hrs | O2: Date | P2: 290 Derry | Q2: Hrs | S2: Date | T2: 3400 Steeles | U2: Hrs | W2: Date | X2: Richmond Hill | Y2: Hrs | AA2: Date | AB2: Ramada Cornwall | AC2: Hrs | AE2: Date | AF2: Manitou | AG2: Hrs
A3: 46033 | C3: 46038 | D3: Niloufar Shirvani BT | E3: 7 | G3: 46035 | H3: Leslie Bacares | I3: 6.5 | T3: NONE | W3: 46033 | X3: Andrew Verches | Y3: 13 | AA3: 46032 | AB3: Dheeraj Kumar | AC3: 8.5
A4: 46034 | G4: 46037 | H4: Leslie Bacares | I4: 7.5 | W4: 46034 | X4: Andrew Verches | Y4: 7 | AA4: 46035 | AB4: Dheeraj Kumar | AC4: 8.5
A5: 46035 | G5: 46037 | H5: Theresa Blackman | I5: 6.5 | W5: 46035 | X5: Andrew Verches | Y5: 7 | AA5: 46038 | AB5: Dheeraj Kumar | AC5: 8.5
A6: 46036 | H6: above are PAID | W6: 46036 | X6: Andrew Verches | Y6: 7 | AA6: 46039 | AB6: Dheeraj Kumar | AC6: 8.5
A7: 46037 | W7: 46037 | X7: Andrew Verches | Y7: 7
A8: 46038 | W8: 46039 | X8: Andrew Verches | Y8: 13
A9: 46039 | W9: 46041 | X9: Andrew Verches | Y9: 7
A10: 46040 | W10: 46042 | X10: Andrew Verches | Y10: 7
A11: 46041 | W11: 46044 | X11: Andrew Verches | Y11: 7
A12: 46042 | W12: 46045 | X12: Andrew Verches | Y12: 7
A13: 46043 | W13: 46032 | X13: Paxson Intal Figueroa | Y13: 7
A14: 46044 | W14: 46033 | X14: Paxson Intal Figueroa | Y14: 8
A15: 46045 | W15: 46035 | X15: Paxson Intal Figueroa | Y15: 7.5
W16: 46036 | X16: Paxson Intal Figueroa | Y16: 7.5
W17: 46037 | X17: Paxson Intal Figueroa | Y17: 7.5
W18: 46038 | X18: Paxson Intal Figueroa | Y18: 7
W19: 46039 | X19: Paxson Intal Figueroa | Y19: 6
W20: 46040 | X20: Paxson Intal Figueroa | Y20: 6
W21: 46043 | X21: Paxson Intal Figueroa | Y21: 7
W22: 46044 | X22: Paxson Intal Figueroa | Y22: 8
W23: 46045 | X23: Paxson Intal Figueroa | Y23: 7

Sheet MMJ
B1: PAY PERIOD January 10 - 23, 2025 | C1: HOURS | D1: TYPE | E1: RATE | F1: GROSS | G1: NET
L2: Carry Over (June 15-28) | M2: Carry Over (June 29 - July 12) | N2: Carry Over (July 13 - 26) | O2: Carry Over (July 27 - Aug 9) | P2: Carry Over (July 27 - Aug 9) | Q2: Carry Over (Aug 10 - 23) SKYWARD | R2: Carry Over (Aug 10 - 23) SKYWARD
B3: Skyward Building | J3: Hours
A4: 5 | B4: Marjorie Kae Sarenas | C4: 60 | D4: PAYROLL | E4: 17.6 | F4: =C4*E4 -> 1056 | G4: 938.48 | H4: =#REF!+#REF! -> #REF! | J4: =(H4+I4)/16.65 -> #REF! | K4: =SUM(N4:X4) -> 104.59847 | L4: 20.29 | M4: 20.585586 | N4: =20.5855855855856-0.12 -> 20.465586 | O4: 18.941441 | P4: 18.941441 | Q4: 23 | R4: 23.25
B6: CAE
B7: Pauline Patterson | C7: =GTA!C219 -> 32 | D7: PAYROLL | E7: 18 | F7: =C7*E7 -> 576 | G7: 589.28
E10: TOTAL | F10: =SUM(F2:F9) -> 1632 | G10: =SUM(G2:G9) -> 1527.76

Sheet SUBCON
A1: =MMJ!B1 -> PAY PERIOD January 10 - 23, 2025 | B1: HOURS | C1: TYPE | D1: RATE | E1: TOTAL
A2: Best Western Plus Scarborough (38 Estate Dr)
A3: Penina Nyanchoka Mang'era | B3: =GTA!F201 -> 0 | C3: SUBCON | D3: 16.65 | E3: =B3*D3 -> 0
I4: BEST WESTERN PLUS (38 ESTATE DR, SCARBOROUGH)
A5: Best Western Plus Scarborough (38 Estate Dr) TOTAL: | B5: =SUM(B2:B4) -> 0 | I5: BEST WESTERN PLUS OTTAWA (1876 ROBERTSON RD)
A7: Maple Hotels
A8: Sunshine Padilla Rebadulla (Printed on Monthly) | B8: =OTTAWA!C72 -> 0 | C8: SUBCON | D8: 18 | E8: =B8*D8 -> 0
I9: BEST WESTERN PLUS (38 ESTATE DR, SCARBOROUGH)
A10: Maple Hotels TOTAL: | B10: =SUM(B7:B9) -> 0 | I10: BEST WESTERN PLUS OTTAWA (1876 ROBERTSON RD)
A12: Sheraton Four Points Cambridge (210 Preston Pkwy)
A13: Marjorie Kae Sarenas | B13: 60 | C13: PAYROLL | D13: 17.6 | E13: 1032.83 | F13: Skyward Building
A14: Pauline Patterson | B14: 28 | C14: PAYROLL | D14: 18 | E14: 575.63 | F14: CAE
A15: Meet Vanraj Mahida | B15: ='OUTSIDE GTA'!G197 -> 0 | C15: SUBCON | D15: 16.65 | E15: =B15*D15 -> 0
A16: Satnam Singh | B16: ='OUTSIDE GTA'!E197 -> 0 | C16: SUBCON | D16: 16.65 | E16: =B16*D16 -> 0
A17: Sukhjot Singh | B17: ='OUTSIDE GTA'!D197 -> 0 | C17: SUBCON | D17: 16.65 | E17: =B17*D17 -> 0
A18: Rahul | B18: ='OUTSIDE GTA'!H197 -> 0 | C18: SUBCON | D18: 16.65 | E18: =B18*D18 -> 0
A19: Sukhjot Singh K | B19: ='OUTSIDE GTA'!F197 -> 0 | C19: SUBCON | D19: 16.65 | E19: =B19*D19 -> 0
A20: Gurbeer | B20: ='OUTSIDE GTA'!I197 -> 0 | C20: SUBCON | D20: 16.65 | E20: =B20*D20 -> 0
A22: Sheraton Four Points Cambridge (210 Preston Pkwy) | B22: =SUM(B12:B21) -> 88
A24: Manitou Springs Resort and Mineral Spa (302 MacLachlan Ave)
A25: Huberto | B25: ='OUTSIDE GTA'!C17 -> 0 | C25: SUBCON | D25: 16.5 | E25: =B25*D25 -> 0
A26: Willy (Less $64.52 Accommodation for 4 days) | B26: ='OUTSIDE GTA'!D17 -> 0 | C26: SUBCON | D26: 16.5 | E26: =(B26*D26)-64.52 -> -64.52 | F26: Manitou Springs Resort and Mineral Spa (302 MacLachlan Ave) | G26: =(500/31)*4 -> 64.516129
C27: SUBCON | E27: =B27*D27 -> 0 | I27: DELTA TORONTO EAST (2035 SCARBOROUGH)
C28: SUBCON | E28: =B28*D28 -> 0
I29: BEST WESTERN PLUS (38 ESTATE DR, SCARBOROUGH)
A30: Holiday Inn Express Woodstock (510 Norwich Ave) TOTAL: | B30: =SUM(B24:B29) -> 0 | I30: BEST WESTERN PLUS OTTAWA (1876 ROBERTSON RD)
A32: Merland Park Cottages (12488 Loyalist Pkwy)
A33: Richard Canillas | B33: ='OUTSIDE GTA'!C270 -> 0 | C33: SUBCON | D33: 18 | E33: =B33*D33 -> 0
A34: Jeffrey | B34: ='OUTSIDE GTA'!D270 -> 0 | C34: SUBCON | D34: 18 | E34: =B34*D34 -> 0 | I34: DELTA TORONTO EAST (2035 SCARBOROUGH)
A35: Rita Shalimar C. Aradillos | B35: ='OUTSIDE GTA'!E270 -> 0 | C35: SUBCON | D35: 18 | E35: =B35*D35 -> 0
A36: Gurpreet | B36: ='OUTSIDE GTA'!F270 -> 0 | C36: SUBCON | D36: 18 | E36: =B36*D36 -> 0
A37: Dikaran | B37: ='OUTSIDE GTA'!G270 -> 0 | C37: SUBCON | D37: 18 | E37: =B37*D37 -> 0
I38: BEST WESTERN PLUS (38 ESTATE DR, SCARBOROUGH)
A39: Merland Park Cottages (12488 Loyalist Pkwy) TOTAL: | B39: =SUM(B32:B38) -> 0 | I39: BEST WESTERN PLUS OTTAWA (1876 ROBERTSON RD)
A41: Tru by Hilton Bracebridge (320 Taylor Rd, Bracebridge)
A42: Armando | B42: ='OUTSIDE GTA'!C288 -> 0 | C42: SUBCON | D42: 16.65 | E42: =B42*D42 -> 0
A43: Shirley | B43: ='OUTSIDE GTA'!D288 -> 0 | C43: SUBCON | D43: 16.65 | E43: =B43*D43 -> 0 | I43: DELTA TORONTO EAST (2035 SCARBOROUGH)
I44: BEST WESTERN PLUS (38 ESTATE DR, SCARBOROUGH)
A45: Tru by Hilton Bracebridge (320 Taylor Rd, Bracebridge) | B45: =SUM(B41:B44) -> 0 | I45: BEST WESTERN PLUS OTTAWA (1876 ROBERTSON RD)
A47: Home 2 by Hilton Woodstock (527 Lampman Pl)
A48: Menandro | B48: ='OUTSIDE GTA'!C35 -> 0 | C48: SUBCON | D48: 16.65 | E48: =B48*D48 -> 0
A49: Catherine Martin | B49: ='OUTSIDE GTA'!G35 -> 0 | C49: SUBCON | D49: 16.65 | E49: =B49*D49 -> 0
A50: Jonervin Agustin | B50: ='OUTSIDE GTA'!D35 -> 0 | C50: SUBCON | D50: 16.65 | E50: =B50*D50 -> 0
A51: Dhruvkumar Harshadkumar Patel | B51: ='OUTSIDE GTA'!E35 -> 0 | C51: SUBCON | D51: 16.65 | E51: =B51*D51 -> 0 | I51: DELTA TORONTO EAST (2035 SCARBOROUGH)
A52: Sukhjivan Singh | B52: ='OUTSIDE GTA'!F35 -> 0 | C52: SUBCON | D52: 16.65 | E52: =B52*D52 -> 0
A53: Harkirat Singh | B53: ='OUTSIDE GTA'!H35 -> 0 | C53: SUBCON | D53: 16.65 | E53: =B53*D53 -> 0
A54: Gagandeep Singh | B54: ='OUTSIDE GTA'!I35 -> 0 | C54: SUBCON | D54: 16.65 | E54: =B54*D54 -> 0
A55: Casey Alexis Rapisura | B55: ='OUTSIDE GTA'!J35 -> 0 | C55: SUBCON | D55: 16.65 | E55: =B55*D55 -> 0
A56: Azubike Emmanuel Eloka | B56: ='OUTSIDE GTA'!K35 -> 0 | C56: SUBCON | D56: 16.65 | E56: =B56*D56 -> 0
I57: BEST WESTERN PLUS (38 ESTATE DR, SCARBOROUGH)
A58: Home 2 by Hilton Woodstock (527 Lampman Pl) TOTAL: | B58: =SUM(B47:B57) -> 0 | I58: BEST WESTERN PLUS OTTAWA (1876 ROBERTSON RD)
I59: COURTYARD MISSISSAUGA WEST (290 DERRY ROAD W)
A60: Quality Inn & Suites Regina Downtown (1907 11th Ave)
A61: Harsh Vyas | B61: ='OUTSIDE GTA'!D125 -> 0 | C61: SUBCON | D61: 17 | E61: =B61*D61 -> 0
A62: Jenny Lyn Garcia Galapia (Paid) | B62: ='OUTSIDE GTA'!C125 -> 0 | C62: SUBCON | D62: 15.5 | E62: =B62*D62 -> 0
A63: Anastasiia Rostovtseva | B63: ='OUTSIDE GTA'!E125 -> 0 | C63: SUBCON | D63: 15.5 | E63: =B63*D63 -> 0
A64: Omoyele Oluwatimilehen Success | B64: ='OUTSIDE GTA'!F125 -> 0 | C64: SUBCON | D64: 15.5 | E64: =B64*D64 -> 0 | F64: Quality Inn & Suites Regina Downtown (1907 11th Ave)
A65: Adwoa | B65: ='OUTSIDE GTA'!G125 -> 0 | C65: SUBCON | D65: 15.5 | E65: =B65*D65 -> 0
I66: BEST WESTERN PLUS (38 ESTATE DR, SCARBOROUGH)
A67: Quality Inn & Suites Regina Downtown (1907 11th Ave) | B67: =SUM(B61:B66) -> 0
I68: COURTYARD MISSISSAUGA WEST (290 DERRY ROAD W)
A69: Hidden Valley Resort Muskoka (1755 Valley Rd)
A70: Armstrong (HK) | B70: {=IF((INDEX('OUTSIDE GTA'!$C$71:$ZZ$71,ROW(A1)))=0, 0,(INDEX('OUTSIDE GTA'!$C$71:$ZZ$71,ROW(A1))))} -> 0 | C70: SUBCON | D70: 16.65 | E70: =IF(B70=0, 0, B70*D70) -> 0
A71: Carl | B71: {=IF((INDEX('OUTSIDE GTA'!$C$71:$ZZ$71,ROW(A2)))=0, 0,(INDEX('OUTSIDE GTA'!$C$71:$ZZ$71,ROW(A2))))} -> 0 | C71: SUBCON | D71: 16.65 | E71: =IF(B71=0, 0, B71*D71) -> 0
A72: Flordelyn (HK) | B72: {=IF((INDEX('OUTSIDE GTA'!$C$71:$ZZ$71,ROW(A3)))=0, 0,(INDEX('OUTSIDE GTA'!$C$71:$ZZ$71,ROW(A3))))} -> 0 | C72: SUBCON | D72: 16.65 | E72: =IF(B72=0, 0, B72*D72) -> 0
A73: Gabriel | B73: {=IF((INDEX('OUTSIDE GTA'!$C$71:$ZZ$71,ROW(A4)))=0, 0,(INDEX('OUTSIDE GTA'!$C$71:$ZZ$71,ROW(A4))))} -> 0 | C73: SUBCON | D73: 16.65 | E73: =IF(B73=0, 0, B73*D73) -> 0
A74: Gerald | B74: {=IF((INDEX('OUTSIDE GTA'!$C$71:$ZZ$71,ROW(A5)))=0, 0,(INDEX('OUTSIDE GTA'!$C$71:$ZZ$71,ROW(A5))))} -> 0 | C74: SUBCON | D74: 16.65 | E74: =IF(B74=0, 0, B74*D74) -> 0
A75: Jan Mayckie | B75: {=IF((INDEX('OUTSIDE GTA'!$C$71:$ZZ$71,ROW(A6)))=0, 0,(INDEX('OUTSIDE GTA'!$C$71:$ZZ$71,ROW(A6))))} -> 0 | C75: SUBCON | D75: 16.65 | E75: =IF(B75=0, 0, B75*D75) -> 0
A76: Jennylyn Ceniza | B76: {=IF((INDEX('OUTSIDE GTA'!$C$71:$ZZ$71,ROW(A7)))=0, 0,(INDEX('OUTSIDE GTA'!$C$71:$ZZ$71,ROW(A7))))} -> 0 | C76: SUBCON | D76: 16.65 | E76: =IF(B76=0, 0, B76*D76) -> 0
A77: Mark G | B77: {=IF((INDEX('OUTSIDE GTA'!$C$71:$ZZ$71,ROW(A8)))=0, 0,(INDEX('OUTSIDE GTA'!$C$71:$ZZ$71,ROW(A8))))} -> 0 | C77: SUBCON | D77: 16.65 | E77: =IF(B77=0, 0, B77*D77) -> 0
A78: Noralyn | B78: {=IF((INDEX('OUTSIDE GTA'!$C$71:$ZZ$71,ROW(A9)))=0, 0,(INDEX('OUTSIDE GTA'!$C$71:$ZZ$71,ROW(A9))))} -> 0 | C78: SUBCON | D78: 16.65 | E78: =IF(B78=0, 0, B78*D78) -> 0
A79: Sheila/Rey | B79: {=IF((INDEX('OUTSIDE GTA'!$C$71:$ZZ$71,ROW(A10)))=0, 0,(INDEX('OUTSIDE GTA'!$C$71:$ZZ$71,ROW(A10))))} -> 0 | C79: SUBCON | D79: 16.65 | E79: =IF(B79=0, 0, B79*D79) -> 0
A80: Wilson | B80: {=IF((INDEX('OUTSIDE GTA'!$C$71:$ZZ$71,ROW(A11)))=0, 0,(INDEX('OUTSIDE GTA'!$C$71:$ZZ$71,ROW(A11))))} -> 0 | C80: SUBCON | D80: 16.65 | E80: =IF(B80=0, 0, B80*D80) -> 0
A81: Carl M | B81: {=IF((INDEX('OUTSIDE GTA'!$C$71:$ZZ$71,ROW(A12)))=0, 0,(INDEX('OUTSIDE GTA'!$C$71:$ZZ$71,ROW(A12))))} -> 0 | C81: SUBCON | D81: 20 | E81: =IF(B81=0, 0, B81*D81) -> 0
... A88: Noralyn Kids Activity | B88: {=IF((INDEX('OUTSIDE GTA'!$C$71:$ZZ$71,ROW(A19)))=0, 0,(INDEX('OUTSIDE GTA'!$C$71:$ZZ$71,ROW(A19))))} -> 0 | C88: SUBCON | D88: 16.65 | E88: =IF(B88=0, 0, B88*D88) -> 0
I89: BEST WESTERN PLUS (38 ESTATE DR, SCARBOROUGH)
A90: Hidden Valley Resort Muskoka (1755 Valley Rd) | B90: =SUM(B70:B89) -> 0
A92: BEST WESTERN PLUS MUSKOKA INN (86 HOWLAND DRIVE )
A93: Lyka | B93: ='OUTSIDE GTA'!C143 -> 0 | C93: SUBCON | D93: 16.65 | E93: =B93*D93 -> 0
A94: Zayrah | B94: ='OUTSIDE GTA'!D143 -> 0 | C94: SUBCON | D94: 16.65 | E94: =B94*D94 -> 0
I95: BEST WESTERN PLUS (38 ESTATE DR, SCARBOROUGH)
A96: BEST WESTERN PLUS MUSKOKA INN (86 HOWLAND DRIVE ) | B96: =SUM(B93:B95) -> 0
A98: Spark by Hilton Woodstock (560 Norwich Ave)
A99: Veronica Wambo Mbugua | B99: ='OUTSIDE GTA'!C53 -> 0 | C99: SUBCON | D99: 16.65 | E99: =B99*D99 -> 0
A100: Adejumo | B100: ='OUTSIDE GTA'!D53 -> 0 | C100: SUBCON | D100: 16.65 | E100: =B100*D100 -> 0
A101: Casey Alexis Rapisura | B101: ='OUTSIDE GTA'!I53 -> 0 | C101: SUBCON | D101: 16.65 | E101: =B101*D101 -> 0
A102: Dianne Grace Rimando | B102: ='OUTSIDE GTA'!E53 -> 0 | C102: SUBCON | D102: 16.65 | E102: =B102*D102 -> 0
A103: Elvira Diolazo | B103: ='OUTSIDE GTA'!G53 -> 0 | C103: SUBCON | D103: 16.65 | E103: =B103*D103 -> 0
A104: Ramanjeep Chauhan | B104: ='OUTSIDE GTA'!H53 -> 0 | C104: SUBCON | D104: 16.65 | E104: =B104*D104 -> 0
A105: Susan Omoghene | B105: ='OUTSIDE GTA'!N53 -> 0 | C105: SUBCON | D105: 16.65 | E105: =B105*D105 -> 0
A106: Jennifer Uson | B106: ='OUTSIDE GTA'!M53 -> 0 | C106: SUBCON | D106: 16.65 | E106: =B106*D106 -> 0
A107: Joseph Daniel Manapsal | B107: ='OUTSIDE GTA'!K53 -> 0 | C107: SUBCON | D107: 16.65 | E107: =B107*D107 -> 0
A108: Gautam Gurung | B108: ='OUTSIDE GTA'!O53 -> 0 | C108: SUBCON | D108: 16.65 | E108: =B108*D108 -> 0
A109: Harkirat Singh | B109: ='OUTSIDE GTA'!P53 -> 0 | C109: SUBCON | D109: 16.65 | E109: =B109*D109 -> 0
A110: Chali Rizal | B110: ='OUTSIDE GTA'!Q53 -> 0 | C110: SUBCON | D110: 16.65 | E110: =B110*D110 -> 0
A111: Voltaire John Buenaflor | B111: ='OUTSIDE GTA'!R53 -> 0 | C111: SUBCON | D111: 16.65 | E111: =B111*D111 -> 0
A112: Julius Garcia | B112: ='OUTSIDE GTA'!S53 -> 0 | C112: SUBCON | D112: 16.65 | E112: =B112*D112 -> 0
A113: Kafila | B113: ='OUTSIDE GTA'!L53 -> 0 | C113: SUBCON | D113: 16.65 | E113: =B113*D113 -> 0
A114: Harpreet Harpreet | B114: ='OUTSIDE GTA'!T53 -> 0 | C114: SUBCON | D114: 16.65 | E114: =B114*D114 -> 0
A115: Folashade Adekoya | B115: ='OUTSIDE GTA'!V53 -> 0 | C115: SUBCON | D115: 16.65 | E115: =B115*D115 -> 0
...

Sheet SUBCON (2)
A1: PAY PERIOD September 20 - October 3, 2025 | B1: HOURS | C1: TYPE | D1: RATE | E1: TOTAL | F1: HOTEL
A2: Best Western Plus Scarborough (38 Estate Dr)
A3: Penina Nyanchoka Mang'era | B3: =GTA!F201 -> 0 | C3: SUBCON | D3: 16.65 | E3: =B3*D3 -> 0
A5: Best Western Plus Scarborough (38 Estate Dr) TOTAL: | B5: =SUM(B2:B4) -> 0
A7: Maple Hotels
A8: Sunshine Padilla Rebadulla (Printed on Monthly) | B8: =OTTAWA!C72 -> 0 | C8: SUBCON | D8: 18 | E8: =B8*D8 -> 0
A10: Maple Hotels TOTAL: | B10: =SUM(B7:B9) -> 0
A12: Sheraton Four Points Cambridge (210 Preston Pkwy)
A13: Joshua Agorilla | B13: ='OUTSIDE GTA'!C197 -> 0 | C13: SUBCON | D13: 16.65 | E13: =B13*D13 -> 0
A14: Aakash | B14: ='OUTSIDE GTA'!J197 -> 0 | C14: SUBCON | D14: 16.65 | E14: =B14*D14 -> 0
A15: Meet Vanraj Mahida | B15: ='OUTSIDE GTA'!G197 -> 0 | C15: SUBCON | D15: 16.65 | E15: =B15*D15 -> 0
A16: Satnam Singh | B16: ='OUTSIDE GTA'!E197 -> 0 | C16: SUBCON | D16: 16.65 | E16: =B16*D16 -> 0
A17: Sukhjot Singh | B17: ='OUTSIDE GTA'!D197 -> 0 | C17: SUBCON | D17: 16.65 | E17: =B17*D17 -> 0
A18: Rahul | B18: ='OUTSIDE GTA'!H197 -> 0 | C18: SUBCON | D18: 16.65 | E18: =B18*D18 -> 0
A19: Sukhjot Singh K | B19: ='OUTSIDE GTA'!F197 -> 0 | C19: SUBCON | D19: 16.65 | E19: =B19*D19 -> 0
A20: Gurbeer | B20: ='OUTSIDE GTA'!I197 -> 0 | C20: SUBCON | D20: 16.65 | E20: =B20*D20 -> 0
A22: Sheraton Four Points Cambridge (210 Preston Pkwy) | B22: =SUM(B12:B21) -> 0
A24: Holiday Inn Express Woodstock (510 Norwich Ave)
A25: Michelle Enriquez | B25: ='OUTSIDE GTA'!D17 -> 0 | C25: SUBCON | D25: 17 | E25: =B25*D25 -> 0 | F25: Holiday Inn Express Woodstock (510 Norwich Ave)
A26: Angel Ellan | B26: ='OUTSIDE GTA'!Q17 -> 0 | C26: SUBCON | D26: 17 | E26: =B26*D26 -> 0 | F26: Holiday Inn Express Woodstock (510 Norwich Ave)
A27: Menandro | B27: ='OUTSIDE GTA'!P17 -> 0 | C27: SUBCON | D27: 16.65 | E27: =B27*D27 -> 0 | F27: Holiday Inn Express Woodstock (510 Norwich Ave)
A28: Herbert | B28: ='OUTSIDE GTA'!C17 -> 0 | C28: SUBCON | D28: 16.65 | E28: =B28*D28 -> 0 | F28: Holiday Inn Express Woodstock (510 Norwich Ave)
A30: Holiday Inn Express Woodstock (510 Norwich Ave) TOTAL: | B30: =SUM(B24:B29) -> 0
A32: Merland Park Cottages (12488 Loyalist Pkwy)
A33: Richard Canillas | B33: ='OUTSIDE GTA'!C270 -> 0 | C33: SUBCON | D33: 18 | E33: =B33*D33 -> 0
A34: Jeffrey | B34: ='OUTSIDE GTA'!D270 -> 0 | C34: SUBCON | D34: 18 | E34: =B34*D34 -> 0
A35: Rita Shalimar C. Aradillos | B35: ='OUTSIDE GTA'!E270 -> 0 | C35: SUBCON | D35: 18 | E35: =B35*D35 -> 0
A36: Gurpreet | B36: ='OUTSIDE GTA'!F270 -> 0 | C36: SUBCON | D36: 18 | E36: =B36*D36 -> 0
A37: Dikaran | B37: ='OUTSIDE GTA'!G270 -> 0 | C37: SUBCON | D37: 18 | E37: =B37*D37 -> 0
A39: Merland Park Cottages (12488 Loyalist Pkwy) TOTAL: | B39: =SUM(B32:B38) -> 0
A41: Tru by Hilton Bracebridge (320 Taylor Rd, Bracebridge)
A42: Armando | B42: ='OUTSIDE GTA'!C288 -> 0 | C42: SUBCON | D42: 16.65 | E42: =B42*D42 -> 0
A43: Shirley | B43: ='OUTSIDE GTA'!D288 -> 0 | C43: SUBCON | D43: 16.65 | E43: =B43*D43 -> 0
A45: Tru by Hilton Bracebridge (320 Taylor Rd, Bracebridge) | B45: =SUM(B41:B44) -> 0
A47: Home 2 by Hilton Woodstock (527 Lampman Pl)
A48: Menandro | B48: ='OUTSIDE GTA'!C35 -> 0 | C48: SUBCON | D48: 16.65 | E48: =B48*D48 -> 0 | F48: Home 2 by Hilton Woodstock (527 Lampman Pl)
A49: Catherine Martin | B49: ='OUTSIDE GTA'!G35 -> 0 | C49: SUBCON | D49: 16.65 | E49: =B49*D49 -> 0 | F49: Home 2 by Hilton Woodstock (527 Lampman Pl)
A50: Jonervin Agustin | B50: ='OUTSIDE GTA'!D35 -> 0 | C50: SUBCON | D50: 16.65 | E50: =B50*D50 -> 0 | F50: Home 2 by Hilton Woodstock (527 Lampman Pl)
A51: Dhruvkumar Harshadkumar Patel | B51: ='OUTSIDE GTA'!E35 -> 0 | C51: SUBCON | D51: 16.65 | E51: =B51*D51 -> 0 | F51: Home 2 by Hilton Woodstock (527 Lampman Pl)
A52: Sukhjivan Singh | B52: ='OUTSIDE GTA'!F35 -> 0 | C52: SUBCON | D52: 16.65 | E52: =B52*D52 -> 0 | F52: Home 2 by Hilton Woodstock (527 Lampman Pl)
A53: Harkirat Singh | B53: ='OUTSIDE GTA'!H35 -> 0 | C53: SUBCON | D53: 16.65 | E53: =B53*D53 -> 0 | F53: Home 2 by Hilton Woodstock (527 Lampman Pl)
A54: Gagandeep Singh | B54: ='OUTSIDE GTA'!I35 -> 0 | C54: SUBCON | D54: 16.65 | E54: =B54*D54 -> 0 | F54: Home 2 by Hilton Woodstock (527 Lampman Pl)
A55: Casey Alexis Rapisura | B55: ='OUTSIDE GTA'!J35 -> 0 | C55: SUBCON | D55: 16.65 | E55: =B55*D55 -> 0 | F55: Home 2 by Hilton Woodstock (527 Lampman Pl)
A56: Azubike Emmanuel Eloka | B56: ='OUTSIDE GTA'!K35 -> 0 | C56: SUBCON | D56: 16.65 | E56: =B56*D56 -> 0 | F56: Home 2 by Hilton Woodstock (527 Lampman Pl)
A58: Home 2 by Hilton Woodstock (527 Lampman Pl) TOTAL: | B58: =SUM(B47:B57) -> 0
A60: Quality Inn & Suites Regina Downtown (1907 11th Ave)
A61: Harsh Vyas | B61: ='OUTSIDE GTA'!D125 -> 0 | C61: SUBCON | D61: 17 | E61: =B61*D61 -> 0 | F61: Quality Inn & Suites Regina Downtown (1907 11th Ave)
A62: Jenny Lyn Garcia Galapia (Paid) | B62: ='OUTSIDE GTA'!C125 -> 0 | C62: SUBCON | D62: 15.5 | E62: =B62*D62 -> 0 | F62: Quality Inn & Suites Regina Downtown (1907 11th Ave)
A63: Anastasiia Rostovtseva | B63: ='OUTSIDE GTA'!E125 -> 0 | C63: SUBCON | D63: 15.5 | E63: =B63*D63 -> 0 | F63: Quality Inn & Suites Regina Downtown (1907 11th Ave)
A64: Omoyele Oluwatimilehen Success | B64: ='OUTSIDE GTA'!F125 -> 0 | C64: SUBCON | D64: 15.5 | E64: =B64*D64 -> 0 | F64: Quality Inn & Suites Regina Downtown (1907 11th Ave)
A65: Adwoa | B65: ='OUTSIDE GTA'!G125 -> 0 | C65: SUBCON | D65: 15.5 | E65: =B65*D65 -> 0 | F65: Quality Inn & Suites Regina Downtown (1907 11th Ave)
A67: Quality Inn & Suites Regina Downtown (1907 11th Ave) | B67: =SUM(B61:B66) -> 0
A69: Hidden Valley Resort Muskoka (1755 Valley Rd)
A70: Gabriel Aaron Ramos | B70: ='OUTSIDE GTA'!C71 -> 0 | C70: SUBCON | D70: 20 | E70: =B70*D70 -> 0 | F70: Hidden Valley Resort Muskoka (1755 Valley Rd)
A71: Rey Salas | B71: ='OUTSIDE GTA'!H71 -> 0 | C71: SUBCON | D71: 16.65 | E71: =B71*D71 -> 0 | F71: Hidden Valley Resort Muskoka (1755 Valley Rd)
A72: Rhandolp Carl Reyes | B72: ='OUTSIDE GTA'!G71 -> 0 | C72: SUBCON | D72: 16.65 | E72: =B72*D72 -> 0 | F72: Hidden Valley Resort Muskoka (1755 Valley Rd)
A73: Carl Maintenance | B73: ='OUTSIDE GTA'!M71 -> 0 | C73: SUBCON | D73: 20 | E73: =B73*D73 -> 0 | F73: Hidden Valley Resort Muskoka (1755 Valley Rd)
A74: Geraldo Aquino | B74: ='OUTSIDE GTA'!F71 -> 0 | C74: SUBCON | D74: 16.65 | E74: =B74*D74 -> 0 | F74: Hidden Valley Resort Muskoka (1755 Valley Rd)
A75: Gerald Maintenance | B75: ='OUTSIDE GTA'!N71 -> 0 | C75: SUBCON | D75: 20 | E75: =B75*D75 -> 0 | F75: Hidden Valley Resort Muskoka (1755 Valley Rd)
A76: Jennylyn | B76: ='OUTSIDE GTA'!I71 -> 0 | C76: SUBCON | D76: 16.65 | E76: =B76*D76 -> 0 | F76: Hidden Valley Resort Muskoka (1755 Valley Rd)
A77: Mark G | B77: ='OUTSIDE GTA'!P71 -> 0 | C77: SUBCON | D77: 16.65 | E77: =B77*D77 -> 0 | F77: Hidden Valley Resort Muskoka (1755 Valley Rd)
A78: Noralyn | B78: ='OUTSIDE GTA'!J71 -> 0 | C78: SUBCON | D78: 16.65 | E78: =B78*D78 -> 0 | F78: Hidden Valley Resort Muskoka (1755 Valley Rd)
A79: Jan Mayckie | B79: ='OUTSIDE GTA'!Q71 -> 0 | C79: SUBCON | D79: 16.65 | E79: =B79*D79 -> 0 | F79: Hidden Valley Resort Muskoka (1755 Valley Rd)
A80: Flordelyn (HK) | B80: ='OUTSIDE GTA'!K71 -> 0 | C80: SUBCON | D80: 16.65 | E80: =B80*D80 -> 0 | F80: Hidden Valley Resort Muskoka (1755 Valley Rd)
A81: Flordelyn (Cook) | B81: ='OUTSIDE GTA'!E71 -> 0 | C81: SUBCON | D81: 20 | E81: =B81*D81 -> 0 | F81: Hidden Valley Resort Muskoka (1755 Valley Rd)
A82: Flordelyn (Kids Activities) | B82: ='OUTSIDE GTA'!T71 -> 0 | C82: SUBCON | D82: 16.65 | E82: =B82*D82 -> 0 | F82: Hidden Valley Resort Muskoka (1755 Valley Rd)
A83: Noralyn (Kids Activities) | B83: ='OUTSIDE GTA'!U71 -> 0 | C83: SUBCON | D83: 16.65 | E83: =B83*D83 -> 0 | F83: Hidden Valley Resort Muskoka (1755 Valley Rd)
A84: Roselle Navidad | B84: ='OUTSIDE GTA'!D71 -> 0 | C84: SUBCON | D84: 20 | E84: =B84*D84 -> 0 | F84: Hidden Valley Resort Muskoka (1755 Valley Rd)
A85: Roselle Navidad (HK) | B85: ='OUTSIDE GTA'!L71 -> 0 | C85: SUBCON | D85: 16.65 | E85: =B85*D85 -> 0 | F85: Hidden Valley Resort Muskoka (1755 Valley Rd)
A86: Flor (Maintenance) | B86: ='OUTSIDE GTA'!O71 -> 0 | C86: SUBCON | D86: 20 | E86: =B86*D86 -> 0 | F86: Hidden Valley Resort Muskoka (1755 Valley Rd)
A87: Wilson (Maintenance) | B87: ='OUTSIDE GTA'!R71 -> 0 | C87: SUBCON | D87: 20 | E87: =B87*D87 -> 0 | F87: Hidden Valley Resort Muskoka (1755 Valley Rd)
A88: Nelson (Maintenance) | B88: ='OUTSIDE GTA'!S71 -> 0 | C88: SUBCON | D88: 20 | E88: =B88*D88 -> 0 | F88: Hidden Valley Resort Muskoka (1755 Valley Rd)
A90: Hidden Valley Resort Muskoka (1755 Valley Rd) | B90: =SUM(B70:B89) -> 0
A92: BEST WESTERN PLUS MUSKOKA INN (86 HOWLAND DRIVE )
A93: Lyka | B93: ='OUTSIDE GTA'!C143 -> 0 | C93: SUBCON | D93: 20 | E93: =B93*D93 -> 0 | F93: BEST WESTERN PLUS MUSKOKA INN (86 HOWLAND DRIVE )
A94: Zayrah | B94: ='OUTSIDE GTA'!D143 -> 0 | C94: SUBCON | D94: 16.65 | E94: =B94*D94 -> 0 | F94: BEST WESTERN PLUS MUSKOKA INN (86 HOWLAND DRIVE )
A96: BEST WESTERN PLUS MUSKOKA INN (86 HOWLAND DRIVE ) | B96: =SUM(B93:B95) -> 0
A98: Spark by Hilton Woodstock (560 Norwich Ave)
A99: Veronica Wambo Mbugua | B99: ='OUTSIDE GTA'!C53 -> 0 | C99: SUBCON | D99: 16.65 | E99: =B99*D99 -> 0
A100: Casey Alexis Rapisura | B100: ='OUTSIDE GTA'!I53 -> 0 | C100: SUBCON | D100: 16.65 | E100: =B100*D100 -> 0
A101: Dianne Grace Rimando | B101: ='OUTSIDE GTA'!E53 -> 0 | C101: SUBCON | D101: 16.65 | E101: =B101*D101 -> 0
A102: Elvira Diolazo | B102: ='OUTSIDE GTA'!G53 -> 0 | C102: SUBCON | D102: 16.65 | E102: =B102*D102 -> 0
A103: Ramanjeep Chauhan | B103: ='OUTSIDE GTA'!H53 -> 0 | C103: SUBCON | D103: 16.65 | E103: =B103*D103 -> 0
A104: Susan Omoghene | B104: ='OUTSIDE GTA'!N53 -> 0 | C104: SUBCON | D104: 16.65 | E104: =B104*D104 -> 0
A105: Jennifer Uson | B105: ='OUTSIDE GTA'!M53 -> 0 | C105: SUBCON | D105: 16.65 | E105: =B105*D105 -> 0
A106: Joseph Daniel Manapsal | B106: ='OUTSIDE GTA'!K53 -> 0 | C106: SUBCON | D106: 16.65 | E106: =B106*D106 -> 0
A107: Gautam Gurung | B107: ='OUTSIDE GTA'!O53 -> 0 | C107: SUBCON | D107: 16.65 | E107: =B107*D107 -> 0
A108: Harkirat Singh | B108: ='OUTSIDE GTA'!P53 -> 0 | C108: SUBCON | D108: 16.65 | E108: =B108*D108 -> 0
A109: Chali Rizal | B109: ='OUTSIDE GTA'!Q53 -> 0 | C109: SUBCON | D109: 16.65 | E109: =B109*D109 -> 0
A110: Voltaire John Buenaflor | B110: ='OUTSIDE GTA'!R53 -> 0 | C110: SUBCON | D110: 16.65 | E110: =B110*D110 -> 0
A111: Julius Garcia | B111: ='OUTSIDE GTA'!S53 -> 0 | C111: SUBCON | D111: 16.65 | E111: =B111*D111 -> 0
A112: Kafila | B112: ='OUTSIDE GTA'!L53 -> 0 | C112: SUBCON | D112: 16.65 | E112: =B112*D112 -> 0
A113: Harpreet Harpreet | B113: ='OUTSIDE GTA'!T53 -> 0 | C113: SUBCON | D113: 16.65 | E113: =B113*D113 -> 0
A114: Folashade Adekoya | B114: ='OUTSIDE GTA'!V53 -> 0 | C114: SUBCON | D114: 16.65 | E114: =B114*D114 -> 0
A115: Santi Thapa | B115: ='OUTSIDE GTA'!X53 -> 0 | C115: SUBCON | D115: 16.65 | E115: =B115*D115 -> 0
A116: Gurpreet K | B116: ='OUTSIDE GTA'!Y53 -> 0 | C116: SUBCON | D116: 16.65 | E116: =B116*D116 -> 0
A117: Isaac | B117: ='OUTSIDE GTA'!J53 -> 0 | C117: SUBCON | D117: 16.65 | E117: =B117*D117 -> 0
A118: Manpreet Singh | B118: ='OUTSIDE GTA'!Z53 -> 0 | C118: SUBCON | D118: 16.65 | E118: =B118*D118 -> 0
A119: Jonervin Agustin | B119: ='OUTSIDE GTA'!AA53 -> 0 | C119: SUBCON | D119: 16.65 | E119: =B119*D119 -> 0
A120: Woddy Rivera | B120: ='OUTSIDE GTA'!AC53 -> 0 | C120: SUBCON | D120: 16.65 | E120: =B120*D120 -> 0
...

Sheet Tally
A1: Hotel | B1: Subcon / Payroll | C1: Timesheet
A2: BC.Holiday Inn Elk Lake Victoria BC (4670 Elk Lake Drive) | B2: ='British Columbia'!T19 -> 111.5 | C2: ='British Columbia'!T19 -> 111.5 | D2: =IF(B2=C2, "✔", "❌❌❌") -> ✔ | F2: =B2-C2 -> 0
A3: BC.Holiday Inn Express & Suites Victoria - Colwood (318 Wale Rd) | B3: ='SUBCON - BC'!B32 -> 0 | C3: =SUM('British Columbia'!C29:S35) -> 0 | D3: =IF(B3=C3, "✔", "❌❌❌") -> ✔ | F3: =B3-C3 -> 0
A4: BC.Motel 6 Saanichton Victoria Airport BC (2401 Mt Newton Cross Rd) | B4: ='SUBCON - BC'!B53 -> 0 | C4: =SUM('British Columbia'!C48:S54) -> 0 | D4: =IF(B4=C4, "✔", "❌❌❌") -> ✔ | F4: =B4-C4 -> 0
A5: Best Western Plus Muskoka Inn (86 Howland Dr) | B5: =SUBCON!B96 -> 0 | C5: ='OUTSIDE GTA'!B143 -> 0 | D5: =IF(B5=C5, "✔", "❌❌❌") -> ✔ | F5: =B5-C5 -> 0
A6: Best Western Plus Ottawa (1876 Robertson Rd) | B6: =SUBCON!B201 -> 0 | C6: =OTTAWA!B18 -> 0 | D6: =IF(B6=C6, "✔", "❌❌❌") -> ✔ | F6: =B6-C6 -> 0
A7: Best Western Plus Scarborough (38 Estate Dr) | B7: =SUBCON!B5 -> 0 | C7: =GTA!B201 -> 0 | D7: =IF(B7=C7, "✔", "❌❌❌") -> ✔ | F7: =B7-C7 -> 0
A8: CAE (2025 Logistics Dr) | B8: =MMJ!C7 -> 32 | C8: =GTA!B219 -> 32 | D8: =IF(B8=C8, "✔", "❌❌❌") -> ✔ | F8: =B8-C8 -> 0
A9: Chatham-Kent | B9: =SUBCON!B838 -> 0 | C9: ='OUTSIDE GTA'!B107 -> 0 | D9: =IF(B9=C9, "✔", "❌❌❌") -> ✔ | F9: =B9-C9 -> 0
A10: Courtyard and TownePlace Suites Oshawa (1011 Bloor St E) | B10: =SUBCON!B253 -> 0 | C10: =GTA!B147 -> 0 | D10: =IF(B10=C10, "✔", "❌❌❌") -> ✔ | F10: =B10-C10 -> 0
A11: Courtyard by Marriott Toronto Mississauga West (290 Derry Rd W) | B11: =SUBCON!B237 -> 0 | C11: =GTA!B129 -> 0 | D11: =IF(B11=C11, "✔", "❌❌❌") -> ✔ | F11: =B11-C11 -> 0
A12: Days Inn Ottawa Downtown (319 Rideau St) | B12: =SUBCON!B135 -> 0 | C12: =OTTAWA!B54 -> 0
A13: Days Inn Ottawa West (350 Moodie Dr) | B13: =SUBCON!B348 -> 0 | C13: =OTTAWA!B36 -> 0 | D13: =IF(B13=C13, "✔", "❌❌❌") -> ✔ | F13: =B13-C13 -> 0
A14: Delta Toronto East Scarborough (2035 Kennedy Rd) | B14: =SUBCON!B363 -> 0 | C14: =GTA!B363 -> 0 | D14: =IF(B14=C14, "✔", "❌❌❌") -> ✔ | F14: =B14-C14 -> 0
A15: Edward Hotel North York (185 Yorkland Blvd) | B15: =SUBCON!B398 -> 0 | C15: =GTA!B111 -> 0 | D15: =IF(B15=C15, "✔", "❌❌❌") -> ✔ | F15: =B15-C15 -> 0
A16: Fairfield Inn and Suites Brampton (150 Westcreek Blvd) | B16: =SUBCON!B403 -> 0 | C16: =GTA!B381 -> 0 | D16: =IF(B16=C16, "✔", "❌❌❌") -> ✔ | F16: =B16-C16 -> 0
A17: Gupta Household Stratford (53 McFarlane Street) | B17: =SUBCON!B557 -> 0 | C17: ='OUTSIDE GTA'!B215 -> 0
A18: Hampton Inn Midland (877 King St) | B18: =SUBCON!B884 -> 0 | C18: ='OUTSIDE GTA'!B161 -> 0 | D18: =IF(B18=C18, "✔", "❌❌❌") -> ✔
A19: Hidden Valley Resort Muskoka (1755 Valley Rd) | B19: =SUBCON!B90 -> 0 | C19: ='OUTSIDE GTA'!B71 -> 0 | D19: =IF(B19=C19, "✔", "❌❌❌") -> ✔ | F19: =B19-C19 -> 0
A20: Hilton Toronto Markham (8500 Warden Ave) | B20: =SUBCON!B476 -> 0 | C20: =GTA!B255 -> 0 | D20: =IF(B20=C20, "✔", "❌❌❌") -> ✔ | F20: =B20-C20 -> 0
A21: Holiday Inn Burlington (3063 S Service Rd) | B21: =SUBCON!B543 -> 20.5 | C21: =GTA!B273 -> 20.5 | D21: =IF(B21=C21, "✔", "❌❌❌") -> ✔ | F21: =B21-C21 -> 0
A22: Holiday Inn Express Mississauga (2125 N Sheridan W) | B22: =SUBCON!B639 -> 0 | C22: =GTA!B57 -> 0 | D22: =IF(B22=C22, "✔", "❌❌❌") -> ✔ | F22: =B22-C22 -> 0
A23: Holiday Inn Express North York (30 Norfinch Dr) | B23: =SUBCON!B373 -> 0 | C23: =GTA!B93 -> 0 | D23: =IF(B23=C23, "✔", "❌❌❌") -> ✔ | F23: =B23-C23 -> 0
A24: Holiday Inn Express Richmond Hill (10 East Pearce St) | B24: =SUBCON!B577 -> 160.5 | C24: =GTA!B39 -> 160.5 | D24: =IF(B24=C24, "✔", "❌❌❌") -> ✔ | F24: =B24-C24 -> 0
A25: Holiday Inn Express Toronto East (50 Estate Dr) | B25: =SUBCON!B647 -> 0 | C25: =GTA!B399 -> 0 | D25: =IF(B25=C25, "✔", "❌❌❌") -> ✔ | F25: =B25-C25 -> 0
A26: Holiday Inn Express Woodstock (510 Norwich Ave) | B26: =SUBCON!B30 -> 0 | C26: ='OUTSIDE GTA'!B17 -> 0 | D26: =IF(B26=C26, "✔", "❌❌❌") -> ✔ | F26: =B26-C26 -> 0
A27: Home 2 by Hilton Woodstock (527 Lampman Pl) | B27: =SUBCON!B58 -> 0 | C27: ='OUTSIDE GTA'!B35 -> 0 | D27: =IF(B27=C27, "✔", "❌❌❌") -> ✔ | F27: =B27-C27 -> 0
A28: Hyatt Place Mississauga (5787 Hurontario St) | B28: =SUBCON!B803 -> 7 | C28: =GTA!B21 -> 7 | D28: =IF(B28=C28, "✔", "❌❌❌") -> ✔ | F28: =B28-C28 -> 0
A29: Knights Inn Toronto East (22 Metropolitan) | B29: =SUBCON!B815 -> 0 | C29: =GTA!B475 -> 0 | D29: =IF(B29=C29, "✔", "❌❌❌") -> ✔ | F29: =B29-C29 -> 0
A30: McKesson Canada - Airport (665B Airport Rd) | D30: =IF(B30=C30, "✔", "❌❌❌") -> ✔ | F30: =B30-C30 -> 0
A31: Merland Park Cottages (12488 Loyalist Pkwy) | B31: =SUBCON!B39 -> 0 | C31: ='OUTSIDE GTA'!B270 -> 0 | D31: =IF(B31=C31, "✔", "❌❌❌") -> ✔ | F31: =B31-C31 -> 0
A32: Quality Inn & Suites Regina Downtown (1907 11th Ave) | B32: =SUBCON!B67 -> 0 | C32: ='OUTSIDE GTA'!B125 -> 0 | D32: =IF(B32=C32, "✔", "❌❌❌") -> ✔ | F32: =B32-C32 -> 0
A33: Radisson Toronto East (55 Hallcrown Pl) | B33: =SUBCON!B849 -> 0 | C33: =GTA!B75 -> 0 | D33: =IF(B33=C33, "✔", "❌❌❌") -> ✔ | F33: =B33-C33 -> 0
A34: Ramada by Wyndham Cornwall (805 Brookdale Ave) | B34: =SUBCON!B855 -> 34 | C34: ='OUTSIDE GTA'!B179 -> 34 | D34: =IF(B34=C34, "✔", "❌❌❌") -> ✔ | F34: =B34-C34 -> 0
A35: Ramada by Wyndham Niagara Falls by the River (4357 River Rd) | B35: =SUBCON!B909 -> 0 | C35: ='OUTSIDE GTA'!B89 -> 0 | D35: =IF(B35=C35, "✔", "❌❌❌") -> ✔ | F35: =B35-C35 -> 0
A36: Sheraton Four Points Cambridge (210 Preston Pky) | B36: =SUBCON!B22 -> 88 | C36: ='OUTSIDE GTA'!B197 -> 0 | D36: =IF(B36=C36, "✔", "❌❌❌") -> ❌❌❌ | F36: =B36-C36 -> 88
A37: Sheraton Four Points Hamilton (49 Goderich Rd) | B37: =SUBCON!B432 -> 0 | C37: ='OUTSIDE GTA'!B233 -> 0 | D37: =IF(B37=C37, "✔", "❌❌❌") -> ✔ | F37: =B37-C37 -> 0
A38: Sheraton Four Points Toronto Airport East (2180 Islington Ave ) | B38: =SUBCON!B408 -> 0 | C38: =GTA!B237 -> 0 | D38: =IF(B38=C38, "✔", "❌❌❌") -> ✔ | F38: =B38-C38 -> 0
A39: Sheraton Four Points Vaughan (3400 Steeles Ave W) | B39: =SUBCON!B591 -> 0 | C39: =SUM(GTA!D165:R165) -> 0 | D39: =IF(B39=C39, "✔", "❌❌❌") -> ✔ | F39: =B39-C39 -> 0
A40: Spark by Hilton Woodstock (560 Norwich Ave) | B40: =SUBCON!B127 -> 0 | C40: ='OUTSIDE GTA'!B53 -> 0 | D40: =IF(B40=C40, "✔", "❌❌❌") -> ✔ | F40: =B40-C40 -> 0
A41: The City View Inn (1400 Plains Rd W) | B41: =SUBCON!B552 -> 0 | C41: =GTA!B291 -> 0 | D41: =IF(B41=C41, "✔", "❌❌❌") -> ✔ | F41: =B41-C41 -> 0
A42: Toronto Plaza Hotel (1677 Wilson Ave) | B42: =SUBCON!B929 -> 0 | C42: =GTA!B183 -> 0 | D42: =IF(B42=C42, "✔", "❌❌❌") -> ✔ | F42: =B42-C42 -> 0
A43: Travelodge Bracebridge (320 Taylor Rd) | B43: =SUBCON!B45 -> 0 | C43: ='OUTSIDE GTA'!B288 -> 0 | D43: =IF(B43=C43, "✔", "❌❌❌") -> ✔ | F43: =B43-C43 -> 0
D44: =IF(B44=C44, "✔", "❌❌❌") -> ✔ | F44: =B44-C44 -> 0
B45: =SUM(B2:B44) -> 453.5 | C45: =SUM(C2:C44) -> 365.5

Sheet Master List
A1: =MMJ!B1 -> PAY PERIOD January 10 - 23, 2025 | B1: HOURS | C1: TYPE | D1: RATE | E1: TOTAL | F1: Hotel
A2: Andrew Verches | B2: 82 | C2: SUBCON | D2: 16.65 | E2: 1365.3 | F2: Holiday Inn Express Richmond Hill (10 East Pearce St)
A3: Dheeraj Kumar I | B3: 34 | C3: SUBCON | D3: 18 | E3: 612 | F3: Ramada by Wyndham Cornwall (805 Brookdale Ave)
A4: Leslie Bacares - PAID | B4: 14 | C4: SUBCON | D4: 16.65 | E4: 233.1 | F4: Holiday Inn Burlington (3063 S Service Rd)
A5: Niloufar Shirvani | B5: 7 | C5: SUBCON | D5: 20 | E5: 140 | F5: Hyatt Place Mississauga (5787 Hurontario St)
A6: Pauline Patterson | B6: 32 | C6: PAYROLL | D6: 18 | E6: 589.28 | F6: CAE
A7: Paxson Intal Figueroa | B7: 78.5 | C7: SUBCON | D7: 16.65 | E7: 1307.025 | F7: Holiday Inn Express Richmond Hill (10 East Pearce St)
A8: Theresa Blackman - PAID | B8: 6.5 | C8: SUBCON | D8: 16.65 | E8: 108.225 | F8: Holiday Inn Burlington (3063 S Service Rd)
H66: ='SUMMARY A-Z'!F8 -> 1093.325 | I66: {='Summary Hotel'!D191:E191} -> 3261.605 | J66: 0
D67: TOTAL: | E67: =SUM(E1:E66) -> 4354.93
E68: =SUM(H66:I66) -> 4354.93 | F68: =E67-E68 -> 0

Sheet SUMMARY A-Z
A1: =MMJ!B1 -> PAY PERIOD January 10 - 23, 2025 | B1: Mail or Pickup | C1: HOURS | D1: TYPE | E1: RATE | F1: TOTAL | G1: Hotel | H1: Interac
A2: Dheeraj Kumar | B2: =VLOOKUP(A2,Table4[[Name]:[Mail or Pickup]],7,FALSE) -> ** | C2: 34 | D2: SUBCON | E2: 18 | F2: 612 | G2: Ramada by Wyndham Cornwall (805 Brookdale Ave) | H2: =VLOOKUP(A2,Subcontractors!B2:D1734,3,FALSE) -> dheerajkashyap615@gmail.com
A3: Leslie Bacares - PAID | C3: 14 | D3: SUBCON | E3: 16.65 | F3: 233.1 | G3: Holiday Inn Burlington (3063 S Service Rd) | H3: Bacaresleslie@gmail.com
A4: Niloufar Shirvani | B4: =VLOOKUP(A4,Table4[[Name]:[Mail or Pickup]],7,FALSE) -> ** | C4: 7 | D4: SUBCON | E4: 20 | F4: 140 | G4: Hyatt Place Mississauga (5787 Hurontario St) | H4: =VLOOKUP(A4,Subcontractors!B4:D1736,3,FALSE) -> shirvaninli@gmail.com
A5: Theresa Blackman -PAID | C5: 6.5 | D5: SUBCON | E5: 16.65 | F5: 108.225 | G5: Holiday Inn Burlington (3063 S Service Rd) | H5: theresablackman75@yahoo.com
H6: =_xlfn.IFNA(VLOOKUP(A6, Table4[[Name]:[Interac Email Final]], 3, FALSE), "")
A7: Total | E7: =SUM(F2:F6) -> 1093.325
F8: =E7 -> 1093.325

Sheet SUBCON (4)
A1: PAY PERIOD September 20 - October 3, 2025 | B1: HOURS | C1: TYPE | D1: RATE | E1: TOTAL | F1: HOTEL
A2: Best Western Plus Scarborough (38 Estate Dr)
A3: Penina Nyanchoka Mang'era | B3: =GTA!F201 -> 0 | C3: SUBCON | D3: 16.65 | E3: =B3*D3 -> 0
A5: Best Western Plus Scarborough (38 Estate Dr) TOTAL: | B5: =SUM(B2:B4) -> 0
A7: Maple Hotels
A8: Sunshine Padilla Rebadulla (Printed on Monthly) | B8: =OTTAWA!C72 -> 0 | C8: SUBCON | D8: 18 | E8: =B8*D8 -> 0
A10: Maple Hotels TOTAL: | B10: =SUM(B7:B9) -> 0
A12: Sheraton Four Points Cambridge (210 Preston Pkwy)
A13: Joshua Agorilla | B13: ='OUTSIDE GTA'!C197 -> 0 | C13: SUBCON | D13: 16.65 | E13: =B13*D13 -> 0
A14: Aakash | B14: ='OUTSIDE GTA'!J197 -> 0 | C14: SUBCON | D14: 16.65 | E14: =B14*D14 -> 0
A15: Meet Vanraj Mahida | B15: ='OUTSIDE GTA'!G197 -> 0 | C15: SUBCON | D15: 16.65 | E15: =B15*D15 -> 0
A16: Satnam Singh | B16: ='OUTSIDE GTA'!E197 -> 0 | C16: SUBCON | D16: 16.65 | E16: =B16*D16 -> 0
A17: Sukhjot Singh | B17: ='OUTSIDE GTA'!D197 -> 0 | C17: SUBCON | D17: 16.65 | E17: =B17*D17 -> 0
A18: Rahul | B18: ='OUTSIDE GTA'!H197 -> 0 | C18: SUBCON | D18: 16.65 | E18: =B18*D18 -> 0
A19: Sukhjot Singh K | B19: ='OUTSIDE GTA'!F197 -> 0 | C19: SUBCON | D19: 16.65 | E19: =B19*D19 -> 0
A20: Gurbeer | B20: ='OUTSIDE GTA'!I197 -> 0 | C20: SUBCON | D20: 16.65 | E20: =B20*D20 -> 0
A22: Sheraton Four Points Cambridge (210 Preston Pkwy) | B22: =SUM(B12:B21) -> 0
A24: Holiday Inn Express Woodstock (510 Norwich Ave)
A25: Angel Ellan | B25: ='OUTSIDE GTA'!Q17 -> 0 | C25: SUBCON | D25: 17 | E25: =B25*D25 -> 0 | F25: Holiday Inn Express Woodstock (510 Norwich Ave)
A26: Menandro | B26: ='OUTSIDE GTA'!P17 -> 0 | C26: SUBCON | D26: 16.65 | E26: =B26*D26 -> 0 | F26: Holiday Inn Express Woodstock (510 Norwich Ave)
A28: Holiday Inn Express Woodstock (510 Norwich Ave) TOTAL: | B28: =SUM(B24:B27) -> 0
A30: Merland Park Cottages (12488 Loyalist Pkwy)
A31: Richard Canillas | B31: ='OUTSIDE GTA'!C270 -> 0 | C31: SUBCON | D31: 18 | E31: =B31*D31 -> 0
A32: Jeffrey | B32: ='OUTSIDE GTA'!D270 -> 0 | C32: SUBCON | D32: 18 | E32: =B32*D32 -> 0
A33: Rita Shalimar C. Aradillos | B33: ='OUTSIDE GTA'!E270 -> 0 | C33: SUBCON | D33: 18 | E33: =B33*D33 -> 0
A34: Gurpreet | B34: ='OUTSIDE GTA'!F270 -> 0 | C34: SUBCON | D34: 18 | E34: =B34*D34 -> 0
A35: Dikaran | B35: ='OUTSIDE GTA'!G270 -> 0 | C35: SUBCON | D35: 18 | E35: =B35*D35 -> 0
A37: Merland Park Cottages (12488 Loyalist Pkwy) TOTAL: | B37: =SUM(B30:B36) -> 0
A39: Tru by Hilton Bracebridge (320 Taylor Rd, Bracebridge)
A40: Armando | B40: ='OUTSIDE GTA'!C288 -> 0 | C40: SUBCON | D40: 16.65 | E40: =B40*D40 -> 0
A41: Shirley | B41: ='OUTSIDE GTA'!D288 -> 0 | C41: SUBCON | D41: 16.65 | E41: =B41*D41 -> 0
A43: Tru by Hilton Bracebridge (320 Taylor Rd, Bracebridge) | B43: =SUM(B39:B42) -> 0
A45: Home 2 by Hilton Woodstock (527 Lampman Pl)
A46: Menandro | B46: ='OUTSIDE GTA'!C35 -> 0 | C46: SUBCON | D46: 16.65 | E46: =B46*D46 -> 0 | F46: Home 2 by Hilton Woodstock (527 Lampman Pl)
A47: Jonervin Agustin | B47: ='OUTSIDE GTA'!D35 -> 0 | C47: SUBCON | D47: 16.65 | E47: =B47*D47 -> 0 | F47: Home 2 by Hilton Woodstock (527 Lampman Pl)
A48: Dhruvkumar Harshadkumar Patel | B48: ='OUTSIDE GTA'!E35 -> 0 | C48: SUBCON | D48: 16.65 | E48: =B48*D48 -> 0 | F48: Home 2 by Hilton Woodstock (527 Lampman Pl)
A49: Sukhjivan Singh | B49: ='OUTSIDE GTA'!F35 -> 0 | C49: SUBCON | D49: 16.65 | E49: =B49*D49 -> 0 | F49: Home 2 by Hilton Woodstock (527 Lampman Pl)
A50: Harkirat Singh | B50: ='OUTSIDE GTA'!H35 -> 0 | C50: SUBCON | D50: 16.65 | E50: =B50*D50 -> 0 | F50: Home 2 by Hilton Woodstock (527 Lampman Pl)
A51: Gagandeep Singh | B51: ='OUTSIDE GTA'!I35 -> 0 | C51: SUBCON | D51: 16.65 | E51: =B51*D51 -> 0 | F51: Home 2 by Hilton Woodstock (527 Lampman Pl)
A52: Casey Alexis Rapisura | B52: ='OUTSIDE GTA'!J35 -> 0 | C52: SUBCON | D52: 16.65 | E52: =B52*D52 -> 0 | F52: Home 2 by Hilton Woodstock (527 Lampman Pl)
A53: Azubike Emmanuel Eloka | B53: ='OUTSIDE GTA'!K35 -> 0 | C53: SUBCON | D53: 16.65 | E53: =B53*D53 -> 0 | F53: Home 2 by Hilton Woodstock (527 Lampman Pl)
A55: Home 2 by Hilton Woodstock (527 Lampman Pl) TOTAL: | B55: =SUM(B45:B54) -> 0
A57: Quality Inn & Suites Regina Downtown (1907 11th Ave)
A58: Harsh Vyas | B58: ='OUTSIDE GTA'!D125 -> 0 | C58: SUBCON | D58: 17 | E58: =B58*D58 -> 0 | F58: Quality Inn & Suites Regina Downtown (1907 11th Ave)
A59: Jenny Lyn Garcia Galapia (Paid) | B59: ='OUTSIDE GTA'!C125 -> 0 | C59: SUBCON | D59: 15.5 | E59: =B59*D59 -> 0 | F59: Quality Inn & Suites Regina Downtown (1907 11th Ave)
A60: Anastasiia Rostovtseva | B60: ='OUTSIDE GTA'!E125 -> 0 | C60: SUBCON | D60: 15.5 | E60: =B60*D60 -> 0 | F60: Quality Inn & Suites Regina Downtown (1907 11th Ave)
A61: Adwoa | B61: ='OUTSIDE GTA'!G125 -> 0 | C61: SUBCON | D61: 15.5 | E61: =B61*D61 -> 0 | F61: Quality Inn & Suites Regina Downtown (1907 11th Ave)
A63: Quality Inn & Suites Regina Downtown (1907 11th Ave) | B63: =SUM(B58:B62) -> 0
A65: Hidden Valley Resort Muskoka (1755 Valley Rd)
A66: Gabriel Aaron Ramos | B66: ='OUTSIDE GTA'!C71 -> 0 | C66: SUBCON | D66: 20 | E66: =B66*D66 -> 0 | F66: Hidden Valley Resort Muskoka (1755 Valley Rd)
A67: Mark G | B67: ='OUTSIDE GTA'!P71 -> 0 | C67: SUBCON | D67: 16.65 | E67: =B67*D67 -> 0 | F67: Hidden Valley Resort Muskoka (1755 Valley Rd)
A68: Jan Mayckie | B68: ='OUTSIDE GTA'!Q71 -> 0 | C68: SUBCON | D68: 16.65 | E68: =B68*D68 -> 0 | F68: Hidden Valley Resort Muskoka (1755 Valley Rd)
A69: Flordelyn (Kids Activities) | B69: ='OUTSIDE GTA'!T71 -> 0 | C69: SUBCON | D69: 16.65 | E69: =B69*D69 -> 0 | F69: Hidden Valley Resort Muskoka (1755 Valley Rd)
A70: Noralyn (Kids Activities) | B70: ='OUTSIDE GTA'!U71 -> 0 | C70: SUBCON | D70: 16.65 | E70: =B70*D70 -> 0 | F70: Hidden Valley Resort Muskoka (1755 Valley Rd)
A71: Roselle Navidad (HK) | B71: ='OUTSIDE GTA'!L71 -> 0 | C71: SUBCON | D71: 16.65 | E71: =B71*D71 -> 0 | F71: Hidden Valley Resort Muskoka (1755 Valley Rd)
A72: Flor (Maintenance) | B72: ='OUTSIDE GTA'!O71 -> 0 | C72: SUBCON | D72: 20 | E72: =B72*D72 -> 0 | F72: Hidden Valley Resort Muskoka (1755 Valley Rd)
A73: Wilson (Maintenance) | B73: ='OUTSIDE GTA'!R71 -> 0 | C73: SUBCON | D73: 20 | E73: =B73*D73 -> 0 | F73: Hidden Valley Resort Muskoka (1755 Valley Rd)
A74: Nelson (Maintenance) | B74: ='OUTSIDE GTA'!S71 -> 0 | C74: SUBCON | D74: 20 | E74: =B74*D74 -> 0 | F74: Hidden Valley Resort Muskoka (1755 Valley Rd)
A76: Hidden Valley Resort Muskoka (1755 Valley Rd) | B76: =SUM(B66:B75) -> 0
A78: BEST WESTERN PLUS MUSKOKA INN (86 HOWLAND DRIVE )
A79: Zayrah | B79: ='OUTSIDE GTA'!D143 -> 0 | C79: SUBCON | D79: 16.65 | E79: =B79*D79 -> 0 | F79: BEST WESTERN PLUS MUSKOKA INN (86 HOWLAND DRIVE )
A81: BEST WESTERN PLUS MUSKOKA INN (86 HOWLAND DRIVE ) | B81: =SUM(B79:B80) -> 0
A83: Spark by Hilton Woodstock (560 Norwich Ave)
A84: Veronica Wambo Mbugua | B84: ='OUTSIDE GTA'!C53 -> 0 | C84: SUBCON | D84: 16.65 | E84: =B84*D84 -> 0 | F84: Spark by Hilton Woodstock (560 Norwich Ave)
A85: Casey Alexis Rapisura | B85: ='OUTSIDE GTA'!I53 -> 0 | C85: SUBCON | D85: 16.65 | E85: =B85*D85 -> 0 | F85: Spark by Hilton Woodstock (560 Norwich Ave)
A86: Dianne Grace Rimando | B86: ='OUTSIDE GTA'!E53 -> 0 | C86: SUBCON | D86: 16.65 | E86: =B86*D86 -> 0 | F86: Spark by Hilton Woodstock (560 Norwich Ave)
A87: Elvira Diolazo | B87: ='OUTSIDE GTA'!G53 -> 0 | C87: SUBCON | D87: 16.65 | E87: =B87*D87 -> 0 | F87: Spark by Hilton Woodstock (560 Norwich Ave)
A88: Ramanjeep Chauhan | B88: ='OUTSIDE GTA'!H53 -> 0 | C88: SUBCON | D88: 16.65 | E88: =B88*D88 -> 0 | F88: Spark by Hilton Woodstock (560 Norwich Ave)
A89: Susan Omoghene | B89: ='OUTSIDE GTA'!N53 -> 0 | C89: SUBCON | D89: 16.65 | E89: =B89*D89 -> 0 | F89: Spark by Hilton Woodstock (560 Norwich Ave)
A90: Jennifer Uson | B90: ='OUTSIDE GTA'!M53 -> 0 | C90: SUBCON | D90: 16.65 | E90: =B90*D90 -> 0 | F90: Spark by Hilton Woodstock (560 Norwich Ave)
A91: Joseph Daniel Manapsal | B91: ='OUTSIDE GTA'!K53 -> 0 | C91: SUBCON | D91: 16.65 | E91: =B91*D91 -> 0 | F91: Spark by Hilton Woodstock (560 Norwich Ave)
A92: Gautam Gurung | B92: ='OUTSIDE GTA'!O53 -> 0 | C92: SUBCON | D92: 16.65 | E92: =B92*D92 -> 0 | F92: Spark by Hilton Woodstock (560 Norwich Ave)
A93: Harkirat Singh | B93: ='OUTSIDE GTA'!P53 -> 0 | C93: SUBCON | D93: 16.65 | E93: =B93*D93 -> 0 | F93: Spark by Hilton Woodstock (560 Norwich Ave)
A94: Chali Rizal | B94: ='OUTSIDE GTA'!Q53 -> 0 | C94: SUBCON | D94: 16.65 | E94: =B94*D94 -> 0 | F94: Spark by Hilton Woodstock (560 Norwich Ave)
A95: Voltaire John Buenaflor | B95: ='OUTSIDE GTA'!R53 -> 0 | C95: SUBCON | D95: 16.65 | E95: =B95*D95 -> 0 | F95: Spark by Hilton Woodstock (560 Norwich Ave)
A96: Julius Garcia | B96: ='OUTSIDE GTA'!S53 -> 0 | C96: SUBCON | D96: 16.65 | E96: =B96*D96 -> 0 | F96: Spark by Hilton Woodstock (560 Norwich Ave)
A97: Kafila | B97: ='OUTSIDE GTA'!L53 -> 0 | C97: SUBCON | D97: 16.65 | E97: =B97*D97 -> 0 | F97: Spark by Hilton Woodstock (560 Norwich Ave)
A98: Harpreet Harpreet | B98: ='OUTSIDE GTA'!T53 -> 0 | C98: SUBCON | D98: 16.65 | E98: =B98*D98 -> 0 | F98: Spark by Hilton Woodstock (560 Norwich Ave)
A99: Folashade Adekoya | B99: ='OUTSIDE GTA'!V53 -> 0 | C99: SUBCON | D99: 16.65 | E99: =B99*D99 -> 0 | F99: Spark by Hilton Woodstock (560 Norwich Ave)
A100: Santi Thapa | B100: ='OUTSIDE GTA'!X53 -> 0 | C100: SUBCON | D100: 16.65 | E100: =B100*D100 -> 0 | F100: Spark by Hilton Woodstock (560 Norwich Ave)
A101: Gurpreet K | B101: ='OUTSIDE GTA'!Y53 -> 0 | C101: SUBCON | D101: 16.65 | E101: =B101*D101 -> 0 | F101: Spark by Hilton Woodstock (560 Norwich Ave)
A102: Manpreet Singh | B102: ='OUTSIDE GTA'!Z53 -> 0 | C102: SUBCON | D102: 16.65 | E102: =B102*D102 -> 0 | F102: Spark by Hilton Woodstock (560 Norwich Ave)
A103: Jonervin Agustin | B103: ='OUTSIDE GTA'!AA53 -> 0 | C103: SUBCON | D103: 16.65 | E103: =B103*D103 -> 0 | F103: Spark by Hilton Woodstock (560 Norwich Ave)
A104: Woddy Rivera | B104: ='OUTSIDE GTA'!AC53 -> 0 | C104: SUBCON | D104: 16.65 | E104: =B104*D104 -> 0 | F104: Spark by Hilton Woodstock (560 Norwich Ave)
A105: Elmer Delos Reyes | B105: ='OUTSIDE GTA'!AB53 -> 0 | C105: SUBCON | D105: 16.65 | E105: =B105*D105 -> 0 | F105: Spark by Hilton Woodstock (560 Norwich Ave)
A107: Spark by Hilton Woodstock (560 Norwich Ave) TOTAL: | B107: =SUM(B83:B106) -> 0
A109: DAYS INN OTTAWA - DOWNTOWN (319 RIDEAU ST)
A110: Connex | B110: =OTTAWA!C54 -> 0 | C110: SUBCON | D110: 16.65 | E110: =B110*D110 -> 0
A111: Eunice | B111: =OTTAWA!D54 -> 0 | C111: SUBCON | D111: 16.65 | E111: =B111*D111 -> 0
A112: Vanessa | B112: =OTTAWA!E54 -> 0 | C112: SUBCON | D112: 16.65 | E112: =B112*D112 -> 0
A113: Etienne Maintenance | B113: =OTTAWA!F54 -> 0 | C113: SUBCON | D113: 20 | E113: =B113*D113 -> 0
A115: DAYS INN OTTAWA - DOWNTOWN (319 RIDEAU ST) | B115: =SUM(B109:B114) -> 0
A117: Best Western Plus Ottawa (1876 Robertson Rd)
A118: Abdullahi Abdi Hirsi | B118: =OTTAWA!D18 -> 0 | C118: SUBCON | D118: 16.65 | E118: =B118*D118 -> 0
A119: Binta | B119: =OTTAWA!C18 -> 0 | C119: SUBCON | D119: 16.65 | E119: =B119*D119 -> 0
A120: Bernard | B120: =OTTAWA!E18 -> 0 | C120: SUBCON | D120: 16.65 | E120: =B120*D120 -> 0
A121: Brenda | B121: =OTTAWA!F18 -> 0 | C121: SUBCON | D121: 16.65 | E121: =B121*D121 -> 0
A122: Carive Dialakana Bahenga | B122: =OTTAWA!G18 -> 0 | C122: SUBCON | D122: 16.65 | E122: =B122*D122 -> 0
A123: Claudine Uwituze | B123: =OTTAWA!H18 -> 0 | C123: SUBCON | D123: 16.65 | E123: =B123*D123 -> 0
A124: Cleine | B124: =OTTAWA!I18 -> 0 | C124: SUBCON | D124: 16.65 | E124: =B124*D124 -> 0
...

Sheet Summary Hotel
A1: Hotel
A2: BEST WESTERN PLUS OTTAWA (1876 ROBERTSON RD)
A3: =MMJ!B1 -> PAY PERIOD January 10 - 23, 2025 | B3: HOURS | C3: TYPE | D3: RATE | E3: TOTAL | F3: Hotel | G3: Etransfer
G4: =VLOOKUP(A4,'[1]Interac Details'!$A:$B, 2, FALSE) -> 0
G5: =VLOOKUP(A5,'[1]Interac Details'!$A:$B, 2, FALSE) -> 0
G6: =VLOOKUP(A6,'[1]Interac Details'!$A:$B, 2, FALSE) -> 0
G7: =VLOOKUP(A7,'[1]Interac Details'!$A:$B, 2, FALSE) -> 0
G8: =VLOOKUP(A8,'[1]Interac Details'!$A:$B, 2, FALSE) -> 0
G9: =VLOOKUP(A9,'[1]Interac Details'!$A:$B, 2, FALSE) -> 0
G10: =VLOOKUP(A10,'[1]Interac Details'!$A:$B, 2, FALSE) -> 0
G11: =VLOOKUP(A11,'[1]Interac Details'!$A:$B, 2, FALSE) -> 0
G12: =VLOOKUP(A12,'[1]Interac Details'!$A:$B, 2, FALSE) -> 0
G13: =VLOOKUP(A13,'[1]Interac Details'!$A:$B, 2, FALSE) -> 0
G14: =VLOOKUP(A14,'[1]Interac Details'!$A:$B, 2, FALSE) -> 0
G15: =VLOOKUP(A15,'[1]Interac Details'!$A:$B, 2, FALSE) -> 0
... G17: =VLOOKUP(A17,'[1]Interac Details'!$A:$B, 2, FALSE) -> 0
B19: Total | D19: =SUM(E4:E17) -> 0 | H19: =D19 -> 0
A20: DAYS INN OTTAWA WEST (350 MOODIE DR, OTTAWA)
A21: =A3 -> PAY PERIOD January 10 - 23, 2025 | B21: HOURS | C21: TYPE | D21: RATE | E21: TOTAL | F21: Hotel | G21: Etransfer
G22: =VLOOKUP(A22,'[1]Interac Details'!$A:$B, 2, FALSE) -> 0
G23: =VLOOKUP(A23,'[1]Interac Details'!$A:$B, 2, FALSE) -> 0
G24: =VLOOKUP(A24,'[1]Interac Details'!$A:$B, 2, FALSE) -> 0
G25: =VLOOKUP(A25,'[1]Interac Details'!$A:$B, 2, FALSE) -> 0
G26: =VLOOKUP(A26,'[1]Interac Details'!$A:$B, 2, FALSE) -> 0
G27: =VLOOKUP(A27,'[1]Interac Details'!$A:$B, 2, FALSE) -> 0
G28: =VLOOKUP(A28,'[1]Interac Details'!$A:$B, 2, FALSE) -> 0
G29: =VLOOKUP(A29,'[1]Interac Details'!$A:$B, 2, FALSE) -> 0
G30: =VLOOKUP(A30,'[1]Interac Details'!$A:$B, 2, FALSE) -> 0
G31: =VLOOKUP(A31,'[1]Interac Details'!$A:$B, 2, FALSE) -> 0
G32: =VLOOKUP(A32,'[1]Interac Details'!$A:$B, 2, FALSE) -> 0
G33: =VLOOKUP(A33,'[1]Interac Details'!$A:$B, 2, FALSE) -> 0
G34: =VLOOKUP(A34,'[1]Interac Details'!$A:$B, 2, FALSE) -> 0
B36: Total | D36: =SUM(E22:E35) -> 0 | H36: =D36 -> 0
A37: EDWARD HOTEL (185 YORKLAND BLVD NORTH YORK)
A38: =A3 -> PAY PERIOD January 10 - 23, 2025 | B38: HOURS | C38: TYPE | D38: RATE | E38: TOTAL | F38: Hotel | G38: Etransfer
G39: =VLOOKUP(A39,'Interac Details'!A:B, 2, FALSE) -> 0
G40: =VLOOKUP(A40,'Interac Details'!A:B, 2, FALSE) -> 0
B43: Total | D43: =SUM(E39:E41) -> 0
A45: HOLIDAY INN EXPRESS - RICHMOND HILL
A46: =A3 -> PAY PERIOD January 10 - 23, 2025 | B46: HOURS | C46: TYPE | D46: RATE | E46: TOTAL | G46: Etransfer
A47: Andrew Verches | B47: 82 | C47: SUBCON | D47: 16.65 | E47: 1365.3 | F47: Holiday Inn Express Richmond Hill (10 East Pearce St) | G47: verchesandrew@yahoo.com
A48: Paxson Intal Figueroa | B48: 78.5 | C48: SUBCON | D48: 16.65 | E48: 1307.025 | F48: Holiday Inn Express Richmond Hill (10 East Pearce St) | G48: paxsonfig09@gmail.com
B50: Total | D50: =SUM(E47:E48) -> 2672.325 | H50: =D50 -> 2672.325
A51: RADISSON (55 HALLCROWN PL, NORTH YORK)
A52: =A3 -> PAY PERIOD January 10 - 23, 2025 | B52: HOURS | C52: TYPE | D52: RATE | E52: TOTAL | F52: Hotel | G52: Etransfer
G53: =VLOOKUP(A53,'[1]Interac Details'!$A:$B, 2, FALSE) -> 0
G54: =VLOOKUP(A54,'[1]Interac Details'!$A:$B, 2, FALSE) -> 0
B56: Total | D56: =SUM(E53:E54) -> 0 | H56: =D56 -> 0
A58: Holiday Inn Express WOODSTOCK (510 Norwich Ave)
A59: =A3 -> PAY PERIOD January 10 - 23, 2025 | B59: HOURS | C59: TYPE | D59: RATE | E59: TOTAL | F59: Hotel | G59: Etransfer
A60: Michelle Enriquez | G60: =VLOOKUP(A60,'[1]Interac Details'!$A:$B, 2, FALSE) -> ellehci_m@yahoo.com.ph
A61: Herbert | G61: =VLOOKUP(A61,'[1]Interac Details'!$A:$B, 2, FALSE) -> ellehci_m@yahoo.com.ph
B64: Total | D64: =SUM(E60:E61) -> 0 | H64: =D64 -> 0
A66: Home 2 Hotel Woodstock (527 Lampman Pl)
A67: =A3 -> PAY PERIOD January 10 - 23, 2025 | B67: HOURS | C67: TYPE | D67: RATE | E67: TOTAL | F67: Hotel | G67: Etransfer
A68: Catherine Martin | G68: =VLOOKUP(A68,'[1]Interac Details'!$A:$B, 2, FALSE) -> cathypundz@gmail.com
B70: Total | D70: =SUM(E68:E68) -> 0 | H70: =D70 -> 0
A72: SHERATON FOUR POINTS - CAMBRIDGE
A73: =A3 -> PAY PERIOD January 10 - 23, 2025 | B73: HOURS | C73: TYPE | D73: RATE | E73: TOTAL | F73: Hotel | G73: Etransfer
B78: Total | D78: =SUM(E74:E76) -> 0 | H78: =D78 -> 0
A81: Spark by Hilton Woodstock
A82: =A3 -> PAY PERIOD January 10 - 23, 2025 | B82: HOURS | C82: TYPE | D82: RATE | E82: TOTAL | F82: Hotel | G82: Etransfer
A83: Adejumo Kehinde - Paid | G83: adejumokehinde804@gmail.com
A84: Isaac Hunter | G84: =VLOOKUP(A84, [2]!Table4[[Name]:[Interac Email Final]], 3, FALSE) -> #REF!
A85: Parimal N Naik | G85: =VLOOKUP(A85, [2]!Table4[[Name]:[Interac Email Final]], 3, FALSE) -> #REF!
A86: Sivakumar Vinoth | G86: =VLOOKUP(A86, [2]!Table4[[Name]:[Interac Email Final]], 3, FALSE) -> #REF!
A87: Dionisio Caro | G87: =VLOOKUP(A87, [2]!Table4[[Name]:[Interac Email Final]], 3, FALSE) -> #REF!
B89: Total | D89: =SUM(E83:E87) -> 0 | H89: =D89 -> 0
A91: Hampton Inn Midland (877 King St)
A92: =A3 -> PAY PERIOD January 10 - 23, 2025 | B92: HOURS | C92: TYPE | D92: RATE | E92: TOTAL | F92: Hotel | G92: Etransfer
B97: Total | D97: =SUM(E93:E95) -> 0 | H97: =D97 -> 0
A99: Ramada by Wyndham Niagara Falls by the River (4357 River Rd)
A100: =A3 -> PAY PERIOD January 10 - 23, 2025 | B100: HOURS | C100: TYPE | D100: RATE | E100: TOTAL | F100: Hotel | G100: Etransfer
B103: Total | D103: =SUM(E101:E101) -> 0 | H103: =D103 -> 0
A105: Quality Inn & Suites Regina Downtown (1907 11th Ave, Regina, SK S4P 0J2)
A106: =A3 -> PAY PERIOD January 10 - 23, 2025 | B106: HOURS | C106: TYPE | D106: RATE | E106: TOTAL | F106: Hotel | G106: Etransfer
A107: Omoyele Oluwatimilehen Success | G107: =VLOOKUP(A107,'[1]Interac Details'!$A:$B, 2, FALSE) -> Omoyeletimi03@gmail.com
B110: Total | D110: =SUM(E107:E108) -> 0 | H110: =D110 -> 0
A111: Hidden Valley Resort 1755 Valley Rd, Huntsville, ON P1H 1A8
A112: =A3 -> PAY PERIOD January 10 - 23, 2025 | B112: HOURS | C112: TYPE | D112: RATE | E112: TOTAL | F112: Hotel | G112: Etransfer
A113: Armstrong (Cook) | F113: Hidden Valley Resort Muskoka (1755 Valley Rd) | G113: =VLOOKUP(A113, [3]!Table4[[Name]:[Interac Email Final]], 3, FALSE) -> #REF!
A114: Rhandolp Carl Reyes | F114: Hidden Valley Resort Muskoka (1755 Valley Rd) | G114: =VLOOKUP(A114, [3]!Table4[[Name]:[Interac Email Final]], 3, FALSE) -> #REF!
A115: Flor M | F115: Hidden Valley Resort Muskoka (1755 Valley Rd) | G115: =VLOOKUP(A115, [3]!Table4[[Name]:[Interac Email Final]], 3, FALSE) -> #REF!
A116: Flordelyn (Cook) | F116: Hidden Valley Resort Muskoka (1755 Valley Rd) | G116: =VLOOKUP(A116, [3]!Table4[[Name]:[Interac Email Final]], 3, FALSE) -> #REF!
A117: Flordelyn (HK) | F117: Hidden Valley Resort Muskoka (1755 Valley Rd) | G117: =VLOOKUP(A117, [3]!Table4[[Name]:[Interac Email Final]], 3, FALSE) -> #REF!
A118: Gerald Policarpio | F118: Hidden Valley Resort Muskoka (1755 Valley Rd) | G118: =VLOOKUP(A118, [3]!Table4[[Name]:[Interac Email Final]], 3, FALSE) -> #REF!
A119: Jennylyn Ceniza | F119: Hidden Valley Resort Muskoka (1755 Valley Rd) | G119: =VLOOKUP(A119, [3]!Table4[[Name]:[Interac Email Final]], 3, FALSE) -> #REF!
A120: Noralyn Torre Camiguing | F120: Hidden Valley Resort Muskoka (1755 Valley Rd) | G120: =VLOOKUP(A120, [3]!Table4[[Name]:[Interac Email Final]], 3, FALSE) -> #REF!
A121: Sheila/Rey | F121: Hidden Valley Resort Muskoka (1755 Valley Rd) | G121: =VLOOKUP(A121, [3]!Table4[[Name]:[Interac Email Final]], 3, FALSE) -> #REF!
B123: Total | D123: =SUM(E113:E122) -> 0 | H123: =D123 -> 0
A124: Quebec (Monica Gupta)
A125: =A3 -> PAY PERIOD January 10 - 23, 2025 | B125: HOURS | C125: TYPE | D125: RATE | E125: TOTAL | F125: Hotel | G125: Etransfer
B129: Total | D129: =SUM(E126:E127) -> 0
A132: Chatham Kent
A133: =A3 -> PAY PERIOD January 10 - 23, 2025 | B133: HOURS | C133: TYPE | D133: RATE | E133: TOTAL | F133: Hotel | G133: Etransfer
A134: Akin Babalola | G134: =VLOOKUP(A134, [2]!Table4[[Name]:[Interac Email Final]], 3, FALSE) -> #REF!
A135: Asmita Baral | G135: =VLOOKUP(A135, [2]!Table4[[Name]:[Interac Email Final]], 3, FALSE) -> #REF!
A136: MC PAINTING AND CLEANING SERVICES (Delmi) | G136: =VLOOKUP(A136, [2]!Table4[[Name]:[Interac Email Final]], 3, FALSE) -> #REF!
A137: Ikponmwosa Evelyn Ogbegie | G137: =VLOOKUP(A137, [2]!Table4[[Name]:[Interac Email Final]], 3, FALSE) -> #REF!
A138: Glenn Uy | G138: =VLOOKUP(A138, [2]!Table4[[Name]:[Interac Email Final]], 3, FALSE) -> #REF!
...

Sheet SUBCON (3)
A1: PAY PERIOD September 20 - October 3, 2025 | B1: HOURS | C1: TYPE | D1: RATE | E1: TOTAL | F1: HOTEL
A2: Best Western Plus Scarborough (38 Estate Dr)
A3: Penina Nyanchoka Mang'era | B3: =GTA!F201 -> 0 | C3: SUBCON | D3: 16.65 | E3: =B3*D3 -> 0
A5: Best Western Plus Scarborough (38 Estate Dr) TOTAL: | B5: =SUM(B2:B4) -> 0
A7: Maple Hotels
A8: Sunshine Padilla Rebadulla (Printed on Monthly) | B8: =OTTAWA!C72 -> 0 | C8: SUBCON | D8: 18 | E8: =B8*D8 -> 0
A10: Maple Hotels TOTAL: | B10: =SUM(B7:B9) -> 0
A12: Sheraton Four Points Cambridge (210 Preston Pkwy)
A13: Joshua Agorilla | B13: ='OUTSIDE GTA'!C197 -> 0 | C13: SUBCON | D13: 16.65 | E13: =B13*D13 -> 0
A14: Aakash | B14: ='OUTSIDE GTA'!J197 -> 0 | C14: SUBCON | D14: 16.65 | E14: =B14*D14 -> 0
A15: Meet Vanraj Mahida | B15: ='OUTSIDE GTA'!G197 -> 0 | C15: SUBCON | D15: 16.65 | E15: =B15*D15 -> 0
A16: Satnam Singh | B16: ='OUTSIDE GTA'!E197 -> 0 | C16: SUBCON | D16: 16.65 | E16: =B16*D16 -> 0
A17: Sukhjot Singh | B17: ='OUTSIDE GTA'!D197 -> 0 | C17: SUBCON | D17: 16.65 | E17: =B17*D17 -> 0
A18: Rahul | B18: ='OUTSIDE GTA'!H197 -> 0 | C18: SUBCON | D18: 16.65 | E18: =B18*D18 -> 0
A19: Sukhjot Singh K | B19: ='OUTSIDE GTA'!F197 -> 0 | C19: SUBCON | D19: 16.65 | E19: =B19*D19 -> 0
A20: Gurbeer | B20: ='OUTSIDE GTA'!I197 -> 0 | C20: SUBCON | D20: 16.65 | E20: =B20*D20 -> 0
A22: Sheraton Four Points Cambridge (210 Preston Pkwy) | B22: =SUM(B12:B21) -> 0
A24: Holiday Inn Express Woodstock (510 Norwich Ave)
A25: Lyka | B25: ='OUTSIDE GTA'!C143 -> 0 | C25: SUBCON | D25: 20 | E25: =B25*D25 -> 0 | F25: BEST WESTERN PLUS MUSKOKA INN (86 HOWLAND DRIVE )
A26: Angel Ellan | B26: ='OUTSIDE GTA'!Q17 -> 0 | C26: SUBCON | D26: 17 | E26: =B26*D26 -> 0 | F26: Holiday Inn Express Woodstock (510 Norwich Ave)
A27: Menandro | B27: ='OUTSIDE GTA'!P17 -> 0 | C27: SUBCON | D27: 16.65 | E27: =B27*D27 -> 0 | F27: Holiday Inn Express Woodstock (510 Norwich Ave)
A28: Akin | B28: ='OUTSIDE GTA'!C107 -> 0 | C28: SUBCON | D28: 16.65 | E28: =B28*D28 -> 0 | F28: Chatham Kent
A30: Holiday Inn Express Woodstock (510 Norwich Ave) TOTAL: | B30: =SUM(B24:B29) -> 0
A32: Merland Park Cottages (12488 Loyalist Pkwy)
A33: Richard Canillas | B33: ='OUTSIDE GTA'!C270 -> 0 | C33: SUBCON | D33: 18 | E33: =B33*D33 -> 0
A34: Jeffrey | B34: ='OUTSIDE GTA'!D270 -> 0 | C34: SUBCON | D34: 18 | E34: =B34*D34 -> 0
A35: Rita Shalimar C. Aradillos | B35: ='OUTSIDE GTA'!E270 -> 0 | C35: SUBCON | D35: 18 | E35: =B35*D35 -> 0
A36: Gurpreet | B36: ='OUTSIDE GTA'!F270 -> 0 | C36: SUBCON | D36: 18 | E36: =B36*D36 -> 0
A37: Dikaran | B37: ='OUTSIDE GTA'!G270 -> 0 | C37: SUBCON | D37: 18 | E37: =B37*D37 -> 0
A39: Merland Park Cottages (12488 Loyalist Pkwy) TOTAL: | B39: =SUM(B32:B38) -> 0
A41: Tru by Hilton Bracebridge (320 Taylor Rd, Bracebridge)
A42: Armando | B42: ='OUTSIDE GTA'!C288 -> 0 | C42: SUBCON | D42: 16.65 | E42: =B42*D42 -> 0
A43: Shirley | B43: ='OUTSIDE GTA'!D288 -> 0 | C43: SUBCON | D43: 16.65 | E43: =B43*D43 -> 0
A45: Tru by Hilton Bracebridge (320 Taylor Rd, Bracebridge) | B45: =SUM(B41:B44) -> 0
A47: Home 2 by Hilton Woodstock (527 Lampman Pl)
A48: Menandro | B48: ='OUTSIDE GTA'!C35 -> 0 | C48: SUBCON | D48: 16.65 | E48: =B48*D48 -> 0 | F48: Home 2 by Hilton Woodstock (527 Lampman Pl)
A49: Asmita | B49: ='OUTSIDE GTA'!D107 -> 0 | C49: SUBCON | D49: 16.65 | E49: =B49*D49 -> 0 | F49: Chatham Kent
A50: Jonervin Agustin | B50: ='OUTSIDE GTA'!D35 -> 0 | C50: SUBCON | D50: 16.65 | E50: =B50*D50 -> 0 | F50: Home 2 by Hilton Woodstock (527 Lampman Pl)
A51: Dhruvkumar Harshadkumar Patel | B51: ='OUTSIDE GTA'!E35 -> 0 | C51: SUBCON | D51: 16.65 | E51: =B51*D51 -> 0 | F51: Home 2 by Hilton Woodstock (527 Lampman Pl)
A52: Sukhjivan Singh | B52: ='OUTSIDE GTA'!F35 -> 0 | C52: SUBCON | D52: 16.65 | E52: =B52*D52 -> 0 | F52: Home 2 by Hilton Woodstock (527 Lampman Pl)
A53: Harkirat Singh | B53: ='OUTSIDE GTA'!H35 -> 0 | C53: SUBCON | D53: 16.65 | E53: =B53*D53 -> 0 | F53: Home 2 by Hilton Woodstock (527 Lampman Pl)
A54: Gagandeep Singh | B54: ='OUTSIDE GTA'!I35 -> 0 | C54: SUBCON | D54: 16.65 | E54: =B54*D54 -> 0 | F54: Home 2 by Hilton Woodstock (527 Lampman Pl)
A55: Casey Alexis Rapisura | B55: ='OUTSIDE GTA'!J35 -> 0 | C55: SUBCON | D55: 16.65 | E55: =B55*D55 -> 0 | F55: Home 2 by Hilton Woodstock (527 Lampman Pl)
A56: Azubike Emmanuel Eloka | B56: ='OUTSIDE GTA'!K35 -> 0 | C56: SUBCON | D56: 16.65 | E56: =B56*D56 -> 0 | F56: Home 2 by Hilton Woodstock (527 Lampman Pl)
A58: Home 2 by Hilton Woodstock (527 Lampman Pl) TOTAL: | B58: =SUM(B47:B57) -> 0
A60: Quality Inn & Suites Regina Downtown (1907 11th Ave) | F60: Quality Inn & Suites Regina Downtown (1907 11th Ave)
A61: Harsh Vyas | B61: ='OUTSIDE GTA'!D125 -> 0 | C61: SUBCON | D61: 17 | E61: =B61*D61 -> 0 | F61: Quality Inn & Suites Regina Downtown (1907 11th Ave)
A62: Jenny Lyn Garcia Galapia (Paid) | B62: ='OUTSIDE GTA'!C125 -> 0 | C62: SUBCON | D62: 15.5 | E62: =B62*D62 -> 0 | F62: Quality Inn & Suites Regina Downtown (1907 11th Ave)
A63: Anastasiia Rostovtseva | B63: ='OUTSIDE GTA'!E125 -> 0 | C63: SUBCON | D63: 15.5 | E63: =B63*D63 -> 0 | F63: Quality Inn & Suites Regina Downtown (1907 11th Ave)
A64: MC PAINTING AND CLEANING SERVICES (Delmi) | B64: ='OUTSIDE GTA'!E107 -> 0 | C64: SUBCON | D64: 18 | E64: =B64*D64 -> 0 | F64: Chatham Kent
A65: Adwoa | B65: ='OUTSIDE GTA'!G125 -> 0 | C65: SUBCON | D65: 15.5 | E65: =B65*D65 -> 0 | F65: Quality Inn & Suites Regina Downtown (1907 11th Ave)
A67: Quality Inn & Suites Regina Downtown (1907 11th Ave) | B67: =SUM(B61:B66) -> 0
A69: Hidden Valley Resort Muskoka (1755 Valley Rd)
A70: Gabriel Aaron Ramos | B70: ='OUTSIDE GTA'!C71 -> 0 | C70: SUBCON | D70: 20 | E70: =B70*D70 -> 0 | F70: Hidden Valley Resort Muskoka (1755 Valley Rd)
A71: Evelyn Ogbegie | B71: ='OUTSIDE GTA'!F107 -> 0 | C71: SUBCON | D71: 16.65 | E71: =B71*D71 -> 0 | F71: Chatham Kent
A72: Glenn | B72: ='OUTSIDE GTA'!G107 -> 0 | C72: SUBCON | D72: 16.65 | E72: =B72*D72 -> 0 | F72: Chatham Kent
A73: Harshdeep Singh | B73: ='OUTSIDE GTA'!H107 -> 0 | C73: SUBCON | D73: 16.65 | E73: =B73*D73 -> 0 | F73: Chatham Kent
A74: Julie Jane Pamunag | B74: ='OUTSIDE GTA'!I107 -> 0 | C74: SUBCON | D74: 16.65 | E74: =B74*D74 -> 0 | F74: Chatham Kent
A75: MC PAINTING AND CLEANING SERVICES (Karen Vera) | B75: ='OUTSIDE GTA'!J107 -> 0 | C75: SUBCON | D75: 18 | E75: =B75*D75 -> 0 | F75: Chatham Kent
A76: Komalpreet Kaur | B76: ='OUTSIDE GTA'!K107 -> 0 | C76: SUBCON | D76: 16.65 | E76: =B76*D76 -> 0 | F76: Chatham Kent
A77: Mark G | B77: ='OUTSIDE GTA'!P71 -> 0 | C77: SUBCON | D77: 16.65 | E77: =B77*D77 -> 0 | F77: Hidden Valley Resort Muskoka (1755 Valley Rd)
A78: Khushdeep | B78: ='OUTSIDE GTA'!L107 -> 0 | C78: SUBCON | D78: 16.65 | E78: =B78*D78 -> 0 | F78: Chatham Kent
A79: Jan Mayckie | B79: ='OUTSIDE GTA'!Q71 -> 0 | C79: SUBCON | D79: 16.65 | E79: =B79*D79 -> 0 | F79: Hidden Valley Resort Muskoka (1755 Valley Rd)
A80: MC PAINTING AND CLEANING SERVICES (Mercedes) | B80: ='OUTSIDE GTA'!M107 -> 0 | C80: SUBCON | D80: 18 | E80: =B80*D80 -> 0 | F80: Chatham Kent
A81: Namandeep Kaur | B81: ='OUTSIDE GTA'!N107 -> 0 | C81: SUBCON | D81: 16.65 | E81: =B81*D81 -> 0 | F81: Chatham Kent
A82: Flordelyn (Kids Activities) | B82: ='OUTSIDE GTA'!T71 -> 0 | C82: SUBCON | D82: 16.65 | E82: =B82*D82 -> 0 | F82: Hidden Valley Resort Muskoka (1755 Valley Rd)
A83: Noralyn (Kids Activities) | B83: ='OUTSIDE GTA'!U71 -> 0 | C83: SUBCON | D83: 16.65 | E83: =B83*D83 -> 0 | F83: Hidden Valley Resort Muskoka (1755 Valley Rd)
A84: Princess Montemayor | B84: ='OUTSIDE GTA'!O107 -> 0 | C84: SUBCON | D84: 16.65 | E84: =B84*D84 -> 0 | F84: Chatham Kent
A85: Roselle Navidad (HK) | B85: ='OUTSIDE GTA'!L71 -> 0 | C85: SUBCON | D85: 16.65 | E85: =B85*D85 -> 0 | F85: Hidden Valley Resort Muskoka (1755 Valley Rd)
A86: Flor (Maintenance) | B86: ='OUTSIDE GTA'!O71 -> 0 | C86: SUBCON | D86: 20 | E86: =B86*D86 -> 0 | F86: Hidden Valley Resort Muskoka (1755 Valley Rd)
A87: Wilson (Maintenance) | B87: ='OUTSIDE GTA'!R71 -> 0 | C87: SUBCON | D87: 20 | E87: =B87*D87 -> 0 | F87: Hidden Valley Resort Muskoka (1755 Valley Rd)
A88: Nelson (Maintenance) | B88: ='OUTSIDE GTA'!S71 -> 0 | C88: SUBCON | D88: 20 | E88: =B88*D88 -> 0 | F88: Hidden Valley Resort Muskoka (1755 Valley Rd)
A90: Hidden Valley Resort Muskoka (1755 Valley Rd) | B90: =SUM(B70:B89) -> 0
A92: BEST WESTERN PLUS MUSKOKA INN (86 HOWLAND DRIVE )
A93: Riza | B93: ='OUTSIDE GTA'!P107 -> 0 | C93: SUBCON | D93: 16.65 | E93: =B93*D93 -> 0 | F93: Chatham Kent
A94: Zayrah | B94: ='OUTSIDE GTA'!D143 -> 0 | C94: SUBCON | D94: 16.65 | E94: =B94*D94 -> 0 | F94: BEST WESTERN PLUS MUSKOKA INN (86 HOWLAND DRIVE )
A96: BEST WESTERN PLUS MUSKOKA INN (86 HOWLAND DRIVE ) | B96: =SUM(B93:B95) -> 0
A98: Spark by Hilton Woodstock (560 Norwich Ave)
A99: Veronica Wambo Mbugua | B99: ='OUTSIDE GTA'!C53 -> 0 | C99: SUBCON | D99: 16.65 | E99: =B99*D99 -> 0 | F99: Spark by Hilton Woodstock (560 Norwich Ave)
A100: Rodel Santos | B100: ='OUTSIDE GTA'!Q107 -> 0 | C100: SUBCON | D100: 16.65 | E100: =B100*D100 -> 0 | F100: Chatham Kent
A101: Casey Alexis Rapisura | B101: ='OUTSIDE GTA'!I53 -> 0 | C101: SUBCON | D101: 16.65 | E101: =B101*D101 -> 0 | F101: Spark by Hilton Woodstock (560 Norwich Ave)
A102: Dianne Grace Rimando | B102: ='OUTSIDE GTA'!E53 -> 0 | C102: SUBCON | D102: 16.65 | E102: =B102*D102 -> 0 | F102: Spark by Hilton Woodstock (560 Norwich Ave)
A103: Elvira Diolazo | B103: ='OUTSIDE GTA'!G53 -> 0 | C103: SUBCON | D103: 16.65 | E103: =B103*D103 -> 0 | F103: Spark by Hilton Woodstock (560 Norwich Ave)
A104: Ramanjeep Chauhan | B104: ='OUTSIDE GTA'!H53 -> 0 | C104: SUBCON | D104: 16.65 | E104: =B104*D104 -> 0 | F104: Spark by Hilton Woodstock (560 Norwich Ave)
A105: Susan Omoghene | B105: ='OUTSIDE GTA'!N53 -> 0 | C105: SUBCON | D105: 16.65 | E105: =B105*D105 -> 0 | F105: Spark by Hilton Woodstock (560 Norwich Ave)
A106: Jennifer Uson | B106: ='OUTSIDE GTA'!M53 -> 0 | C106: SUBCON | D106: 16.65 | E106: =B106*D106 -> 0 | F106: Spark by Hilton Woodstock (560 Norwich Ave)
A107: Joseph Daniel Manapsal | B107: ='OUTSIDE GTA'!K53 -> 0 | C107: SUBCON | D107: 16.65 | E107: =B107*D107 -> 0 | F107: Spark by Hilton Woodstock (560 Norwich Ave)
A108: Gautam Gurung | B108: ='OUTSIDE GTA'!O53 -> 0 | C108: SUBCON | D108: 16.65 | E108: =B108*D108 -> 0 | F108: Spark by Hilton Woodstock (560 Norwich Ave)
A109: Harkirat Singh | B109: ='OUTSIDE GTA'!P53 -> 0 | C109: SUBCON | D109: 16.65 | E109: =B109*D109 -> 0 | F109: Spark by Hilton Woodstock (560 Norwich Ave)
A110: Chali Rizal | B110: ='OUTSIDE GTA'!Q53 -> 0 | C110: SUBCON | D110: 16.65 | E110: =B110*D110 -> 0 | F110: Spark by Hilton Woodstock (560 Norwich Ave)
A111: Voltaire John Buenaflor | B111: ='OUTSIDE GTA'!R53 -> 0 | C111: SUBCON | D111: 16.65 | E111: =B111*D111 -> 0 | F111: Spark by Hilton Woodstock (560 Norwich Ave)
A112: Julius Garcia | B112: ='OUTSIDE GTA'!S53 -> 0 | C112: SUBCON | D112: 16.65 | E112: =B112*D112 -> 0 | F112: Spark by Hilton Woodstock (560 Norwich Ave)
A113: Kafila | B113: ='OUTSIDE GTA'!L53 -> 0 | C113: SUBCON | D113: 16.65 | E113: =B113*D113 -> 0 | F113: Spark by Hilton Woodstock (560 Norwich Ave)
A114: Harpreet Harpreet | B114: ='OUTSIDE GTA'!T53 -> 0 | C114: SUBCON | D114: 16.65 | E114: =B114*D114 -> 0 | F114: Spark by Hilton Woodstock (560 Norwich Ave)
A115: Folashade Adekoya | B115: ='OUTSIDE GTA'!V53 -> 0 | C115: SUBCON | D115: 16.65 | E115: =B115*D115 -> 0 | F115: Spark by Hilton Woodstock (560 Norwich Ave)
A116: Santi Thapa | B116: ='OUTSIDE GTA'!X53 -> 0 | C116: SUBCON | D116: 16.65 | E116: =B116*D116 -> 0 | F116: Spark by Hilton Woodstock (560 Norwich Ave)
A117: Gurpreet K | B117: ='OUTSIDE GTA'!Y53 -> 0 | C117: SUBCON | D117: 16.65 | E117: =B117*D117 -> 0 | F117: Spark by Hilton Woodstock (560 Norwich Ave)
A118: Rupinder Singh | B118: ='OUTSIDE GTA'!R107 -> 0 | C118: SUBCON | D118: 16.65 | E118: =B118*D118 -> 0 | F118: Chatham Kent
A119: Manpreet Singh | B119: ='OUTSIDE GTA'!Z53 -> 0 | C119: SUBCON | D119: 16.65 | E119: =B119*D119 -> 0 | F119: Spark by Hilton Woodstock (560 Norwich Ave)
A120: Virgelio Magna | B120: ='OUTSIDE GTA'!S107 -> 0 | C120: SUBCON | D120: 16.65 | E120: =B120*D120 -> 0 | F120: Chatham Kent
...

Sheet Subcontractors
A1: ID | B1: Name | C1: Physical Address | D1: Interac Email Final | E1: Phone Number | F1: Alias | G1: Comment | H1: Mail or Pickup | I1: Column1 | J1: Column2
A2: MMJW0001 | B2: Danica Lauzon | C2: 1055A Forestwood Dr, Mississauga, ON L5C 2T8 | D2: lauzon_danica@yahoo.com | F2: Kenneth Abarra | G2: For Kenneth Abarra | H2: (PICK UP)
A3: MMJW0002 | B3: Noralyn Torre Camiguing | C3: 132 Holditch St, Bracebridge, ON P1L 1E7 | D3: jaysoncamiguing@gmail.com | E3: 164 744 8102 | G3: delayed salary | H3: #N/A
A4: MMJW0003 | B4: Anthony Baslot | C4: #204 565 Manchester Rd, Victoria, BC V8T 2N7 | D4: shielaann.baslot@yahoo.com | E4: 204 990 4956 | H4: #N/A
A5: MMJW0004 | B5: Michelle Curit | C5: 426 Huron St, Woodstock, ON N4S 7A7 | D5: michelle_sarabosing@yahoo.com | E5: 226 219 9521 | H5: #N/A
A6: MMJW0005 | B6: Herbert Centeno | C6: 110 Windermere Crescent, Woodstock, ON N4S 6T2 | D6: ellehci_m@yahoo.com.ph | E6: 226 228 4590 | G6: Forward to Michelle Enriquez | H6: E-transfer
A7: MMJW0006 | B7: Michelle Enriquez | C7: 110 Windermere Crescent, Woodstock, ON N4S 6T2 | D7: ellehci_m@yahoo.com.ph | E7: 226 228 4590 | F7: Myla, Herbert | G7: For Myla and Herbert Centeno | H7: E-transfer
A8: MMJW0007 | B8: Isaac Hunter | C8: 700 Chieftain Street Woodstock ON N4T 1S2 | D8: isaac.hunter2003@gmail.com | E8: 226 232 8065 | G8: i would prefer an etransfer and also i am in need of a paystub. | H8: #N/A
A9: MMJW0008 | B9: Armando C. Gabriola Jr. | C9: 1548 Purser St, London, ON N5V 5J4 | D9: armandogabriola2017@gmail.com | E9: 226 386 8343 | H9: #N/A
A10: MMJW0009 | B10: Jonervin Agustin | C10: 110 Windermere Crescent, Woodstock, ON N4S 6T2 | D10: jonervinagustin25@gmail.com | E10: 226 448 1652 | H10: **
A11: MMJW0010 | B11: Angel Lynne Ellan | C11: #1 579 Dundas St, Woodstock, ON N4S 1C9 | D11: angelgwapa28@gmail.com | E11: 226 503 7828 | G11: Interac pls | H11: E-transfer
A12: MMJW0011 | B12: Woddy Rivera | C12: 869 Adelaide St N, London, ON N5Y 2M2 | D12: epoi89091@gmail.com | E12: 226 582 5539 | H12: E-transfer
A13: MMJW0012 | B13: Gautam Gurung | C13: 1326 Fuller St, London, ON N5Y 4R2 | D13: thapasanti753@gmail.com | E13: 226 582 6757 | G13: Thanks | H13: 0
A14: MMJW0013 | B14: Ishpreet Kaur | C14: 14 Albright Rd, Brampton, ON L6X 5C8 | D14: ishpreetkaur28122004@gmail.com | E14: 226 753 1661 | H14: (PICK UP)
A15: MMJW0014 | B15: Kingsley Anugwo | C15: #B1 1279 Woodroffe Ave, Ottawa, ON K2C 2T7 | D15: anugwokingsley72@gmail.com | E15: 226 758 9937 | G15: Happy working with your organization, Thanks | H15: **
A16: MMJW0015 | B16: Zayrah Jusi | C16: 70 Hanes Road Huntsville ON P1H 1M3 | D16: zayrahjusi23@gmail.com | E16: 226 759 1522 | H16: #N/A
A17: MMJW0016 | B17: Elmer Delos Reyes | C17: 319 Dundas St, Woodstock, ON N4S 1B5 | D17: lmher03@yahoo.com | E17: 226 883 0592 | H17: E-transfer
A18: MMJW0017 | B18: Folashade Adekoya | C18: #2306 857 James St, Woodstock, ON N4S 8H5 | D18: ashandyawotungase@gmail.com | E18: 226 883 1763 | G18: Good | H18: **
A19: MMJW0018 | B19: Harpreet Harpreet | C19: 15 Graham St, Woodstock, ON N4S 6J5 | D19: jhinjerharpreet2@gmail.com | E19: 226 888 7747 | H19: 0
A20: MMJW0019 | B20: Meet Vanraj Mahida | C20: 257 Thorncrest Dr, Waterloo, ON N2L 4L2 | D20: meetmahida09500@gmail.com | E20: 226 899 7818 | H20: **
A21: MMJW0020 | B21: Daniel Ogunleye Bukoye | C21: 214 Speckled Alder Row, Ottawa, ON K2J 7G8 | D21: danielbukoye@gmail.com | E21: 226 966 5895 | F21: Daniel | G21: Non | H21: #N/A
A22: MMJW0021 | B22: Julie Jane Pamunag | C22: #11 511 Admiral Dr, London, ON N5V 4R4 | D22: jaepamunag95@gmail.com | E22: 226 977 9813 | G22: Kindly send the interac transfer with no notes. Please and thank you. Previous Address: 27A Empire St, London, ON N5Y 1G6 | H22: (PICK UP)
A23: MMJW0022 | B23: Julius Garcia | C23: #410 583 Mornington Ave, London, ON N5Y 3E9 | D23: jgarcia3327@gmail.com | E23: 226 998 1489 | H23: 0
A24: MMJW0023 | B24: Paul Jordan Untalan | C24: #715 621 Sheppard Ave E, Toronto, ON M2K 0G4 | D24: pauljordanuntalan@gmail.com | E24: 226-961-8796 | F24: Kapwa | H24: (PICK UP)
A25: MMJW0024 | B25: Anmol Saluja | C25: 2938 Oldcorn Pl, Victoria, BC V9B 2E9 | D25: anmolcan12@gmail.com | E25: 236 333 2065 | H25: #N/A
A26: MMJW0025 | B26: Heide Loraine Favor | C26: #2 853 Burdett Ave, Victoria, BC V8W 1B3 | D26: angelica.tadena@yahoo.com | E26: 236 638 6525 | G26: Interac details is through phone number please: 7786833737 | H26: 0
A27: MMJW0026 | B27: Henry Lopecillo | C27: 4111 24 Ave, Vernon, BC V1T 1M1 | D27: henrylopecillo@gmail.com | E27: 236 873 0036 | H27: #N/A
A28: MMJW0027 | B28: Henry Lopecillo Jr. | C28: 5300 25 Ave, Vernon, BC V1T 6Y2 | D28: henrylopecillo@gmail.com | E28: 236 873 0036 | H28: 0
A29: MMJW0028 | B29: Eduardo Dela Cruz | C29: BC V3R 7H7 | D29: khejdc1008@gmail.com | E29: 236 998 7645 | H29: #N/A
A30: MMJW0029 | B30: Sungcang Marvin | C30: 821 Hockley Ave, Victoria, BC V9B 0Z9 | D30: m.sungcang@yahoo.com | E30: 236-238-1372 | G30: NOTE : Void check provided but please I am prefer E transfer please | H30: E-transfer
A31: MMJW0030 | B31: Hazel Anne Masangkay | C31: 19 Newcastle Ct, Victoria, BC V9B 6V5 | D31: hazelsalvador.masangkay@gmail.com | E31: 236-638-8468 | H31: E-transfer
A32: MMJW0031 | B32: Muhammed Ibrahim | C32: 722 Spitfire St, Woodstock, ON N4T 0B1 | D32: muhad61191@gmail.com | E32: 249 885 5453 | H32: **
A33: MMJW0032 | B33: Carmela Ogena | C33: #521 1701 Cedar Hill Cross Rd, Victoria, BC V8P 2P9 | D33: vinperegrino@yahoo.com | E33: 250 885 1834 | G33: Please send it to my husband's account. | H33: 0
A34: MMJW0033 | B34: Jose Baldovino | C34: 3534 Redwood Ave., Victoria, BC V8P 4Z7 | D34: baldobaldovino1981@gmail.com | E34: 250 945 5840 | F34: Jose (Elk Lake) | G34: Thank you | H34: 0
A35: MMJW0034 | B35: Barkha Devi | C35: 3195 Balfour Ave, Victoria, BC V9A 1R9 | D35: barkhadevi015@gmail.com | E35: 250 986 1357 | H35: #N/A
A36: MMJW0035 | B36: Sheila Marie Cordon | C36: #304 844 Goldstream Ave, Langford, BC V9B 2X7 | D36: allancordon111969@gmail.com | E36: 250-532-1498 | G36: Holiday inn ekl lake time in 3:35 pm to 5:55 pm | H36: E-transfer
A37: MMJW0036 | B37: Ethel Ysabelle Delos Reyes | C37: #9 2105 Ave Van Horne, Montreal, QC H3S 1P3 | D37: ethelysabelle08@yahoo.com | E37: 263 881 4576 | H37: E-transfer
A38: MMJW0037 | B38: Prabin Pariyar | C38: 435 Upper Gage Ave. Hamilton, ON L8V 4H8 | D38: pariyarprabin1019@gmail.com | E38: 289 556 7245 | H38: **
A39: MMJW0038 | B39: Alish Shrestha | C39: 4653 Mcdougall Crescent, Niagara Falls, ON L2E 1B6 | D39: shresthaalish43@gmail.com | E39: 289 673 5618 | H39: E-transfer
A40: MMJW0039 | B40: Carlo Mallare | C40: 500 First Ave, Welland, ON L3C 1Z3 | D40: erlmediran@gmail.com / erlmediran@yahoo.com | E40: 289 681 5935 | G40: i haven't receive my pay for the June 30th i worked at Wyndamm Niagara Falls. Alternate email: erlmediran@yahoo.com | H40: #N/A
A41: MMJW0040 | B41: Karan Khatri | C41: #1602 165 Queen St S, Hamilton, ON L8P 4R3 | D41: karankhatrik10@gmail.com | E41: 289 698 7989 | G41: I hope this message finds you well. I wanted to kindly inquire about my payment for October 1, when I worked as a laborer from 8:00 AM to 4:00 PM, and for November 2, when I worked as a server from 4:00 PM to 8:30 PM. I would greatly appreciate it if you could assist me with this. Thank you! | H41: **
A42: MMJW0041 | B42: Mayank Kathuria | C42: 262 First Ave, Welland, ON L3C 1Y9 | D42: mayank5013697@gmail.com | E42: 289 821 2314 | H42: #N/A
A43: MMJW0042 | B43: Charles Ephraim Usita | C43: 7920 Preakness St, Niagara Falls, ON L2H 2Y4 | D43: charlesephraim30101@gmail.com | E43: 289 823 0525 | H43: #N/A
A44: MMJW0043 | B44: Ahmed Salim Zakaria | C44: 7056 Harriman St, Niagara Falls, ON L2J 3S2 | D44: yasinsalim998@gmail.com | E44: 289 823 2970 | H44: #N/A
A45: MMJW0044 | B45: Pardip Oli | C45: 156 Caroline St S, Hamilton, ON L8P 3K9 | D45: pradipwoli47@gmail.com | E45: 289 933 2477 | G45: Dear Sir/Madam, I sincerely apologize for selecting the pickup option. Could you kindly mail the cheque to my home address instead? I am truly sorry for the delayed response ON my part. Thank you for your understanding. Please, send cheques ON my home address. If you are using email to send the money please send by your personal email. | H45: (PICK UP)
A46: MMJW0045 | B46: Lilian Wamaitha Wanjiku | C46: 1075 Taffy Ln, Orleans, ON K1C 1Y4 | D46: wamaithalilian@gmail.com | E46: 289 946 5602 | H46: **
A47: MMJW0046 | B47: Christian Hiro Bonsol | C47: #74 292 Vine St, St. Catharines, ON L2M 0E1 | D47: christianhirobonsol@gmail.com | E47: 289 969 8978 | H47: 0
A48: MMJW0047 | B48: Harjeet Kaur | C48: 56 Yuile Ct, Brampton, ON L6Y 5J4 | D48: kaurharjeet9599@gmail.com | E48: 289-952-3594 | H48: (PICK UP)
A49: MMJW0048 | B49: Jenny Lyn Garcia Galapia | C49: 7207 Maple View Cres, Regina Sk, S4X 4S3 | D49: jlggalapia0913@gmail.com | E49: 306 216 7425 | H49: 0
A50: MMJW0049 | B50: Omoyele Oluwatimilehen Success | C50: #2 1879 Broder St, Regina, SK S4N 3R7 | D50: omoyeletimi03@gmail.com | E50: 306 520 5945 | H50: 0
A51: MMJW0050 | B51: Harsh Vyas | C51: #307 215 Windfield Rd, Regina, SK S4V 0L1 | D51: harsh23.vyas@gmail.com | E51: 306 999 2304 | H51: **
A52: MMJW0051 | B52: Abdulaziz Ketout | C52: 2573 Hobson Road Ottawa ON K1V 8M6 | D52: zizoketout@gmail.com | E52: 343 209 5281 | H52: **
A53: MMJW0052 | B53: Ishimwe Sarah | C53: Kanata, ON K2L 1Y3 | D53: ishimwesarah256@gmail.com | E53: 343 254 0328 | H53: 0
A54: MMJW0053 | B54: Teta Shenge Nonette | C54: 47 Upney Dr, Nepean, ON K2J 5G7 | D54: shengenigelle@gmail.com | E54: 343 254 3874 | H54: #N/A
A55: MMJW0054 | B55: Immacullee Maruhutsa | C55: 1 Corkstown Rd, Ottawa, ON K2H 0E4 | D55: imwamikazi11@gmail.com | E55: 343 254 8471 | H55: #N/A
A56: MMJW0055 | B56: Maruhutsa Immaculée | C56: 1 Corkstown Rd Ottawa ON K2H 0E4 | D56: imwamikazi11@gmail.com | E56: 343 254 8471 | G56: I would like to know when they gonna pay us plz thank you | H56: #N/A
A57: MMJW0056 | B57: Ugochukwu Ogbuaku | C57: 234 Chapel St, Ottawa, ON K1N 7Y7 | D57: ugochukwu.ogbuaku@gmail.com | E57: 343 297 0183 | H57: 0
A58: MMJW0057 | B58: Enny Hakkole Igirubuntu | C58: #1103 1365 Bank St, Ottawa, ON K1H 8K8 | D58: igirennyhak739@gmail.com | E58: 343 297 6502 | H58: #N/A
A59: MMJW0058 | B59: Sahi Salia | C59: #1 1170 Clyde Ave., Ottawa, ON K2C 1Y6 | D59: sahisalia123@gmail.com | E59: 343 297 7810 | G59: Hajia | H59: 0
A60: MMJW0059 | B60: Pedro Mago Sendon | C60: #21 28 Midland Crescent, Nepean, ON K2H 8N2 | D60: sendonpeter23@gmail.com | E60: 343 322 1979 | H60: #N/A
A61: MMJW0060 | B61: Paxella Mizero | C61: 2 Masonbrook St, Nepean, ON K2J 4C4 | D61: paxellamizero@gmail.com | E61: 343 322 8896 | H61: 0
A62: MMJW0061 | B62: Stella Asong Nchonganyi | C62: 6 Southview Crescent, Ottawa, ON K2E 5R3 | D62: stellaasong75@gmail.com | E62: 343 463 4211 | H62: 0
A63: MMJW0062 | B63: Lawrencia Okyere | C63: 1113 Field St, Ottawa, ON K2C 2P6 | D63: okyerelawrencia81@gmail.com | E63: 343 558 9457 | H63: #N/A
A64: MMJW0063 | B64: Safia Benafsha | C64: 520 St. Laurent Blvd, Ottawa, ON K1K 4N1 | D64: hmis.benafsha@gmail.com | E64: 343 572 8951 | G64: This is my personal information | H64: E-transfer
A65: MMJW0064 | B65: Danel Roussel Mafonou Nde | C65: 229 Hannah St, Ottawa, ON K1L 7N2 | D65: danelmafonou@gmail.com | E65: 343 574 2425 | H65: #N/A
A66: MMJW0065 | B66: Jordan Tsakou Kenne | C66: 217 Murray St, Ottawa, ON K1N 5M9 | D66: tsakoujordan0@gmail.com | E66: 343 574 4013 | H66: 0
A67: MMJW0066 | B67: Laurelle Sandra Saa Sandra | C67: 217 Murray St, Ottawa, ON K1N 5M9 | D67: saanguepie@gmail.com | E67: 343 575 0771 | H67: #N/A
A68: MMJW0067 | B68: Deborah Akinola | C68: #19 1591 Lycée Place, Ottawa, ON K1G 4A7 | D68: deborah.akinolaa@gmail.com | E68: 343 596 3121 | H68: E-transfer
A69: MMJW0068 | B69: Abidemi Tawakalit Olaore | C69: 2980 Carling Ave, Nepean, ON K2B 7K2 | D69: olaoreabidemi86@gmail.com | E69: 343 596 5617 | G69: Excited | H69: **
A70: MMJW0069 | B70: Emilly Azevedo da Rocha | C70: #1003 70 Mcewen Ave, Ottawa, ON K2B 5M3 | D70: rochaemilly01@gmail.com | E70: 343 598 9075 | F70: Emily Da Rocha | H70: **
A71: MMJW0070 | B71: Joshua Ikeji | C71: #29 11 Majestic Dr, Nepean, ON K2G 1C5 | D71: joeikeji7@gmail.com | E71: 343 630 4002 | H71: 0
A72: MMJW0071 | B72: Divya Sampoornatha Bokinala | C72: Bishops Mills Way, Kanata, ON K2K 3B9 | D72: divyasampoorna.b1@gmail.com | E72: 343 777 9940 | H72: #N/A
A73: MMJW0072 | B73: Christian Izuchukwu Osoagba | C73: 96B Meadowlands Dr W, Ottawa, ON K2G 2R8 | D73: christianizuchukwu00@gmail.com / chukwunonyefranklyn@gmail.com | E73: 343 843 6936 | H73: E-transfer
A74: MMJW0073 | B74: Azeez Abefe | C74: 309 Mcarthur Ave., Vanier, ON K1L 6P1 | D74: abefelion308@gmail.com | E74: 343 961 3113 | H74: **
A75: MMJW0074 | B75: Ibrahim Adebayo | C75: 309 Mcarthur Ave., Vanier, ON K1L 6P1 | D75: adebayoibrahim303030@gmail.com | E75: 343 961 3560 | H75: 0
A76: MMJW0075 | B76: Julien Vincent | C76: 12 Eastwood Pl, Ottawa, ON K1L 6X1 | D76: jay20cent@gmail.com | E76: 343 987 2147 | G76: No cheque. Previous Address: 4960 Abbott St E, Stittsville ON K2V 0M6 | H76: **
A77: MMJW0076 | B77: Pascaline Irakoze | C77: #515 1975 St. Laurent Blvd, Ottawa, ON K1G 3S7 | D77: fabriziolavaneri@yahoo.fr | E77: 343 987 4864 | H77: #N/A
A78: MMJW0077 | B78: Omar Teofilo | C78: 3205 Upland Drive Ottawa Ontario K1V 9T3 | E78: 343 988 7857 | F78: Jasmin Arce, Jasmine | G78: For Jasmin Arce | H78: #N/A
A79: MMJW0078 | B79: Farel Manirakiza | C79: #7 1675 Heatherington Rd, Ottawa, ON K1V 8V8 | D79: manirakizafarel8@gmail.com | E79: 343 996 3273 | H79: BEST WESTERN PLUS OTTAWA (1876 ROBERTSON RD)
A80: MMJW0079 | B80: Isha Touray | C80: 2750 Carousel Crescent, Gloucester, ON K1T 1Z5 | D80: jallowisha588@gmail.com | E80: 343 997 4403 | H80: 0
A81: MMJW0080 | B81: Nafisa Akter | C81: #2 418 Rideau St, Ottawa, ON K1N 5Z1 | D81: akternaf7@gmail.com | E81: 343 999 3935 | G81: I live in Ottawa, kindly send me pay through interac e transfer please. | H81: **
A82: MMJW0081 | B82: Patrick Belanger | C82: 28 Rue Oakwood b, Gatineau, QC J9H 3Z2 | D82: patrick.belanger@me.com | E82: 343-961-5753 | H82: E-transfer
A83: MMJW0082 | B83: Darran Larrance | C83: 105 Degrassi Cove Cir, Brampton, ON L6X 0N7 | D83: darranlarrance@gmail.com | E83: 347 869 6903 | H83: **
A84: MMJW0083 | B84: Varkha Varkha | C84: 287 E 24Th St, Hamilton, ON L8V 2Y7 | D84: varkha904@gmail.com | E84: 365 366 6077 | H84: **
A85: MMJW0084 | B85: Rishabh Kumar | C85: 296 W 2Nd St, Hamilton, ON L9C 3H2 | D85: rishabhkumar8787@gmail.com | E85: 365 476 7241 | H85: (PICK UP)
A86: MMJW0085 | B86: Eduardo Ferrer | C86: #98 145 Rice Ave, Hamilton, ON L9C 5X6 | D86: eduardoferrer1017@gmail.com | E86: 365 833 9728 | H86: **
A87: MMJW0086 | B87: Mohit | C87: 287 E 24Th Street, Hamilton, Ontario, L8V 2Y7 | D87: mohitgakhar3022@gmail.com | E87: 365 883 0922 | H87: #N/A
A88: MMJW0087 | B88: Sachin Phago | C88: 850 Brucedale Ave E, Hamilton, ON L8T 1L5 | D88: phago08sachin@gmail.com | E88: 365 883 3045 | H88: **
A89: MMJW0088 | B89: Jeremy Kenneth Mendoza | C89: #1101 150 Hughson St S, Hamilton, ON L8N 2B4 | D89: emorej24.jcm@gmail.com | E89: 365-883-4334 | F89: Jerome Mendoza | G89: For Jerome Mendoza | H89: **
A90: MMJW0089 | B90: Regine Akayezu | C90: #803 2850 Cedarwood Dr, Ottawa, ON K1V 8Y4 | D90: akayezu.reginec@gmail.com | E90: 367 330 0991 | G90: Thanks | H90: 0
A91: MMJW0090 | B91: Onyeka Chibuzor Maryann | C91: #911 75 Silver Springs Blvd, Scarborough, On M1V 1W2 | D91: maryann02082000@icloud.com | E91: 382-885-0236 | H91: **
A92: MMJW0091 | B92: Shedrack David Ifeanyi | C92: 6 Southview Crescent, Ottawa, ON K2E 5R3 | D92: shedrackdavid29@gmail.com | E92: 416 301 1447 | H92: 0
A93: MMJW0092 | B93: Tunde Balogh | C93: #1108 5 Agate Rd, North York, ON M3M 2B2 | D93: bt65425@gmail.com | E93: 416 419 6183 | G93: Don’t have void check | H93: (PICK UP)
A94: MMJW0093 | B94: Jualyn Barbarona | C94: 20 Lanark Ave, York, ON M6C 2B3 | D94: barbaronajualyn@yahoo.ca | E94: 416 428 6014 | G94: When will it arrive pls | H94: (PICK UP)
A95: MMJW0094 | B95: Rene Ramos | C95: 21 Warkdale Dr, St. Catharines, ON L2T 2V8 | D95: arkineers@gmail.com | E95: 416 454 7921 | G95: Payment: E transfer | H95: 0
A96: MMJW0095 | B96: Naveed John | C96: 77 Muscat Crescent, Ajax, ON L1Z 0B8 | D96: malihajohn@hotmail.com | E96: 416 475 7567 | F96: Mursal | G96: Please Etransfer my pay thank you so much. For Mursal | H96: Etransfer
A97: MMJW0096 | B97: Rita Aladi | C97: #809 75 Silver Springs Blvd, Scarborough, ON M1V 1W1 | D97: chijiokeblessing0@gmail.com | E97: 416 524 6174 | H97: **
A98: MMJW0097 | B98: Ivy Mendoza | C98: 311 The West Mall Ertobicoke ON M9C 1C9 | D98: ivyamendoza@gmail.com | E98: 416 670 4840 | H98: (PICK UP)
A99: MMJW0098 | B99: Casey Alexis Rapisura | C99: 604 Crawford Cres, Woodstock, ON N4S 0B6 | D99: caseyrapisura@gmail.com | E99: 416 688 8930 | H99: E-transfer
A100: MMJW0099 | B100: Gabriel Aaron Ramos | C100: 149 Medora St, Port Carling, ON P0B 1J0 | D100: gabs100312@gmail.com | E100: 416 731 3189 | G100: Can you just interact it? Thanks | H100: E-transfer
...

Sheet GTA
A5: Hyatt Place 5787 Hurontario St - Hyatt Place 5787 Hurontario St - Hyatt Place 5787 Hurontario St - Hyatt Place 5787 Hurontario St - Hyatt Place 5787 Hurontario St - Hyatt Place 5787 Hurontario St - Hyatt Place 5787 Hurontario St - Hyatt Place 5787 Hurontario St - Hyatt Place 5787 | BA5: ADJUSTMENT
B6: Jan | C6: Niloufar Shirvani | D6: Arman Thind | E6: Ernesto Jr. Gampon | F6: Gabriel Oloro Oloro | G6: Guilherme Augusto Coscarelli | H6: Inderjit Kaur | I6: Jan Choy Tee | J6: Joshua Jhon Emmanuel Sosa | K6: Komal Preet Kaur | L6: Madhur Manocha | M6: Mannat Badhan | N6: Naima | O6: Navneet Kaur.. | P6: Nuuradin Hassan | Q6: Olawale Onabanjo | R6: Olayiwola Emmanuel Olatide | S6: Osarenren Osamuyimen | T6: Rafael | U6: Ritesh Kumar | V6: Sapna Kumari | W6: Shifa Ibrahim | X6: Tolulope Opeyemi Gbenga-Olufeyisan | Y6: Ujunwa Jessica Okwuaka
A7: Sat | B7: 10 | ER7: Sat
A8: Sun | B8: 11 | ER8: Sun
A9: Mon | B9: 12 | ER9: Mon
A10: Tue | B10: 13 | ER10: Tue
A11: Wed | B11: 14 | ER11: Wed
A12: Thu | B12: 15 | ER12: Thu
A13: Fri | B13: 16 | C13: 7 | ER13: Fri
A14: Sat | B14: 17 | ER14: Sat
A15: Sun | B15: 18 | ER15: Sun
A16: Mon | B16: 19 | ER16: Mon
A17: Tue | B17: 20 | ER17: Tue
A18: Wed | B18: 21 | ER18: Wed
A19: Thu | B19: 22 | ER19: Thu
A20: Fri | B20: 23 | ER20: Fri
A21: Total | B21: =SUM(C21:EP21,ET21:EV21) -> 7 | C21: =SUM(C7:C20) -> 7 | D21: =SUM(D7:D20) -> 0 | E21: =SUM(E7:E20) -> 0 | F21: =SUM(F7:F20) -> 0 | G21: =SUM(G7:G20) -> 0 | H21: =SUM(H7:H20) -> 0 | I21: =SUM(I7:I20) -> 0 | J21: =SUM(J7:J20) -> 0 | ... EO21: =SUM(EO7:EO20) -> 0 | ER21: Total | ES21: =SUM(ET21:EV21) -> 0 | ET21: =SUM(ET7:ET20) -> 0 | EU21: =SUM(EU7:EU20) -> 0 | EV21: =SUM(EV7:EV20) -> 0
A22: =B22-B21 -> 444.5 | B22: 451.5
A23: HOLIDAY INN EXPRESS - RICHMOND HILL (10 East Pearce St.) | N23: ADJUSTMENT
B24: =B6 -> Jan | C24: Andrew Verches | D24: Paxson Intal Figueroa
A25: Sat | B25: =B7 -> 10 | D25: 7 | T25: Sat
A26: Sun | B26: =B8 -> 11 | C26: 13 | D26: 8 | T26: Sun
A27: Mon | B27: =B9 -> 12 | C27: 7 | T27: Mon
A28: Tue | B28: =B10 -> 13 | C28: 7 | D28: 7.5 | T28: Tue
A29: Wed | B29: =B11 -> 14 | C29: 7 | D29: 7.5 | T29: Wed
A30: Thu | B30: =B12 -> 15 | C30: 7 | D30: 7.5 | T30: Thu
A31: Fri | B31: =B13 -> 16 | D31: 7 | T31: Fri
A32: Sat | B32: =B14 -> 17 | C32: 13 | D32: 6 | T32: Sat
A33: Sun | B33: =B15 -> 18 | D33: 6 | T33: Sun
A34: Mon | B34: =B16 -> 19 | C34: 7 | T34: Mon
A35: Tue | B35: =B17 -> 20 | C35: 7 | T35: Tue
A36: Wed | B36: =B18 -> 21 | D36: 7 | T36: Wed
A37: Thu | B37: =B19 -> 22 | C37: 7 | D37: 8 | T37: Thu
A38: Fri | B38: =B20 -> 23 | C38: 7 | D38: 7 | T38: Fri
A39: Total | B39: =SUM(C39:S39)+U39 -> 160.5 | C39: =SUM(C26:C38) -> 82 | D39: =SUM(D25:D38) -> 78.5 | E39: =SUM(E25:E38) -> 0 | F39: =SUM(F25:F38) -> 0 | G39: =SUM(G25:G38) -> 0 | H39: =SUM(H25:H38) -> 0 | I39: =SUM(I25:I38) -> 0 | J39: =SUM(J25:J38) -> 0 | K39: =SUM(K25:K38) -> 0 | ... R39: =SUM(R25:R38) -> 0 | T39: Total | U39: =SUM(V39:X39) -> 0 | V39: =SUM(V25:V38) -> 0 | W39: =SUM(W25:W38) -> 0 | X39: =SUM(X25:X38) -> 0
A41: HOLIDAY INN EXPRESS (2125 NORTH SHERIDAN WAY MISSISSAUGA) | N41: ADJUSTMENT
B42: =B24 -> Jan | C42: Asmita Baral | D42: Rizalina | E42: Ansherina Orda | F42: Angelo | G42: Akin | H42: Baljit | I42: Bansi | J42: Pepito | K42: Kenneth | L42: Elo | M42: Komalpreet | N42: Merxedes MC Painting | O42: Namandeep | P42: Pardeep SS | Q42: Hameen | R42: Khristine | S42: Ranjit Singh | T42: Navneet | U42: Aldrin | V42: Aman | W42: Naneth Miro | X42: Cain | Y42: Chander | Z42: Esther | AA42: Cora | AB42: Giovanni Dulay | AC42: Gurpinder | AD42: Harpreet K | AE42: Harshdeep Singh | AF42: Ishpreet | AG42: Kamaljit | AH42: Karan Maheriya | AI42: Madhur | AJ42: Catherine MC Painting | AK42: Yohanny MC Painting | AL42: Simranjeet Kaur | AM42: Simranjot | AN42: Mark Jan | AO42: Mark V | AP42: Monia | AQ42: Myriam | AR42: Upasna | AS42: Damodar Dahal | AT42: Vivek
A43: Sat | B43: =B25 -> 10 | AV43: Sat
A44: Sun | B44: =B26 -> 11 | AV44: Sun
A45: Mon | B45: =B27 -> 12 | AV45: Mon
A46: Tue | B46: =B28 -> 13 | AV46: Tue
A47: Wed | B47: =B29 -> 14 | AV47: Wed
A48: Thu | B48: =B30 -> 15 | AV48: Thu
A49: Fri | B49: =B31 -> 16 | AV49: Fri
A50: Sat | B50: =B32 -> 17 | AV50: Sat
A51: Sun | B51: =B33 -> 18 | AV51: Sun
A52: Mon | B52: =B34 -> 19 | AV52: Mon
A53: Tue | B53: =B35 -> 20 | AV53: Tue
A54: Wed | B54: =B36 -> 21 | AV54: Wed
... A56: Fri | B56: =B38 -> 23 | AV56: Fri
A57: Total | B57: =SUM(C57:AU57)+AW57 -> 0 | C57: =SUM(C43:C56) -> 0 | D57: =SUM(D43:D56) -> 0 | E57: =SUM(E43:E56) -> 0 | F57: =SUM(F43:F56) -> 0 | G57: =SUM(G43:G56) -> 0 | H57: =SUM(H43:H56) -> 0 | I57: =SUM(I43:I56) -> 0 | J57: =SUM(J43:J56) -> 0 | ... AU57: =SUM(AU43:AU56) -> 0 | AV57: Total | AW57: =SUM(AX57:AZ57) -> 0 | AX57: =SUM(AX43:AX56) -> 0 | AY57: =SUM(AY43:AY56) -> 0 | AZ57: =SUM(AZ43:AZ56) -> 0
A59: RADISSON (55 HALLCROWN PL, NORTHYORK) | M59: ADJUSTMENT
B60: =B42 -> Jan | C60: Alejandra Cristina Lugo Martinez | D60: Diana Laura Priego Jimenez | E60: Jonas Layug Macaspac | F60: José Antonio Martínez Rodríguez | G60: Manuel Alejandro Uribe Adame | H60: Simranjit Kaur | J60: Ivan Sicat I
A61: Sat | B61: =B43 -> 10 | L61: Sat
A62: Sun | B62: =B44 -> 11 | L62: Sun
A63: Mon | B63: =B45 -> 12 | L63: Mon
A64: Tue | B64: =B46 -> 13 | L64: Tue
A65: Wed | B65: =B47 -> 14 | L65: Wed
A66: Thu | B66: =B48 -> 15 | L66: Thu
A67: Fri | B67: =B49 -> 16 | L67: Fri
A68: Sat | B68: =B50 -> 17 | L68: Sat
A69: Sun | B69: =B51 -> 18 | L69: Sun
A70: Mon | B70: =B52 -> 19 | L70: Mon
A71: Tue | B71: =B53 -> 20 | L71: Tue
A72: Wed | B72: =B54 -> 21 | L72: Wed
... A74: Fri | B74: =B56 -> 23 | L74: Fri
A75: Total | B75: =SUM(C75:K75)+M75 -> 0 | C75: =SUM(C61:C74) -> 0 | D75: =SUM(D61:D74) -> 0 | E75: =SUM(E61:E74) -> 0 | F75: =SUM(F61:F74) -> 0 | G75: =SUM(G61:G74) -> 0 | H75: =SUM(H61:H74) -> 0 | J75: =SUM(J61:J74) -> 0 | K75: =SUM(K61:K74) -> 0 | L75: Total | M75: =SUM(N75:P75) -> 0 | N75: =SUM(N61:N74) -> 0 | O75: =SUM(O61:O74) -> 0 | P75: =SUM(P61:P74) -> 0
A77: Holiday Inn Express (30 Norfinch Dr, North York, ON M3N 1X1 | L77: ADJUSTMENT
B78: =B60 -> Jan | C78: Dheeraj Kumar I | D78: Tunde | E78: Mirasol | F78: Esther Omono | G78: Kamaljit
A79: Sat | B79: =B61 -> 10 | L79: Sat
A80: Sun | B80: =B62 -> 11 | L80: Sun
A81: Mon | B81: =B63 -> 12 | L81: Mon
A82: Tue | B82: =B64 -> 13 | L82: Tue
A83: Wed | B83: =B65 -> 14 | L83: Wed
A84: Thu | B84: =B66 -> 15 | L84: Thu
A85: Fri | B85: =B67 -> 16 | L85: Fri
A86: Sat | B86: =B68 -> 17 | L86: Sat
A87: Sun | B87: =B69 -> 18 | L87: Sun
A88: Mon | B88: =B70 -> 19 | L88: Mon
A89: Tue | B89: =B71 -> 20 | L89: Tue
A90: Wed | B90: =B72 -> 21 | L90: Wed
... A92: Fri | B92: =B74 -> 23 | L92: Fri
A93: Total | B93: =SUM(C93:K93)+M93 -> 0 | C93: =SUM(C79:C92) -> 0 | D93: =SUM(D79:D92) -> 0 | E93: =SUM(E79:E92) -> 0 | F93: =SUM(F79:F92) -> 0 | G93: =SUM(G79:G92) -> 0 | H93: =SUM(H79:H92) -> 0 | I93: =SUM(I79:I92) -> 0 | J93: =SUM(J79:J92) -> 0 | K93: =SUM(K79:K92) -> 0 | L93: Total | M93: =SUM(N93:P93) -> 0 | N93: =SUM(N79:N92) -> 0 | O93: =SUM(O79:O92) -> 0 | P93: =SUM(P79:P92) -> 0
A95: EDWARD HOTEL (185 YORKLAND BLVD NORTHYORK) | L95: ADJUSTMENT
B96: =B78 -> Jan | C96: Jacqueline Arethea Ford-Bah L | D96: Ariadne Huesca Medina A | E96: Lauren Plester M | F96: Madeline Simogan D
A97: Sat | B97: =B79 -> 10 | L97: Sat
A98: Sun | B98: =B80 -> 11 | L98: Sun
A99: Mon | B99: =B81 -> 12 | L99: Mon
A100: Tue | B100: =B82 -> 13 | L100: Tue
A101: Wed | B101: =B83 -> 14 | L101: Wed
A102: Thu | B102: =B84 -> 15 | L102: Thu
A103: Fri | B103: =B85 -> 16 | L103: Fri
A104: Sat | B104: =B86 -> 17 | L104: Sat
A105: Sun | B105: =B87 -> 18 | L105: Sun
A106: Mon | B106: =B88 -> 19 | L106: Mon
A107: Tue | B107: =B89 -> 20 | L107: Tue
A108: Wed | B108: =B90 -> 21 | L108: Wed
... A110: Fri | B110: =B92 -> 23 | L110: Fri
A111: Total | B111: =SUM(C111:K111)+M111 -> 0 | C111: =SUM(C97:C110) -> 0 | D111: =SUM(D97:D110) -> 0 | E111: =SUM(E97:E110) -> 0 | F111: =SUM(F97:F110) -> 0 | G111: =SUM(G97:G110) -> 0 | H111: =SUM(H97:H110) -> 0 | I111: =SUM(I97:I110) -> 0 | J111: =SUM(J97:J110) -> 0 | K111: =SUM(K97:K110) -> 0 | L111: Total | M111: =SUM(N111:P111) -> 0 | N111: =SUM(N97:N110) -> 0 | O111: =SUM(O97:O110) -> 0 | P111: =SUM(P97:P110) -> 0
A113: COURTYARD | MARRIOTT TORONTO MISSISSAUGA WEST (290 DERRY ROAD W) | T113: ADJUSTMENT
...

Sheet OUTSIDE GTA
A1: Manitou Springs Resort and Mineral Spa (302 MacLachlan Ave) | T1: ADJUSTMENT
B2: =GTA!B6 -> Jan | C2: Huberto | D2: Willy | P2: Menandro | Q2: Angel Ellan
A3: Sat | B3: =GTA!B7 -> 10 | U3: Sat | V3: 26
A4: Sun | B4: =GTA!B8 -> 11 | U4: Sun | V4: 27
A5: Mon | B5: =GTA!B9 -> 12 | U5: Mon | V5: 28
A6: Tue | B6: =GTA!B10 -> 13 | U6: Tue | V6: 29
A7: Wed | B7: =GTA!B11 -> 14 | U7: Wed | V7: 30
A8: Thu | B8: =GTA!B12 -> 15 | U8: Thu | V8: 31
A9: Fri | B9: =GTA!B13 -> 16 | U9: Fri | V9: 1
A10: Sat | B10: =GTA!B14 -> 17 | U10: Sat | V10: 2
A11: Sun | B11: =GTA!B15 -> 18 | U11: Sun | V11: 3
A12: Mon | B12: =GTA!B16 -> 19 | U12: Mon | V12: 4
A13: Tue | B13: =GTA!B17 -> 20 | U13: Tue | V13: 5
A14: Wed | B14: =GTA!B18 -> 21 | U14: Wed | V14: 6
... A16: Fri | B16: =GTA!B20 -> 23 | U16: Fri | V16: 8
A17: Total | B17: =SUM(C17:T17)+V17 -> 0 | C17: =SUM(C3:C16) -> 0 | D17: =SUM(D3:D16) -> 0 | F17: =SUM(F3:F16) -> 0 | G17: =SUM(G3:G16) -> 0 | H17: =SUM(H3:H16) -> 0 | I17: =SUM(I3:I16) -> 0 | J17: =SUM(J3:J16) -> 0 | K17: =SUM(K3:K16) -> 0 | L17: =SUM(L3:L16) -> 0 | M17: =SUM(M3:M16) -> 0 | ... T17: =SUM(T3:T16) -> 0 | U17: Total | V17: =SUM(W17:Y17) -> 0 | W17: =SUM(W3:W16) -> 0 | X17: =SUM(X3:X16) -> 0 | Y17: =SUM(Y3:Y16) -> 0
A19: Home 2 Hotel Woodstock (527 Lampman) | T19: ADJUSTMENT
B20: =B2 -> Jan | C20: Menandro | D20: Ruben | E20: Dhruv | F20: Sukhjivan | G20: Wilmar | H20: Harkirat | I20: Gagan | J20: Casey | K20: Emmanuel
A21: =A3 -> Sat | B21: =B3 -> 10 | T21: Sat
A22: =A4 -> Sun | B22: =B4 -> 11 | T22: Sun
A23: =A5 -> Mon | B23: =B5 -> 12 | T23: Mon
A24: =A6 -> Tue | B24: =B6 -> 13 | T24: Tue
A25: =A7 -> Wed | B25: =B7 -> 14 | T25: Wed
A26: =A8 -> Thu | B26: =B8 -> 15 | T26: Thu
A27: =A9 -> Fri | B27: =B9 -> 16 | T27: Fri
A28: =A10 -> Sat | B28: =B10 -> 17 | T28: Sat
A29: =A11 -> Sun | B29: =B11 -> 18 | T29: Sun
A30: =A12 -> Mon | B30: =B12 -> 19 | T30: Mon
A31: =A13 -> Tue | B31: =B13 -> 20 | T31: Tue
A32: =A14 -> Wed | B32: =B14 -> 21 | T32: Wed
... A34: =A16 -> Fri | B34: =B16 -> 23 | T34: Fri
A35: Total | B35: =SUM(C35:S35)+U35 -> 0 | C35: =SUM(C21:C34) -> 0 | D35: =SUM(D21:D34) -> 0 | E35: =SUM(E21:E34) -> 0 | F35: =SUM(F21:F34) -> 0 | G35: =SUM(G21:G34) -> 0 | H35: =SUM(H21:H34) -> 0 | I35: =SUM(I21:I34) -> 0 | J35: =SUM(J21:J34) -> 0 | ... S35: =SUM(S21:S34) -> 0 | T35: Total | U35: =SUM(V35:X35) -> 0 | V35: =SUM(V21:V34) -> 0 | W35: =SUM(W21:W34) -> 0 | X35: =SUM(X21:X34) -> 0
A37: Spark by Hilton Woodstock | T37: ADJUSTMENT
B38: October | C38: Veronica | D38: Adejumo | E38: Dianne G | F38: Dionisio | G38: Elvira D | H38: Balvir | I38: Casey | J38: Isaac | K38: Joseph | L38: Kafila | M38: Jennifer | N38: Susan | O38: Gautam | P38: Harkirat | Q38: Chali | R38: Voltair J | S38: Julius G | T38: Harpreet2x | U38: Parimal | V38: Fola | W38: Sivakumar Vinoth | X38: Nishal | Y38: Gurpreet K | Z38: Manpreet S | AA38: Jonervin Agustin | AB38: Elmer Delosreyes | AC38: Woddy
A39: Sat | B39: 4 | AE39: Sat
A40: Sun | B40: 5 | AE40: Sun
A41: Mon | B41: 6 | AE41: Mon
A42: Tue | B42: 7 | AE42: Tue
A43: Wed | B43: 8 | AE43: Wed
A44: Thu | B44: 9 | AE44: Thu
A45: Fri | B45: 10 | AE45: Fri
A46: Sat | B46: 11 | AE46: Sat
A47: Sun | B47: 12 | AE47: Sun
A48: Mon | B48: 13 | AE48: Mon
A49: Tue | B49: 14 | AE49: Tue
A50: Wed | B50: 15 | AE50: Wed
... A52: Fri | B52: 17 | AE52: Fri
A53: Total | B53: =SUM(C53:AD53)+AF53 -> 0 | C53: =SUM(C39:C52) -> 0 | D53: =SUM(D39:D52) -> 0 | E53: =SUM(E39:E52) -> 0 | F53: =SUM(F39:F52) -> 0 | G53: =SUM(G39:G52) -> 0 | H53: =SUM(H39:H52) -> 0 | I53: =SUM(I39:I52) -> 0 | J53: =SUM(J39:J52) -> 0 | ... AD53: =SUM(AD39:AD52) -> 0 | AE53: Total | AF53: =SUM(AG53:AI53) -> 0 | AG53: =SUM(AG39:AG52) -> 0 | AH53: =SUM(AH39:AH52) -> 0 | AI53: =SUM(AI39:AI52) -> 0
A55: Hidden Valley Resort 1755 Valley Rd, Huntsville, ON P1H 1A8 | T55: ADJUSTMENT
B56: =B38 -> October | C56: Armstrong (HK) | D56: Carl | E56: Flordelyn (HK) | F56: Gabriel | G56: Gerald | H56: Jan Mayckie | I56: Jennylyn Ceniza | J56: Mark G | K56: Noralyn | L56: Sheila/Rey | M56: Wilson | N56: Carl M | O56: Flor M | P56: Gerald M | Q56: Nelson M | R56: Armstrong (Cook) | S56: Flordelyn (Cook) | T56: Flordelyn Kids Activity | U56: Noralyn Kids Activity | Y56: July - August | Z56: Flordelyn Kids Activity | AA56: Flordelyn (Cook)
A57: Sat | B57: =B39 -> 4 | X57: Sat | Y57: 26
A58: Sun | B58: =B40 -> 5 | X58: Sun | Y58: 27
A59: Mon | B59: =B41 -> 6 | X59: Mon | Y59: 28
A60: Tue | B60: =B42 -> 7 | X60: Tue | Y60: 29
A61: Wed | B61: =B43 -> 8 | X61: Wed | Y61: 30
A62: Thu | B62: =B44 -> 9 | X62: Thu | Y62: 31
A63: Fri | B63: =B45 -> 10 | X63: Fri | Y63: 1
A64: Sat | B64: =B46 -> 11 | X64: Sat | Y64: 2
A65: Sun | B65: =B47 -> 12 | X65: Sun | Y65: 3
A66: Mon | B66: =B48 -> 13 | X66: Mon | Y66: 4
A67: Tue | B67: =B49 -> 14 | X67: Tue | Y67: 5
A68: Wed | B68: =B50 -> 15 | X68: Wed | Y68: 6
... A70: Fri | B70: =B52 -> 17 | X70: Fri | Y70: 8
A71: Total | B71: =SUM(C71:W71) -> 0 | C71: =SUM(C57:C70) -> 0 | D71: =SUM(D57:D70) -> 0 | E71: =SUM(E57:E70) -> 0 | F71: =SUM(F57:F70) -> 0 | G71: =SUM(G57:G70) -> 0 | H71: =SUM(H57:H70) -> 0 | I71: =SUM(I57:I70) -> 0 | J71: =SUM(J57:J70) -> 0 | ... V71: =SUM(V57:V70) -> 0 | X71: Total | Y71: =SUM(Z71:AQ71)+AS71 -> 0 | Z71: =SUM(Z57:Z70) -> 0 | AA71: =SUM(AA57:AA70) -> 0
A73: RAMADA NIAGARA (4357 River Rd.) | T73: ADJUSTMENT
B74: =B56 -> October | C74: Maureen | D74: Alish | E74: Wilfried | F74: Karamveer | G74: Dev | H74: Chonnelie | I74: Himanshu | J74: Jelery | K74: Christian | L74: Charles | M74: Adwan | N74: Mayan | O74: Carlo | P74: Lovepreet | Q74: Rene | R74: Aisha | S74: Salim | T74: Reyson | U74: Thomas | V74: Mikee
A75: Sat | B75: =B57 -> 4 | W75: Sat
A76: Sun | B76: =B58 -> 5 | W76: Sun
A77: Mon | B77: =B59 -> 6 | W77: Mon
A78: Tue | B78: =B60 -> 7 | W78: Tue
A79: Wed | B79: =B61 -> 8 | W79: Wed
A80: Thu | B80: =B62 -> 9 | W80: Thu
A81: Fri | B81: =B63 -> 10 | W81: Fri
A82: Sat | B82: =B64 -> 11 | W82: Sat
A83: Sun | B83: =B65 -> 12 | W83: Sun
A84: Mon | B84: =B66 -> 13 | W84: Mon
A85: Tue | B85: =B67 -> 14 | W85: Tue
A86: Wed | B86: =B68 -> 15 | W86: Wed
... A88: Fri | B88: =B70 -> 17 | W88: Fri
A89: Total | B89: =SUM(C89:V89)+X89 -> 0 | C89: =SUM(C75:C88) -> 0 | D89: =SUM(D75:D88) -> 0 | E89: =SUM(E75:E88) -> 0 | F89: =SUM(F75:F88) -> 0 | G89: =SUM(G75:G88) -> 0 | H89: =SUM(H75:H88) -> 0 | I89: =SUM(I75:I88) -> 0 | J89: =SUM(J75:J88) -> 0 | ... V89: =SUM(V75:V88) -> 0 | W89: Total | X89: =SUM(Y89:AA89) -> 0 | Y89: =SUM(Y75:Y88) -> 0 | Z89: =SUM(Z75:Z88) -> 0 | AA89: =SUM(AA75:AA88) -> 0
A91: Chatham Kent | T91: ADJUSTMENT
B92: =B74 -> October | C92: Akin | D92: Asmita | E92: Delmi | F92: Evelyn Ogbegie | G92: Glenn | H92: Harshdeep Singh | I92: Julie Jane Pamunag | J92: Karen Vera | K92: Komalpreet Kaur | L92: Khushdeep | M92: Mercedes | N92: Namandeep Kaur | O92: Princess Montemayor | P92: Riza | Q92: Rodel Santos | R92: Rupinder Singh | S92: Virgelio Magna | T92: Vivek Dahiya | U92: Yaime Aguerro
A93: Sat | B93: =B75 -> 4 | Y93: Sat
A94: Sun | B94: =B76 -> 5 | Y94: Sun
A95: Mon | B95: =B77 -> 6 | Y95: Mon
A96: Tue | B96: =B78 -> 7 | Y96: Tue
A97: Wed | B97: =B79 -> 8 | Y97: Wed
A98: Thu | B98: =B80 -> 9 | Y98: Thu
A99: Fri | B99: =B81 -> 10 | Y99: Fri
A100: Sat | B100: =B82 -> 11 | Y100: Sat
A101: Sun | B101: =B83 -> 12 | Y101: Sun
A102: Mon | B102: =B84 -> 13 | Y102: Mon
A103: Tue | B103: =B85 -> 14 | Y103: Tue
A104: Wed | B104: =B86 -> 15 | Y104: Wed
... A106: Fri | B106: =B88 -> 17 | Y106: Fri
A107: Total | B107: =SUM(C107:X107)+Z107 -> 0 | C107: =SUM(C93:C106) -> 0 | D107: =SUM(D93:D106) -> 0 | E107: =SUM(E93:E106) -> 0 | F107: =SUM(F93:F106) -> 0 | G107: =SUM(G93:G106) -> 0 | H107: =SUM(H93:H106) -> 0 | I107: =SUM(I93:I106) -> 0 | J107: =SUM(J93:J106) -> 0 | ... X107: =SUM(X93:X106) -> 0 | Y107: Total | Z107: =SUM(AA107:AC107) -> 0 | AA107: =SUM(AA93:AA106) -> 0 | AB107: =SUM(AB93:AB106) -> 0 | AC107: =SUM(AC93:AC106) -> 0
A109: Quality Inn & Suites Regina Downtown (1907 11th Ave, Regina, SK S4P 0J2) | T109: ADJUSTMENT
B110: November | C110: Jenny | D110: Harsh | E110: Anastasia | F110: Omoyele Oluwatimilehen Success | G110: Adwoa
A111: Sat | B111: 15 | T111: Sat
A112: Sun | B112: 16 | T112: Sun
...

Sheet OTTAWA
A2: BEST WESTERN PLUS OTTAWA (1876 ROBERTSON RD, OTTAWA) | T2: ADJUSTMENT
B3: August - Sept | C3: Binta | D3: Abdulahi | E3: Bernard | F3: Brenda | G3: Carive | H3: Claudine | I3: Clein | J3: Collins Darko Nimako | K3: Christian Izuchukwu Osoagba | L3: Daisy Jerono Cheboswony | M3: Daniel Aboagye | N3: Daniela | O3: David Shedrack | P3: Douglas (HP) | Q3: Elvera | R3: Gary Maintenance | S3: Ivy | T3: Elsie Ndobegang Zinkeng | U3: Farel Manirakiza | V3: Fatouma | W3: Frank | X3: Freda | Y3: Flor | Z3: Hannah | AA3: Hargor Roberto Ninziza | AB3: Hursulla Camara Da Rocha (Front Desk) | AC3: Imaculee | AD3: Rita | AE3: Joshua F/O | AF3: Julien Vincent | AG3: Jordan | AH3: Ibrahim Adebayo | AI3: Ibrahim Kamaru | AJ3: James | AK3: Nick | AL3: Ilka Ingabire Bukuru | AM3: Isha Jallow | AN3: Manuela Doloresse Njikam Nzeket | AO3: Nancy Andong | AP3: Nonette Teta Shenge | AQ3: Manuella | AR3: Nshimirimana Carine | AS3: Olga | AT3: Paxella | AU3: Kevine | AV3: Rachel | AW3: Regine | AX3: Rehoboth Byiringiro | AY3: Rochell Ann Magtangobe Anne | AZ3: Rosette | BA3: Sarah Nyanduko | BB3: Sarah Ishimwe | BC3: Sahi | BD3: Simon | BE3: Safia Benafsha | BF3: Sofoa | BG3: Sodimu | BH3: Sylvester | BI3: William Gateru Ngure | BJ3: Yasin | BK3: Omowunmi Samuel | BL3: Farel Manirakiza (M) | BN3: Sat | BO3: SeptOct | BP3: Hursulla
A4: Sat | B4: 23 | BN4: Sat | BO4: 21
A5: Sun | B5: 24 | BM5: =BM13-BM12 -> 0 | BN5: Sun | BO5: 22
A6: Mon | B6: 25 | BN6: Mon | BO6: 23
A7: Tue | B7: 26 | BN7: Tue | BO7: 24
A8: Wed | B8: 27 | BN8: Wed | BO8: 25
A9: Thu | B9: 28 | BN9: Thu | BO9: 26
A10: Fri | B10: 29 | BN10: Fri | BO10: 27
A11: Sat | B11: 30 | BN11: Sat | BO11: 28
A12: Sun | B12: 31 | BM12: =SUM(C6:BL12) -> 0 | BN12: Sun | BO12: 29
A13: Mon | B13: 1 | BM13: =SUM(C4:BL12) -> 0 | BN13: Mon | BO13: 30 | BS13: =SUM(C13:BL13) -> 0
A14: Tue | B14: 2 | BN14: Tue | BO14: 1 | BS14: =SUM(C14:BL14) -> 0
A15: Wed | B15: 3 | BN15: Wed | BO15: 2 | BS15: =SUM(C15:BL15) -> 0
A16: Thu | B16: 4 | BN16: Thu | BO16: 3 | BS16: =SUM(C16:BL16) -> 0
A17: Fri | B17: 5 | BM17: =SUM(C13:BL17) -> 0 | BN17: Fri | BO17: 4 | BS17: =SUM(C17:BL17) -> 0
A18: Total | B18: =SUM(C18:BL18)+BO18 -> 0 | C18: =SUM(C4:C17) -> 0 | D18: =SUM(D4:D17) -> 0 | E18: =SUM(E4:E17) -> 0 | F18: =SUM(F4:F17) -> 0 | G18: =SUM(G4:G17) -> 0 | H18: =SUM(H4:H17) -> 0 | I18: =SUM(I4:I17) -> 0 | J18: =SUM(J4:J17) -> 0 | ... BL18: =SUM(BL4:BL17) -> 0 | BN18: Total | BO18: =SUM(BP18:BR18) -> 0 | BP18: =SUM(BP3:BP17) -> 0 | BQ18: =SUM(BQ3:BQ17) -> 0 | BR18: =SUM(BR3:BR17) -> 0
A20: DAYS INN OTTAWA WEST (350 MOODIE DR, OTTAWA)
B21: =B3 -> August - Sept | C21: Abidemi Tawakalit Olaore | D21: Abdulasiz | E21: Audriel | F21: Azeez Abefe | G21: Doly Tatchou Djikemi | H21: Amado | I21: Binta | J21: Brenda | K21: Carive | L21: Claudine | M21: Cleine | N21: Cleopatra | O21: Christian Izuchukwu Osoagba | P21: Christopher | Q21: Daniela | R21: Deborah | S21: Delphine | T21: Elsie Ndobegang Zinkeng | U21: Emily | V21: Enny | W21: Esther Suubi | X21: Eunice Ndinda Sammy | Y21: Fannie | Z21: Fatouma | AA21: Freda | AB21: Flor | AC21: Hannah | AD21: Safia Benafsha | AE21: Gary | AF21: Hargor Roberto Ninziza | AG21: Sunshine | AH21: Ibrahim Kamaru | AI21: Ibrahim Adebayo | AJ21: Ilona Diandra Igiraneza | AK21: Isha Touray | AL21: Ishwori | AM21: Jandira Vissolela Pedro da Costa E | AN21: Jasmine | AO21: Julien | AP21: Kevine | AQ21: Khaled Rugamba | AR21: Grace | AS21: Ivy | AT21: Laurie | AU21: Lawrencia | AV21: Marie | AW21: Manuela Doloresse Njikam Nzeket | AX21: Mbazumutima Dionne | AY21: Nafisa Akter | AZ21: Nancy Andong | BA21: Nelly | BB21: Nick | BC21: Njong Precious Eghah | BD21: Noela | BE21: Nonette Teta Shenge | BF21: Nshimirimana Carine | BG21: Nyinawase Merveille | BH21: Ojo | BI21: Olave Akundwe | BJ21: Olga Uwikunze | BK21: Onuchukwu Chidera | BL21: Oyebola Oladoyin | BM21: Pascaline | BN21: Pierre | BO21: Paxella Mizero | BP21: Pedro Mago Sendon | BQ21: Rehoboth Byiringiro | BR21: Rochell Ann Magtangobe | BS21: Roxette | BT21: Sarah Ishimwe | BU21: Simon Waweru | BV21: Sofoa | BW21: Sohail Mohammed Abdul | BX21: Stella | BY21: Tandi Suwaneh | BZ21: Ugochukwu | CA21: Vaida Awuor Ouma | CB21: Vanessa | CC21: Wumni | CD21: Yasin | CE21: Yvonne Wanjiru (HK) | CF21: Yvonne Wanjiru (SV) | CG21: Zita Charone Igihozo | CH21: Nataliia | CI21: Anna | CJ21: Imaculee | CK21: Daniel | CL21: Isaac | CM21: Divya | CN21: Abdula | CO21: Diego | CU21: July | CV21: Nataliia
A22: Sat | B22: =B4 -> 23 | CT22: Sat | CU22: 12
A23: Sun | B23: =B5 -> 24 | CT23: Sun | CU23: 13
A24: Mon | B24: =B6 -> 25 | CT24: Mon | CU24: 14
A25: Tue | B25: =B7 -> 26 | CT25: Tue | CU25: 15
A26: Wed | B26: =B8 -> 27 | CT26: Wed | CU26: 16
A27: Thu | B27: =B9 -> 28 | CT27: Thu | CU27: 17
A28: Fri | B28: =B10 -> 29 | CR28: =SUM(C22:CQ28) -> 0 | CT28: Fri | CU28: 18
A29: Sat | B29: =B11 -> 30 | CT29: Sat | CU29: 19
A30: Sun | B30: =B12 -> 31 | CT30: Sun | CU30: 20
A31: Mon | B31: =B13 -> 1 | CT31: Mon | CU31: 21
A32: Tue | B32: =B14 -> 2 | CT32: Tue | CU32: 22
A33: Wed | B33: =B15 -> 3 | CT33: Wed | CU33: 23
A34: Thu | B34: =B16 -> 4 | CT34: Thu | CU34: 24
A35: Fri | B35: =B17 -> 5 | CR35: =SUM(C29:CQ35) -> 0 | CT35: Fri | CU35: 25
A36: Total | B36: =SUM(C36:CP36) -> 0 | C36: =SUM(C22:C35) -> 0 | D36: =SUM(D22:D35) -> 0 | E36: =SUM(E22:E35) -> 0 | F36: =SUM(F22:F35) -> 0 | G36: =SUM(G22:G35) -> 0 | H36: =SUM(H22:H35) -> 0 | I36: =SUM(I22:I35) -> 0 | J36: =SUM(J22:J35) -> 0 | ... CP36: =SUM(CP22:CP35) -> 0 | CT36: Total | CU36: =SUM(CV36:GI36)+GN35 -> 0 | CV36: =SUM(CV22:CV35) -> 0 | CW36: =SUM(CW22:CW35) -> 0 | CX36: =SUM(CX22:CX35) -> 0
C37: =SUM(C29:C35) -> 0 | D37: =SUM(D29:D35) -> 0 | E37: =SUM(E29:E35) -> 0 | F37: =SUM(F29:F35) -> 0 | G37: =SUM(G29:G35) -> 0 | H37: =SUM(H29:H35) -> 0 | I37: =SUM(I29:I35) -> 0 | J37: =SUM(J29:J35) -> 0 | ... CP37: =SUM(CP29:CP35) -> 0 | CR37: =CR28+CR35 -> 0
A38: DAYS INN OTTAWA DOWNTOWN (319 RIDEAU ST, OTTAWA)
B39: =B21 -> August - Sept | C39: Connex | D39: Eunice | E39: Vanessa | F39: Etienne
A40: Sat | B40: =B22 -> 23
A41: Sun | B41: =B23 -> 24
A42: Mon | B42: =B24 -> 25
A43: Tue | B43: =B25 -> 26
A44: Wed | B44: =B26 -> 27
A45: Thu | B45: =B27 -> 28
A46: Fri | B46: =B28 -> 29
A47: Sat | B47: =B29 -> 30
A48: Sun | B48: =B30 -> 31
A49: Mon | B49: =B31 -> 1
A50: Tue | B50: =B32 -> 2
A51: Wed | B51: =B33 -> 3
... A53: Fri | B53: =B35 -> 5
A54: Total | B54: =SUM(C40:P53) -> 0 | C54: =SUM(C40:C53) -> 0 | D54: =SUM(D40:D53) -> 0 | E54: =SUM(E40:E53) -> 0 | F54: =SUM(F40:F53) -> 0 | G54: =SUM(G40:G53) -> 0 | H54: =SUM(H40:H53) -> 0 | I54: =SUM(I40:I53) -> 0 | J54: =SUM(J40:J53) -> 0 | ... P54: =SUM(P40:P53) -> 0
A56: Male Hotels Pankaj
B57: June | C57: Sunshine | E57: Shine
A58: Sat | B58: 14
A59: Sun | B59: 15
A60: Mon | B60: 16
A61: Tue | B61: 17
A62: Wed | B62: 18
A63: Thu | B63: 19
A64: Fri | B64: 20
A65: Sat | B65: 21
A66: Sun | B66: 22
A67: Mon | B67: 23
A68: Tue | B68: 24
A69: Wed | B69: 25
... A71: Fri | B71: 27
A72: Total | B72: =SUM(C72:BB72)+BG72 -> 0 | C72: =SUM(C58:C71) -> 0 | D72: =SUM(D58:D71) -> 0 | E72: =SUM(E58:E71) -> 0 | F72: =SUM(F58:F71) -> 0 | G72: =SUM(G58:G71) -> 0 | H72: =SUM(H58:H71) -> 0 | I72: =SUM(I58:I71) -> 0 | J72: =SUM(J58:J71) -> 0 | ... P72: =SUM(P58:P71) -> 0
C73: =SUM(C60:C67) -> 0
C74: =C73*18 -> 0
A76: RIDEAU HEIGHTS INN (72 Rideau Heights Dr)
B77: May | C77: Ilona | D77: Elsie
A78: Sat | B78: 31
A79: Sun | B79: 1
A80: Mon | B80: 2
A81: Tue | B81: 3
A82: Wed | B82: 4
A83: Thu | B83: 5
A84: Fri | B84: 6
A85: Sat | B85: 7
A86: Sun | B86: 8
A87: Mon | B87: 9
A88: Tue | B88: 10
A89: Wed | B89: 11
... A91: Fri | B91: 13
B92: =SUM(C92:BB92)+BG92 -> 0 | C92: =SUM(C78:C91) -> 0 | D92: =SUM(D78:D91) -> 0 | E92: =SUM(E78:E91) -> 0 | F92: =SUM(F78:F91) -> 0 | G92: =SUM(G78:G91) -> 0 | H92: =SUM(H78:H91) -> 0 | I92: =SUM(I78:I91) -> 0 | J92: =SUM(J78:J91) -> 0 | ... R92: =SUM(R78:R91) -> 0

Sheet SUBCON - BC
A1: PAY PERIOD November 15 - 28, 2025 | B1: HOURS | C1: TYPE | D1: RATE | E1: TOTAL | Z1: =IFERROR( DATEVALUE( MID(A1,12,FIND("-",A1)-12) & ", " & RIGHT(A1,4) ), "") -> 45976
A2: Holiday Inn Elk Lake Victoria BC (4670 Elk Lake Drive) | Z2: {=_xlfn.LET( _xlpm.hdr, TRIM(A1), _xlpm.yr, TRIM(RIGHT(_xlpm.hdr,4)), _xlpm.body, TRIM(MID(_xlpm.hdr, 12, FIND(",", _xlpm.hdr) - 12)), _xlpm.startPart, TRIM(LEFT(_xlpm.body, FIND("-", _xlpm.body) - 1)), _xlpm.endRaw, TRIM(MID(_xlpm.body, FIND("-", _xlpm.body) + 1, 999)), _xlpm.months, {"January","February","March","April","May","June","July","August","September","October","November","December"}, _xlpm.hasMonth, SUM(--ISNUMBER(SEARCH(_xlpm.months, _xlpm.endRaw))), _xlpm.endPart, IF(_xlpm.hasMonth>0, _xlpm.endRaw, LEFT(_xlpm.startPart, FIND(" ", _xlpm.startPart & " ") - 1) & " " & _xlpm.endRaw), _xlpm.result, IFERROR(DATEVALUE(_xlpm.endPart & ", " & _xlpm.yr), ""), _xlpm.result )} -> 45989
A3: Aljhon | B3: {=IF((INDEX('British Columbia'!$C$18:$Z$18,ROW(A1)))=0,"",(INDEX('British Columbia'!$C$18:$Z$18,ROW(A1))))} | C3: SUBCON | D3: 16.65 | E3: =IF(B3="", 0, B3*D3) -> 0
A4: Anmol | B4: {=IF((INDEX('British Columbia'!$C$18:$Z$18,ROW(A2)))=0,"",(INDEX('British Columbia'!$C$18:$Z$18,ROW(A2))))} | C4: SUBCON | D4: 17 | E4: =IF(B4="", 0, B4*D4) -> 0
A5: Barkha | C5: SUBCON | D5: 17 | E5: =IF(B5="", 0, B5*D5) -> 0
A6: Emily | C6: SUBCON | D6: 17 | E6: =IF(B6="", 0, B6*D6) -> 0
A7: Harsh Kumar Sharma | C7: SUBCON | D7: 17 | E7: =IF(B7="", 0, B7*D7) -> 0
A8: Heide FD | C8: SUBCON | D8: 18 | E8: =IF(B8="", 0, B8*D8) -> 0
A9: Heide HK | C9: SUBCON | D9: 17 | E9: =IF(B9="", 0, B9*D9) -> 0
A10: Mirzi Lisa Pangan | B10: ='British Columbia'!J19 -> 23.5 | C10: SUBCON | D10: 17 | E10: =IF(B10="", 0, B10*D10) -> 399.5
A11: Jean Martin Junio (JM) | B11: ='British Columbia'!K19 -> 29 | C11: SUBCON | D11: 17 | E11: =IF(B11="", 0, B11*D11) -> 493
A12: Antonio | B12: ='British Columbia'!L19 -> 13 | C12: SUBCON | D12: 17 | E12: =IF(B12="", 0, B12*D12) -> 221
A13: Rolyn | B13: {=IF((INDEX('British Columbia'!$C$18:$Z$18,ROW(A11)))=0,"",(INDEX('British Columbia'!$C$18:$Z$18,ROW(A11))))} | C13: SUBCON | D13: 17 | E13: =IF(B13="", 0, B13*D13) -> 0
E14: =SUM(E6:E11) -> 892.5 | I14: BEST WESTERN PLUS (38 ESTATE DR, SCARBOROUGH)
A15: Holiday Inn Elk Lake Victoria BC (4670 Elk Lake Drive) TOTAL: | B15: =SUM(B3:B14) -> 65.5
I16: COURTYARD MISSISSAUGA WEST (290 DERRY ROAD W)
I17: COURTYARD MISSISSAUGA WEST (290 DERRY ROAD W)
A18: Holiday Inn Express & Suites Victoria - Colwood (318 Wale Rd)
A19: Aljhon Galgo | C19: SUBCON | D19: 17 | E19: =IF(B19="", 0, B19*D19) -> 0
A20: Barkha | B20: {=IF((INDEX('British Columbia'!$C$37:$Z$37,ROW(A2)))=0,"",(INDEX('British Columbia'!$C$37:$Z$37,ROW(A2))))} | C20: SUBCON | D20: 17 | E20: =IF(B20="", 0, B20*D20) -> 0
A21: Emily | C21: SUBCON | D21: 17 | E21: =IF(B21="", 0, B21*D21) -> 0
A22: Hazel | C22: SUBCON | D22: 17 | E22: =IF(B22="", 0, B22*D22) -> 0
A23: Heide FD | C23: SUBCON | D23: 18 | E23: =B23*D23 -> 0
A24: Jashan | C24: SUBCON | D24: 17 | E24: =IF(B24="", 0, B24*D24) -> 0
A25: Mar | C25: SUBCON | D25: 17 | E25: =IF(B25="", 0, B25*D25) -> 0
A26: Neeru | C26: SUBCON | D26: 17 | E26: =IF(B26="", 0, B26*D26) -> 0
A27: Marvin | C27: SUBCON | D27: 17 | E27: =IF(B27="", 0, B27*D27) -> 0
A28: Pedro Saluta Calvar | B28: {=IF((INDEX('British Columbia'!$C$37:$Z$37,ROW(A10)))=0,"",(INDEX('British Columbia'!$C$37:$Z$37,ROW(A10))))} | C28: SUBCON | D28: 17 | E28: =IF(B28="", 0, B28*D28) -> 0
A29: Sheila | C29: SUBCON | D29: 17 | E29: =IF(B29="", 0, B29*D29) -> 0
A30: Simrat | B30: {=IF((INDEX('British Columbia'!$C$37:$Z$37,ROW(A12)))=0,"",(INDEX('British Columbia'!$C$37:$Z$37,ROW(A12))))} | C30: SUBCON | D30: 17 | E30: =IF(B30="", 0, B30*D30) -> 0 | F30: =B32+B53+B15 -> 65.5
I31: BEST WESTERN PLUS (38 ESTATE DR, SCARBOROUGH)
A32: Holiday Inn Express & Suites Victoria - Colwood (318 Wale Rd) | B32: =SUM(B19:B31) -> 0
I33: COURTYARD MISSISSAUGA WEST (290 DERRY ROAD W)
I34: COURTYARD MISSISSAUGA WEST (290 DERRY ROAD W)
A35: Motel 6 Saanichton Victoria Airport BC (2401 Mt Newton Cross Rd)
A36: Aljhon | C36: SUBCON | D36: 17 | E36: =B36*D36 -> 0
A37: Pedro Saluta Calvar | C37: SUBCON | D37: 17 | E37: =B37*D37 -> 0
A38: Mirzi | C38: SUBCON | D38: 17 | E38: =B38*D38 -> 0
A39: JM | C39: SUBCON | D39: 17 | E39: =B39*D39 -> 0
A40: Haider | C40: SUBCON | D40: 18 | E40: =B40*D40 -> 0
A41: Marica | C41: SUBCON | D41: 17 | E41: =B41*D41 -> 0
A42: Lorraine | C42: SUBCON | D42: 17 | E42: =B42*D42 -> 0
A43: Czarina | C43: SUBCON | D43: 17 | E43: =B43*D43 -> 0
A44: Dante | C44: SUBCON | D44: 17 | E44: =B44*D44 -> 0
A45: Emily | B45: ='British Columbia'!R57 -> 0 | C45: SUBCON | D45: 17 | E45: =B45*D45 -> 0
A46: Paul Brian | C46: SUBCON | D46: 17 | E46: =B46*D46 -> 0
A47: Sukhpreet | C47: SUBCON | D47: 17 | E47: =B47*D47 -> 0
A48: Anthony | C48: SUBCON | D48: 17 | E48: =B48*D48 -> 0
A49: Anmol | C49: SUBCON | D49: 17 | E49: =B49*D49 -> 0
A50: Marvin | C50: SUBCON | D50: 17 | E50: =B50*D50 -> 0
A51: Rizzabelle | C51: SUBCON | D51: 17 | E51: =B51*D51 -> 0
I52: BEST WESTERN PLUS (38 ESTATE DR, SCARBOROUGH)
A53: Motel 6 Saanichton Victoria Airport BC (2401 Mt Newton Cross Rd) | B53: =SUM(B36:B52) -> 0
A55: Queens Hotel (130-1110 Ewen Ave, New Westminster, BC V3M 5E4)
A56: Manmeet | B56: ='British Columbia'!C74 -> 21.5 | C56: SUBCON | D56: 17 | E56: =(B56*D56) -> 365.5
A57: Mandeep | C57: SUBCON | D57: 17 | E57: =B57*D57 -> 0
A58: Eduardo | C58: SUBCON | D58: 17 | E58: =B58*D58 -> 0
A59: Sukhpreet | B59: ='British Columbia'!F75 -> 0 | C59: SUBCON | D59: 17 | E59: =B59*D59 -> 0 | F59: =B61+B15 -> 87
A61: Queens Hotel (130-1110 Ewen Ave, New Westminster, BC V3M 5E4) | B61: =SUM(B56:B60) -> 21.5
A63: Four Points Edmonton
A64: Ronald | B64: ='British Columbia'!C95 -> 0 | C64: SUBCON | D64: 17 | E64: =B64*D64 -> 0
A66: Four Points Edmonton | B66: =SUM(B64:B65) -> 0

Sheet British Columbia
A1: Holiday Inn Elk Lake Victoria BC (4670 Elk Lake) | U1: ADJUSTMENT
B2: Jan | C2: Aljhon | D2: Anmol | E2: Barkha | F2: Emily | G2: Harsh | H2: Heide FD | I2: Heide HK | J2: Mirzi | K2: JM | L2: Antonio | M2: Rolyn | V2: July | W2: Heide FD | X2: Heide HK
A3: Mon | B3: 12 | U3: Mon | V3: 14 | AA3: =_xlfn.LET( _xlpm.monthText, $B$2, _xlpm.dayNum, B3, _xlpm.prevDay, IF(ROW()=3, 0, B2), _xlpm.month1, TRIM(LEFT(_xlpm.monthText, FIND("-", _xlpm.monthText & "-") - 1)), _xlpm.month2, IFERROR(TRIM(MID(_xlpm.monthText, FIND("-", _xlpm.monthText & "-") + 1, 99)), ""), _xlpm.useMonth, IF( _xlpm.month2 = "", _xlpm.month1, IF(ROW()=3, _xlpm.month1, IF(_xlpm.dayNum < _xlpm.prevDay, _xlpm.month2, _xlpm.month1)) ), IFERROR(DATEVALUE(_xlpm.useMonth & " " & _xlpm.dayNum & ", " & 2025), "") ) -> 45669 | AD3: =5.5+6+7.5+7.5+7.5+6.75+4.45+7.25+6.25+8 -> 66.7
A4: Tue | B4: 13 | K4: 5 | U4: Tue | V4: 15 | AA4: =_xlfn.LET( _xlpm.monthText, $B$2, _xlpm.dayNum, B4, _xlpm.prevDay, IF(ROW()=3, 0, B3), _xlpm.month1, TRIM(LEFT(_xlpm.monthText, FIND("-", _xlpm.monthText & "-") - 1)), _xlpm.month2, IFERROR(TRIM(MID(_xlpm.monthText, FIND("-", _xlpm.monthText & "-") + 1, 99)), ""), _xlpm.useMonth, IF( _xlpm.month2 = "", _xlpm.month1, IF(ROW()=3, _xlpm.month1, IF(_xlpm.dayNum < _xlpm.prevDay, _xlpm.month2, _xlpm.month1)) ), IFERROR(DATEVALUE(_xlpm.useMonth & " " & _xlpm.dayNum & ", " & 2025), "") ) -> 45670
A5: Wed | B5: 14 | J5: 4.5 | K5: 5 | U5: Wed | V5: 16 | AA5: =_xlfn.LET( _xlpm.monthText, $B$2, _xlpm.dayNum, B5, _xlpm.prevDay, IF(ROW()=3, 0, B4), _xlpm.month1, TRIM(LEFT(_xlpm.monthText, FIND("-", _xlpm.monthText & "-") - 1)), _xlpm.month2, IFERROR(TRIM(MID(_xlpm.monthText, FIND("-", _xlpm.monthText & "-") + 1, 99)), ""), _xlpm.useMonth, IF( _xlpm.month2 = "", _xlpm.month1, IF(ROW()=3, _xlpm.month1, IF(_xlpm.dayNum < _xlpm.prevDay, _xlpm.month2, _xlpm.month1)) ), IFERROR(DATEVALUE(_xlpm.useMonth & " " & _xlpm.dayNum & ", " & 2025), "") ) -> 45671
A6: Thu | B6: 15 | J6: 5.5 | K6: 5.5 | U6: Thu | V6: 17 | AA6: =_xlfn.LET( _xlpm.monthText, $B$2, _xlpm.dayNum, B6, _xlpm.prevDay, IF(ROW()=3, 0, B5), _xlpm.month1, TRIM(LEFT(_xlpm.monthText, FIND("-", _xlpm.monthText & "-") - 1)), _xlpm.month2, IFERROR(TRIM(MID(_xlpm.monthText, FIND("-", _xlpm.monthText & "-") + 1, 99)), ""), _xlpm.useMonth, IF( _xlpm.month2 = "", _xlpm.month1, IF(ROW()=3, _xlpm.month1, IF(_xlpm.dayNum < _xlpm.prevDay, _xlpm.month2, _xlpm.month1)) ), IFERROR(DATEVALUE(_xlpm.useMonth & " " & _xlpm.dayNum & ", " & 2025), "") ) -> 45672
A7: Fri | B7: 16 | J7: 5.5 | K7: 5.5 | U7: Fri | V7: 18 | AA7: =_xlfn.LET( _xlpm.monthText, $B$2, _xlpm.dayNum, B7, _xlpm.prevDay, IF(ROW()=3, 0, B6), _xlpm.month1, TRIM(LEFT(_xlpm.monthText, FIND("-", _xlpm.monthText & "-") - 1)), _xlpm.month2, IFERROR(TRIM(MID(_xlpm.monthText, FIND("-", _xlpm.monthText & "-") + 1, 99)), ""), _xlpm.useMonth, IF( _xlpm.month2 = "", _xlpm.month1, IF(ROW()=3, _xlpm.month1, IF(_xlpm.dayNum < _xlpm.prevDay, _xlpm.month2, _xlpm.month1)) ), IFERROR(DATEVALUE(_xlpm.useMonth & " " & _xlpm.dayNum & ", " & 2025), "") ) -> 45673
A8: Sat | B8: 17 | K8: 4 | U8: Sat | V8: 19 | AA8: =_xlfn.LET( _xlpm.monthText, $B$2, _xlpm.dayNum, B8, _xlpm.prevDay, IF(ROW()=3, 0, B7), _xlpm.month1, TRIM(LEFT(_xlpm.monthText, FIND("-", _xlpm.monthText & "-") - 1)), _xlpm.month2, IFERROR(TRIM(MID(_xlpm.monthText, FIND("-", _xlpm.monthText & "-") + 1, 99)), ""), _xlpm.useMonth, IF( _xlpm.month2 = "", _xlpm.month1, IF(ROW()=3, _xlpm.month1, IF(_xlpm.dayNum < _xlpm.prevDay, _xlpm.month2, _xlpm.month1)) ), IFERROR(DATEVALUE(_xlpm.useMonth & " " & _xlpm.dayNum & ", " & 2025), "") ) -> 45674
A9: Sun | B9: 18 | K9: 5.5 | T9: =SUM(C3:S9) -> 46 | U9: Sun | V9: 20 | AA9: =_xlfn.LET( _xlpm.monthText, $B$2, _xlpm.dayNum, B9, _xlpm.prevDay, IF(ROW()=3, 0, B8), _xlpm.month1, TRIM(LEFT(_xlpm.monthText, FIND("-", _xlpm.monthText & "-") - 1)), _xlpm.month2, IFERROR(TRIM(MID(_xlpm.monthText, FIND("-", _xlpm.monthText & "-") + 1, 99)), ""), _xlpm.useMonth, IF( _xlpm.month2 = "", _xlpm.month1, IF(ROW()=3, _xlpm.month1, IF(_xlpm.dayNum < _xlpm.prevDay, _xlpm.month2, _xlpm.month1)) ), IFERROR(DATEVALUE(_xlpm.useMonth & " " & _xlpm.dayNum & ", " & 2025), "") ) -> 45675
A10: Mon | B10: 19 | J10: 7 | U10: Mon | V10: 21 | AA10: =_xlfn.LET( _xlpm.monthText, $B$2, _xlpm.dayNum, B10, _xlpm.prevDay, IF(ROW()=3, 0, B9), _xlpm.month1, TRIM(LEFT(_xlpm.monthText, FIND("-", _xlpm.monthText & "-") - 1)), _xlpm.month2, IFERROR(TRIM(MID(_xlpm.monthText, FIND("-", _xlpm.monthText & "-") + 1, 99)), ""), _xlpm.useMonth, IF( _xlpm.month2 = "", _xlpm.month1, IF(ROW()=3, _xlpm.month1, IF(_xlpm.dayNum < _xlpm.prevDay, _xlpm.month2, _xlpm.month1)) ), IFERROR(DATEVALUE(_xlpm.useMonth & " " & _xlpm.dayNum & ", " & 2025), "") ) -> 45676
A11: Tue | B11: 20 | L11: 8 | U11: Tue | V11: 22 | AA11: =_xlfn.LET( _xlpm.monthText, $B$2, _xlpm.dayNum, B11, _xlpm.prevDay, IF(ROW()=3, 0, B10), _xlpm.month1, TRIM(LEFT(_xlpm.monthText, FIND("-", _xlpm.monthText & "-") - 1)), _xlpm.month2, IFERROR(TRIM(MID(_xlpm.monthText, FIND("-", _xlpm.monthText & "-") + 1, 99)), ""), _xlpm.useMonth, IF( _xlpm.month2 = "", _xlpm.month1, IF(ROW()=3, _xlpm.month1, IF(_xlpm.dayNum < _xlpm.prevDay, _xlpm.month2, _xlpm.month1)) ), IFERROR(DATEVALUE(_xlpm.useMonth & " " & _xlpm.dayNum & ", " & 2025), "") ) -> 45677
A12: Wed | B12: 21 | J12: 6 | K12: 6 | L12: 5 | U12: Wed | V12: 23 | AA12: =_xlfn.LET( _xlpm.monthText, $B$2, _xlpm.dayNum, B12, _xlpm.prevDay, IF(ROW()=3, 0, B11), _xlpm.month1, TRIM(LEFT(_xlpm.monthText, FIND("-", _xlpm.monthText & "-") - 1)), _xlpm.month2, IFERROR(TRIM(MID(_xlpm.monthText, FIND("-", _xlpm.monthText & "-") + 1, 99)), ""), _xlpm.useMonth, IF( _xlpm.month2 = "", _xlpm.month1, IF(ROW()=3, _xlpm.month1, IF(_xlpm.dayNum < _xlpm.prevDay, _xlpm.month2, _xlpm.month1)) ), IFERROR(DATEVALUE(_xlpm.useMonth & " " & _xlpm.dayNum & ", " & 2025), "") ) -> 45678
A13: Thu | B13: 22 | J13: 5 | K13: 5 | U13: Thu | V13: 24 | AA13: =_xlfn.LET( _xlpm.monthText, $B$2, _xlpm.dayNum, B13, _xlpm.prevDay, IF(ROW()=3, 0, B12), _xlpm.month1, TRIM(LEFT(_xlpm.monthText, FIND("-", _xlpm.monthText & "-") - 1)), _xlpm.month2, IFERROR(TRIM(MID(_xlpm.monthText, FIND("-", _xlpm.monthText & "-") + 1, 99)), ""), _xlpm.useMonth, IF( _xlpm.month2 = "", _xlpm.month1, IF(ROW()=3, _xlpm.month1, IF(_xlpm.dayNum < _xlpm.prevDay, _xlpm.month2, _xlpm.month1)) ), IFERROR(DATEVALUE(_xlpm.useMonth & " " & _xlpm.dayNum & ", " & 2025), "") ) -> 45679
A14: Fri | B14: 23 | J14: 5.5 | K14: 5.5 | U14: Fri | V14: 25 | AA14: =_xlfn.LET( _xlpm.monthText, $B$2, _xlpm.dayNum, B14, _xlpm.prevDay, IF(ROW()=3, 0, B13), _xlpm.month1, TRIM(LEFT(_xlpm.monthText, FIND("-", _xlpm.monthText & "-") - 1)), _xlpm.month2, IFERROR(TRIM(MID(_xlpm.monthText, FIND("-", _xlpm.monthText & "-") + 1, 99)), ""), _xlpm.useMonth, IF( _xlpm.month2 = "", _xlpm.month1, IF(ROW()=3, _xlpm.month1, IF(_xlpm.dayNum < _xlpm.prevDay, _xlpm.month2, _xlpm.month1)) ), IFERROR(DATEVALUE(_xlpm.useMonth & " " & _xlpm.dayNum & ", " & 2025), "") ) -> 45680
A15: Sat | B15: 24 | K15: 7.5 | U15: Sat | V15: 26 | AA15: =_xlfn.LET( _xlpm.monthText, $B$2, _xlpm.dayNum, B15, _xlpm.prevDay, IF(ROW()=3, 0, B14), _xlpm.month1, TRIM(LEFT(_xlpm.monthText, FIND("-", _xlpm.monthText & "-") - 1)), _xlpm.month2, IFERROR(TRIM(MID(_xlpm.monthText, FIND("-", _xlpm.monthText & "-") + 1, 99)), ""), _xlpm.useMonth, IF( _xlpm.month2 = "", _xlpm.month1, IF(ROW()=3, _xlpm.month1, IF(_xlpm.dayNum < _xlpm.prevDay, _xlpm.month2, _xlpm.month1)) ), IFERROR(DATEVALUE(_xlpm.useMonth & " " & _xlpm.dayNum & ", " & 2025), "") ) -> 45681
A16: Sun | B16: 25 | K16: 5 | T16: =SUM(C10:S16) -> 65.5 | U16: Sun | V16: 27 | AA16: =_xlfn.LET( _xlpm.monthText, $B$2, _xlpm.dayNum, B16, _xlpm.prevDay, IF(ROW()=3, 0, B15), _xlpm.month1, TRIM(LEFT(_xlpm.monthText, FIND("-", _xlpm.monthText & "-") - 1)), _xlpm.month2, IFERROR(TRIM(MID(_xlpm.monthText, FIND("-", _xlpm.monthText & "-") + 1, 99)), ""), _xlpm.useMonth, IF( _xlpm.month2 = "", _xlpm.month1, IF(ROW()=3, _xlpm.month1, IF(_xlpm.dayNum < _xlpm.prevDay, _xlpm.month2, _xlpm.month1)) ), IFERROR(DATEVALUE(_xlpm.useMonth & " " & _xlpm.dayNum & ", " & 2025), "") ) -> 45682
A17: Total | B17: =SUM(C17:S17)+V17 -> 0 | R17: =SUM(R3:R14) -> 0 | S17: =SUM(S3:S14) -> 0 | U17: Total | V17: =SUM(W17:Y17) -> 0 | W17: =SUM(W3:W16) -> 0 | X17: =SUM(X3:X16) -> 0 | Y17: =SUM(Y3:Y14) -> 0
C18: =SUM(C3:C9) -> 0 | D18: =SUM(D3:D9)+AB17 -> 0 | E18: =SUM(E3:E9)+W17 -> 0 | F18: =SUM(F3:F9)+X17 -> 0 | G18: =SUM(G3:G9) -> 0 | H18: =SUM(H3:H9) -> 0 | I18: =SUM(I3:I10) -> 0 | J18: =SUM(J3:J9)+Y17 -> 15.5 | K18: =SUM(K3:K9)+Z17 -> 30.5 | L18: =SUM(L3:L9)+AA17 -> 0 | M18: =SUM(M3:M9)+AC17 -> 0 | N18: =SUM(N3:N9)+AD17 -> 0
C19: =SUM(C10:C16) -> 0 | D19: =SUM(D10:D16) -> 0 | E19: =SUM(E10:E16) -> 0 | F19: =SUM(F10:F16) -> 0 | G19: =SUM(G10:G16) -> 0 | H19: =SUM(H10:H16) -> 0 | I19: =SUM(I10:I16) -> 0 | J19: =SUM(J10:J16) -> 23.5 | ... N19: =SUM(N10:N16) -> 0 | T19: =T9+T16 -> 111.5
A20: Holiday Inn Express & Suites Victoria - Colwood 318 Wale Rd, Colwood, BC V9B 2W3 | U20: ADJUSTMENT
B21: =B2 -> Jan | C21: Aljhon | D21: Barkha | E21: Carmela | F21: Emily | G21: Hedi FD | H21: Jashan | I21: Mar | J21: Neeru | K21: Marvin | L21: Pedro | M21: Sheila | N21: Simrat
A22: Mon | B22: =B3 -> 12 | U22: Mon
A23: Tue | B23: =B4 -> 13 | U23: Tue
A24: Wed | B24: =B5 -> 14 | U24: Wed
A25: Thu | B25: =B6 -> 15 | U25: Thu
A26: Fri | B26: =B7 -> 16 | U26: Fri
A27: Sat | B27: =B8 -> 17 | U27: Sat
A28: Sun | B28: =B9 -> 18 | T28: =SUM(C22:S28) -> 0 | U28: Sun
A29: Mon | B29: =B10 -> 19 | U29: Mon
A30: Tue | B30: =B11 -> 20 | U30: Tue
A31: Wed | B31: =B12 -> 21 | U31: Wed
A32: Thu | B32: =B13 -> 22 | U32: Thu
A33: Fri | B33: =B14 -> 23 | U33: Fri
A34: Sat | B34: =B15 -> 24 | U34: Sat
A35: Sun | B35: =B16 -> 25 | T35: =SUM(C29:S35) -> 0 | U35: Sun
A36: Total | B36: =SUM(C36:S36)+V36 -> 0 | C36: =SUM(C22:C35) -> 0 | D36: =SUM(D22:D35) -> 0 | E36: =SUM(E22:E35) -> 0 | F36: =SUM(F22:F35) -> 0 | G36: =SUM(G22:G35) -> 0 | H36: =SUM(H22:H35) -> 0 | I36: =SUM(I22:I35) -> 0 | J36: =SUM(J22:J35) -> 0 | ... S36: =SUM(S22:S35) -> 0 | U36: Total | V36: =SUM(W36:Y36) -> 0 | W36: =SUM(W22:W33) -> 0 | X36: =SUM(X22:X33) -> 0 | Y36: =SUM(Y22:Y33) -> 0
C37: =SUM(C22:C28) -> 0 | D37: =SUM(D22:D28) -> 0 | E37: =SUM(E22:E28) -> 0 | F37: =SUM(F22:F28) -> 0 | G37: =SUM(G22:G28) -> 0 | H37: =SUM(H22:H28) -> 0 | I37: =SUM(I22:I28) -> 0 | J37: =SUM(J22:J28) -> 0 | ... N37: =SUM(N22:N28) -> 0 | T37: =SUM(A37:M37) -> 0
C38: =SUM(C29:C35) -> 0 | D38: =SUM(D29:D35) -> 0 | E38: =SUM(E29:E35) -> 0 | F38: =SUM(F29:F35) -> 0 | G38: =SUM(G29:G35) -> 0 | H38: =SUM(H29:H35) -> 0 | I38: =SUM(I29:I35) -> 0 | J38: =SUM(J29:J35) -> 0 | ... N38: =SUM(N29:N35) -> 0 | T38: =SUM(A38:M38) -> 0
A39: Motel 6 Saanichton, BC - Victoria Airport (2401 Mt Newton Cross Rd, Saanichton, BC V8M 1T8) | U39: ADJUSTMENT
B40: =B21 -> Jan | C40: Aljon | D40: Jose | E40: Mirzi | F40: JM | G40: Anthony | H40: Anmol | I40: Pedro | J40: Henry | K40: Haider | L40: Marica | M40: Lorraine | N40: Czarina | O40: Dante | P40: Rizzabelle | Q40: Marvin | R40: Emily
A41: Mon | B41: =B22 -> 12 | U41: Mon
A42: Tue | B42: =B23 -> 13 | U42: Tue
A43: Wed | B43: =B24 -> 14 | U43: Wed
A44: Thu | B44: =B25 -> 15 | U44: Thu
A45: Fri | B45: =B26 -> 16 | U45: Fri
A46: Sat | B46: =B27 -> 17 | U46: Sat
A47: Sun | B47: =B28 -> 18 | T47: =SUM(C41:S47) -> 0 | U47: Sun
A48: Mon | B48: =B29 -> 19 | U48: Mon
A49: Tue | B49: =B30 -> 20 | U49: Tue
A50: Wed | B50: =B31 -> 21 | U50: Wed
A51: Thu | B51: =B32 -> 22 | U51: Thu
A52: Fri | B52: =B33 -> 23 | U52: Fri
A53: Sat | B53: =B34 -> 24 | U53: Sat
A54: Sun | B54: =B35 -> 25 | T54: =SUM(C48:S54) -> 0 | U54: Sun
A55: Total | B55: =SUM(C55:S55)+V55 -> 0 | C55: =SUM(C41:C54) -> 0 | D55: =SUM(D41:D52) -> 0 | E55: =SUM(E41:E54) -> 0 | F55: =SUM(F41:F54) -> 0 | G55: =SUM(G41:G52) -> 0 | H55: =SUM(H41:H52) -> 0 | I55: =SUM(I41:I54) -> 0 | J55: =SUM(J41:J54) -> 0 | K55: =SUM(K41:K52) -> 0 | L55: =SUM(L41:L52) -> 0 | M55: =SUM(M41:M52) -> 0 | N55: =SUM(N41:N54) -> 0 | O55: =SUM(O41:O54) -> 0 | P55: =SUM(P41:P52) -> 0 | Q55: =SUM(Q41:Q52) -> 0 | R55: =SUM(R41:R52) -> 0 | S55: =SUM(S41:S52) -> 0 | U55: Total | V55: =SUM(W55:AM55)+AP55 -> 0 | W55: =SUM(W41:W54) -> 0 | X55: =SUM(X41:X52) -> 0 | Y55: =SUM(Y41:Y52) -> 0
C56: =SUM(C41:C47) -> 0 | D56: =SUM(D41:D47) -> 0 | E56: =SUM(E41:E47) -> 0 | F56: =SUM(F41:F47) -> 0 | G56: =SUM(G41:G47) -> 0 | H56: =SUM(H41:H47) -> 0 | I56: =SUM(I41:I47) -> 0 | J56: =SUM(J41:J47) -> 0 | ... S56: =SUM(S41:S47) -> 0
C57: =SUM(C48:C54) -> 0 | D57: =SUM(D48:D54) -> 0 | E57: =SUM(E48:E54) -> 0 | F57: =SUM(F48:F54) -> 0 | G57: =SUM(G48:G54) -> 0 | H57: =SUM(H48:H54) -> 0 | I57: =SUM(I48:I54) -> 0 | J57: =SUM(J48:J54) -> 0 | ... S57: =SUM(S48:S54) -> 0
A58: Queens Hotel (130-1110 Ewen Ave, New Westminster, BC V3M 5E4) | U58: ADJUSTMENT
B59: =B40 -> Jan | C59: Manmeet | D59: Mandeep | E59: Eduardo | F59: Sukhpreet | V59: July
A60: Mon | B60: =B41 -> 12 | C60: 6.5 | U60: Mon | V60: 14
A61: Tue | B61: =B42 -> 13 | C61: 6 | U61: Tue | V61: 15
A62: Wed | B62: =B43 -> 14 | U62: Wed | V62: 16
A63: Thu | B63: =B44 -> 15 | C63: 9 | U63: Thu | V63: 17
A64: Fri | B64: =B45 -> 16 | U64: Fri | V64: 18
A65: Sat | B65: =B46 -> 17 | U65: Sat | V65: 19
A66: Sun | B66: =B47 -> 18 | T66: =SUM(C60:S66) -> 21.5 | U66: Sun | V66: 20
A67: Mon | B67: =B48 -> 19 | U67: Mon | V67: 21
A68: Tue | B68: =B49 -> 20 | U68: Tue | V68: 22
A69: Wed | B69: =B50 -> 21 | U69: Wed | V69: 23
A70: Thu | B70: =B51 -> 22 | U70: Thu | V70: 24
A71: Fri | B71: =B52 -> 23 | U71: Fri | V71: 25
A72: Sat | B72: =B53 -> 24 | U72: Sat | V72: 26
A73: Sun | B73: =B54 -> 25 | T73: =SUM(C67:S73) -> 0 | U73: Sun | V73: 27
A74: Total | B74: =SUM(C74:S74)+V74 -> 21.5 | C74: =SUM(C60:C73) -> 21.5 | D74: =SUM(D60:D73) -> 0 | E74: =SUM(E60:E73) -> 0 | F74: =SUM(F60:F71) -> 0 | G74: =SUM(G60:G71) -> 0 | H74: =SUM(H60:H71) -> 0 | I74: =SUM(I60:I71) -> 0 | J74: =SUM(J60:J73) -> 0 | K74: =SUM(K60:K73) -> 0 | L74: =SUM(L60:L73) -> 0 | M74: =SUM(M60:M73) -> 0 | N74: =SUM(N60:N71) -> 0 | O74: =SUM(O60:O71) -> 0 | P74: =SUM(P60:P71) -> 0 | Q74: =SUM(Q60:Q71) -> 0 | R74: =SUM(R60:R71) -> 0 | S74: =SUM(S60:S71) -> 0 | U74: Total | V74: =SUM(W74:Y74) -> 0 | W74: =SUM(W60:W73) -> 0 | X74: =SUM(X60:X71) -> 0 | Y74: =SUM(Y60:Y71) -> 0
C75: =SUM(C60:C66) -> 21.5 | D75: =SUM(D60:D66) -> 0 | E75: =SUM(E60:E66) -> 0 | F75: =SUM(F60:F66) -> 0 | G75: =SUM(G60:G66) -> 0 | H75: =SUM(H60:H66) -> 0 | I75: =SUM(I60:I66) -> 0 | J75: =SUM(J60:J66) -> 0 | ... O75: =SUM(O60:O66) -> 0
C76: =SUM(C67:C73) -> 0 | D76: =SUM(D67:D73) -> 0 | E76: =SUM(E67:E73) -> 0 | F76: =SUM(F67:F73) -> 0 | G76: =SUM(G67:G73) -> 0 | H76: =SUM(H67:H73) -> 0 | I76: =SUM(I67:I73) -> 0 | J76: =SUM(J67:J73) -> 0 | ... O76: =SUM(O67:O73) -> 0
A77: Four Points Edmonton | U77: ADJUSTMENT
B78: =B59 -> Jan | C78: Ronald | V78: July | W78: Mandeep
A79: Mon | B79: =B60 -> 12 | U79: Mon | V79: 14
A80: Tue | B80: =B61 -> 13 | U80: Tue | V80: 15
A81: Wed | B81: =B62 -> 14 | U81: Wed | V81: 16
A82: Thu | B82: =B63 -> 15 | U82: Thu | V82: 17
A83: Fri | B83: =B64 -> 16 | U83: Fri | V83: 18
A84: Sat | B84: =B65 -> 17 | U84: Sat | V84: 19
A85: Sun | B85: =B66 -> 18 | T85: =SUM(C79:S85) -> 0 | U85: Sun | V85: 20
A86: Mon | B86: =B67 -> 19 | U86: Mon | V86: 21
A87: Tue | B87: =B68 -> 20 | U87: Tue | V87: 22
A88: Wed | B88: =B69 -> 21 | U88: Wed | V88: 23
A89: Thu | B89: =B70 -> 22 | U89: Thu | V89: 24
A90: Fri | B90: =B71 -> 23 | U90: Fri | V90: 25
A91: Sat | B91: =B72 -> 24 | U91: Sat | V91: 26
A92: Sun | B92: =B73 -> 25 | T92: =SUM(C86:S92) -> 0 | U92: Sun | V92: 27
A93: Total | B93: =SUM(C93:S93)+V93 -> 0 | C93: =SUM(C79:C92) -> 0 | D93: =SUM(D79:D92) -> 0 | E93: =SUM(E79:E92) -> 0 | F93: =SUM(F79:F90) -> 0 | G93: =SUM(G79:G90) -> 0 | H93: =SUM(H79:H90) -> 0 | I93: =SUM(I79:I90) -> 0 | J93: =SUM(J79:J92) -> 0 | K93: =SUM(K79:K92) -> 0 | L93: =SUM(L79:L92) -> 0 | M93: =SUM(M79:M92) -> 0 | N93: =SUM(N79:N90) -> 0 | O93: =SUM(O79:O90) -> 0 | P93: =SUM(P79:P90) -> 0 | Q93: =SUM(Q79:Q90) -> 0 | R93: =SUM(R79:R90) -> 0 | S93: =SUM(S79:S90) -> 0 | U93: Total | V93: =SUM(W93:Y93) -> 0 | W93: =SUM(W79:W92) -> 0 | X93: =SUM(X79:X90) -> 0 | Y93: =SUM(Y79:Y90) -> 0
C94: =SUM(C79:C85) -> 0 | D94: =SUM(D79:D85)+W93 -> 0 | E94: =SUM(E79:E85) -> 0 | F94: =SUM(F79:F85) -> 0 | G94: =SUM(G79:G85) -> 0 | H94: =SUM(H79:H85) -> 0 | I94: =SUM(I79:I85) -> 0 | J94: =SUM(J79:J85) -> 0 | K94: =SUM(K79:K85) -> 0 | L94: =SUM(L79:L85) -> 0 | ... O94: =SUM(O79:O85) -> 0
C95: =SUM(C86:C92) -> 0 | D95: =SUM(D86:D92) -> 0 | E95: =SUM(E86:E92) -> 0 | F95: =SUM(F86:F92) -> 0 | G95: =SUM(G86:G92) -> 0 | H95: =SUM(H86:H92) -> 0 | I95: =SUM(I86:I92) -> 0 | J95: =SUM(J86:J92) -> 0 | ... O95: =SUM(O86:O92) -> 0

Sheet COUNTER
C2: SHERIDAN BRAMPTON | K2: GRAPHIC PACKAGING (7830 TRANMERE DR, MISSISSAUGA) | T2: COUNTER
D5: December | E5: Time in | F5: Time out | G5: Calc | H5: Hours | I5: Break | L5: December | M5: Time in | N5: Time out | O5: Calc | P5: Hours | Q5: Break | U5: Oct-Nov | V5: Time in | W5: Time out | X5: Calc | Y5: Hours | Z5: NoBreak
C6: Sat | D6: 3 | G6: =TEXT(F6-E6,"h,m") -> 0,0 | K6: Sat | L6: 3 | O6: =TEXT(N6-M6,"h,m") -> 0,0 | T6: Sat | U6: 19 | V6: 0.39583333 | W6: 0.64583333 | X6: =(W6-V6)*24 -> 6 | Y6: =X6-0.5 -> 5.5 | AA6: 5.5
C7: Sun | D7: 4 | G7: =TEXT(F7-E7,"h,m") -> 0,0 | K7: Sun | L7: 4 | O7: =TEXT(N7-M7,"h,m") -> 0,0 | T7: Sun | U7: 20 | V7: 0.32638889 | W7: 0.6875 | X7: =(W7-V7)*24 -> 8.6666667 | Y7: =X7-0.5 -> 8.1666667 | AA7: 5.25
C8: Mon | D8: 5 | G8: =TEXT(F8-E8,"h,m") -> 0,0 | K8: Mon | L8: 5 | O8: =TEXT(N8-M8,"h,m") -> 0,0 | T8: Mon | U8: 21 | V8: 0.32986111 | W8: 0.66666667 | X8: =(W8-V8)*24 -> 8.0833333 | Y8: =X8-0.5 -> 7.5833333 | AA8: 7.5
C9: Tue | D9: 6 | G9: =TEXT(F9-E9,"h,m") -> 0,0 | K9: Tue | L9: 6 | O9: =TEXT(N9-M9,"h,m") -> 0,0 | T9: Tue | U9: 22 | X9: =(W9-V9)*24 -> 0
C10: Wed | D10: 7 | G10: =TEXT(F10-E10,"h,m") -> 0,0 | K10: Wed | L10: 7 | O10: =TEXT(N10-M10,"h,m") -> 0,0 | T10: Wed | U10: 23 | X10: =(W10-V10)*24 -> 0
C11: Thu | D11: 8 | G11: =TEXT(F11-E11,"h,m") -> 0,0 | K11: Thu | L11: 8 | O11: =TEXT(N11-M11,"h,m") -> 0,0 | T11: Thu | U11: 24 | X11: =(W11-V11)*24 -> 0
C12: Fri | D12: 9 | G12: =TEXT(F12-E12,"h,m") -> 0,0 | K12: Fri | L12: 9 | O12: =TEXT(N12-M12,"h,m") -> 0,0 | T12: Fri | U12: 25 | X12: =(W12-V12)*24 -> 0
C13: Sat | D13: 10 | G13: =TEXT(F13-E13,"h,m") -> 0,0 | K13: Sat | L13: 10 | O13: =TEXT(N13-M13,"h,m") -> 0,0 | T13: Sat | U13: 26 | X13: =(W13-V13)*24 -> 0
C14: Sun | D14: 11 | G14: =TEXT(F14-E14,"h,m") -> 0,0 | K14: Sun | L14: 11 | O14: =TEXT(N14-M14,"h,m") -> 0,0 | T14: Sun | U14: 27 | X14: =(W14-V14)*24 -> 0
C15: Mon | D15: 12 | G15: =TEXT(F15-E15,"h,m") -> 0,0 | K15: Mon | L15: 12 | O15: =TEXT(N15-M15,"h,m") -> 0,0 | T15: Mon | U15: 28 | X15: =(W15-V15)*24 -> 0
C16: Tue | D16: 13 | G16: =TEXT(F16-E16,"h,m") -> 0,0 | K16: Tue | L16: 13 | O16: =TEXT(N16-M16,"h,m") -> 0,0 | T16: Tue | U16: 29 | X16: =(W16-V16)*24 -> 0
C17: Wed | D17: 14 | G17: =TEXT(F17-E17,"h,m") -> 0,0 | K17: Wed | L17: 14 | O17: =TEXT(N17-M17,"h,m") -> 0,0 | T17: Wed | U17: 30 | X17: =(W17-V17)*24 -> 0
C18: Thu | D18: 15 | G18: =TEXT(F18-E18,"h,m") -> 0,0 | K18: Thu | L18: 15 | O18: =TEXT(N18-M18,"h,m") -> 0,0 | T18: Thu | U18: 31 | X18: =(W18-V18)*24 -> 0
C19: Fri | D19: 16 | G19: =TEXT(F19-E19,"h,m") -> 0,0 | K19: Fri | L19: 16 | O19: =TEXT(N19-M19,"h,m") -> 0,0 | T19: Fri | U19: 1 | X19: =(W19-V19)*24 -> 0
H20: =SUM(H6:H19) -> 0 | I20: =SUM(I6:I19) -> 0 | P20: =SUM(P6:P19) -> 0 | Q20: =SUM(Q6:Q19) -> 0
I21: =H20-I20 -> 0 | Q21: =P20-Q20 -> 0
T24: COUNTER
T26: Flordelyn
U27: Oct-Nov | V27: Time in | W27: Time out | X27: Calc | Y27: Break | Z27: NoBreak
T28: Sat | U28: 19 | V28: 0.38888889 | W28: 0.64583333 | X28: =(W28-V28)*24 -> 6.1666667 | Z28: =X28-Y28 -> 6.1666667 | AA28: =Z28+Z29 -> 11.916667
T29: Sun | U29: 20 | V29: 0.15625 | W29: 0.41666667 | X29: =(W29-V29)*24 -> 6.25 | Y29: 0.5 | Z29: =X29-Y29 -> 5.75
T30: Mon | U30: 21 | V30: 0.23611111 | W30: 0.44791667 | X30: =(W30-V30)*24 -> 5.0833333 | Y30: 0.5 | Z30: =X30-Y30 -> 4.5833333 | AA30: =Z30+Z31 -> 10.5
T31: Tue | U31: 22 | V31: 0.15625 | W31: 0.42361111 | X31: =(W31-V31)*24 -> 6.4166667 | Y31: 0.5 | Z31: =X31-Y31 -> 5.9166667
T32: Wed | U32: 23 | V32: 0.23611111 | W32: 0.45833333 | X32: =(W32-V32)*24 -> 5.3333333 | Y32: 0.5 | Z32: =X32-Y32 -> 4.8333333 | AA32: =Z32+Z33 -> 12
T33: Thu | U33: 24 | V33: 0.10763889 | W33: 0.42708333 | X33: =(W33-V33)*24 -> 7.6666667 | Y33: 0.5 | Z33: =X33-Y33 -> 7.1666667
T34: Fri | U34: 25 | V34: 0.23611111 | W34: 0.46527778 | X34: =(W34-V34)*24 -> 5.5 | Y34: 0.5 | Z34: =X34-Y34 -> 5 | AA34: =Z34+Z35 -> 13
T35: Sat | U35: 26 | V35: 0.11458333 | W35: 0.46875 | X35: =(W35-V35)*24 -> 8.5 | Y35: 0.5 | Z35: =X35-Y35 -> 8
T36: Sun | U36: 27 | V36: 0.11458333 | W36: 0.48263889 | X36: =(W36-V36)*24 -> 8.8333333 | Y36: 0.5 | Z36: =X36-Y36 -> 8.3333333
T37: Mon | U37: 28 | V37: 0.23611111 | W37: 0.47222222 | X37: =(W37-V37)*24 -> 5.6666667 | Y37: 0.5 | Z37: =X37-Y37 -> 5.1666667
T38: Tue | U38: 29 | X38: =TEXT(W38-V38,"h,m") -> 0,0
T39: Wed | U39: 30 | X39: =TEXT(W39-V39,"h,m") -> 0,0
T40: Thu | U40: 31 | X40: =TEXT(W40-V40,"h,m") -> 0,0
T41: Fri | U41: 1 | X41: =TEXT(W41-V41,"h,m") -> 0,0
T45: COUNTER
T47: Flordelyn
U48: Sept | V48: Time in | W48: Time out | X48: Calc | Y48: Break | Z48: NoBreak | AA48: August | AB48: Sub-Total | AC48: Total
U49: 8 | V49: 0.22916667 | W49: 0.45833333 | X49: =(W49-V49)*24 -> 5.5 | Z49: =X49-Y49 -> 5.5 | AA49: 5.5
U50: 9 | V50: 0.22916667 | W50: 0.47916667 | X50: =(W50-V50)*24 -> 6 | Z50: =X50-Y50 -> 6 | AA50: 6 | AG50: 6.5
U51: 10 | V51: 0.23263889 | W51: 0.48611111 | X51: =(W51-V51)*24 -> 6.0833333 | Z51: =X51-Y51 -> 6.0833333 | AA51: 6 | AG51: 9.5
U52: 11 | V52: 0.23263889 | W52: 0.46180556 | X52: =(W52-V52)*24 -> 5.5 | Z52: =X52-Y52 -> 5.5 | AA52: 8.75 | AG52: 8.25
U53: 11 | V53: 0.20138889 | W53: 0.30208333 | X53: =(W53-V53)*24 -> 2.4166667 | Z53: =X53-Y53 -> 2.4166667 | AG53: 10.5
U54: 12 | V54: 0.22916667 | W54: 0.44791667 | X54: =(W54-V54)*24 -> 5.25 | Z54: =X54-Y54 -> 5.25 | AA54: 10 | AG54: 11
U55: 12 | V55: 0.19444444 | W55: 0.375 | X55: =(W55-V55)*24 -> 4.3333333 | Z55: =X55-Y55 -> 4.3333333
U56: 13 | V56: 0.20138889 | W56: 0.42361111 | X56: =(W56-V56)*24 -> 5.3333333 | Z56: =X56-Y56 -> 5.3333333 | AA56: 5.25
U57: 14 | V57: 0.23263889 | W57: 0.47916667 | X57: =(W57-V57)*24 -> 5.9166667 | Z57: =X57-Y57 -> 5.9166667 | AA57: 5.75
X60: =(W60-V60)*24 -> 0
X61: =(W61-V61)*24 -> 0
X62: =(W62-V62)*24 -> 0

Sheet Interac Details
A1: Name | B1: Etransfer
A2: Aileen Dino I | B2: aileendino5@gmail.com
A3: Ajay Kumar | B3: ajverma0002@gmail.com
A4: Akin Babalola | B4: babalolaakin.a@gmail.com
A5: Alejandra Cristina Lugo Martinez | B5: alelugo2090@yahoo.com
A6: Ariadne Huesca Medina A | B6: alelugo2090@yahoo.com
A7: Amandeep Kaur | B7: amandeepkaurbrar0007@gmail.com
A8: Amrinder Singh | B8: davinderdeol255@gmail.com
A9: Andrea | B9: andreaguevarar1998@gmail.com
A10: Andrew Verches | B10: verchesandrew@yahoo.com
A11: AnIsha Touray Khanal | B11: anIsha Touraykhanal934@gmail.com
A12: Asmita Baral | B12: Asmitabadal28@gmail.com
... A26: Eduardo Abuel | B26: arabuel@yahoo.com
A27: Eleazar S. Cariaga
A28: Elisa Malunay | B28: elisamalunay456@gmail.com
A29: Elsie Ndobegang Zinkeng | B29: zinkengelsie1@gmail.com
A30: Emilio Libao | B30: emiliolibao@gmail.com
A31: Emily | B31: emendoza0131yahoo.com
A32: Emmanuel Owoichogbe Jesse | B32: Ihotu11@gmail.com
A33: Esau Miguel J. Bernardo | B33: bernardoesaumiguel@gmail.com
A34: Eunice Ndinda Sammy | B34: Eunice88sammy@gmail.com
A35: Florablanca Erika Aquino | B35: derechoflorablancaerika@gmail.com
A36: Florie Mae G. Semblante | B36: floriemaesemblante@gmail.com
A37: Florie Mae G. Semblante Y | B37: floriemaesemblante@gmail.com
A38: Florie Mae G. Semblante N | B38: floriemaesemblante@gmail.com
A39: Freda Asumadu | B39: fasumuda4@gmail.com
... A44: Harpreet Kaur | B44: Harpreetaujla2014@gmail.com
A45: Himaya James | B45: #N/A
A46: Hursulla Camara Da Rocha (Front Desk) | B46: hursulla_rocha@hotmail.com
A47: Ibrahim Adebayo | B47: ibrahimadebayo303030@gmail.com
A48: Ilona Diandra Igiraneza | B48: ilonaigira32@gmail.com
A49: Dheeraj Kumar I Sicat | B49: bernasicat@gmail.com
A50: Henry Guisalta | B50: irish.alva@yahoo.com
A51: Irish | B51: irish.alva@yahoo.com
A52: Jaimal Singh | B52: jaimals263@gmail.com
A53: Jamie Narvaez | B53: romano28jamie@gmail.com
A54: Jancel Gray Pineda | B54: jancelgraypineda@gmail.com
A55: Jandira Vissolela Pedro da Costa E | B55: jandy.cst@hotmail.com
A56: Jasbeer Kaur | B56: Kjasbeer366@gmail.com
A57: Jatin kumar | B57: jatin701528@gmail.com
A58: Jitesh Kumar | B58: ieltssynonyms@gmail.com
A59: Jonalyn Mercado
A60: Jonas Layug Macaspac | B60: Jonasmacaspac03@gmail.com
A61: José Antonio Martínez Rodríguez | B61: Jos.rodriguez2728@gmail.com
A62: Joselito Jr Cajandig | B62: jrcajandig1988@gmail.com
A63: Joselito Jr Cajandig R | B63: jrcajandig1988@gmail.com
A64: Joseph Miguel G. Lazaro | B64: migslaz@gmail.com
A65: Ujunwa Okwuaka (Bartender) | B65: ujuokwuaka1@gmail.com
A66: Ujunwa Okwuaka (Server) | B66: ujuokwuaka1@gmail.com
A67: Karan Pun Magar | B67: karanpoon30@gmail.com
A68: Ke-ann Olarte | B68: keanolarte10@gmail.com
A69: Khaled Rugamba | B69: khaledbabou3@gmail.com
A70: Komalpreet Kaur
A71: Kunal Dhiman | B71: kunaldhimankd.kd@gmail.com
A72: Leander | B72: leenelson014@gmail.com
A73: Jacqueline Arethea Ford-Bah L | B73: leenelson014@gmail.com
A74: Lilian Wamaitha Wanjiku | B74: wamaithalilian@gmail.com
A75: Lynsey Joy Arbolado | B75: lynseyarbolado03@gmail.com
A76: Maliha John | B76: malihajohn@hotmail.com
A77: Manjot Kaur | B77: Manjot51202@gmail.com
A78: Manuel Alejandro Uribe Adame | B78: alejandro.uribeadame@gmail.com
A79: Manuela Doloresse Njikam Nzeket | B79: manuelanjikam@gmail.com
A80: Maria Sydney Ortiz C | B80: sydneycagalawan@gmail.com
A81: Clyde | B81: sydneycagalawan@gmail.com
A82: Marina Pereira | B82: marinamateuspereira@gmail.com
... A91: Muhawenimana Angelique | B91: mpanoangel21@gmail.com
A92: Nabagala Viviannie Carolyne
A93: Nafisa Akter | B93: akternaf7@gmail.com
A94: Nancy Acen | B94: mbalirenancy@gmail.com
A95: Naneth Miro | B95: cainmiro81@gmail.com
A96: Naveed John M | B96: malihajohn@hotmail.com
A97: Nikhil Ghimire | B97: nikhilghimire44@gmail.com
A98: Njong Precious Eghah | B98: njongpreciouseghah@gmail.com
A99: Nonette Teta Shenge | B99: shengenigelle@gmail.com
A100: Nshimirimana Carine | B100: nshimirimanacarine22@gmail.com
A101: Nyinawase Merveille | B101: nyinawasemerveille@gmail.com
A102: Olave Akundwe | B102: olaveak@gmail.com
A103: Parneet Kaur | B103: parneetbrar302@gmail.com
A104: Parth Goswami | B104: parthgosai2033@gmail.com
... A118: Rijul Chauhan | B118: ritikagulati3000@gmail.com
A119: RIsha Touraybh Bumb
A120: RIsha Touraybh RIsha Touraybh | B120: rIsha Touraybh22ji.s@gmail.com
A121: Roshana Jade McLeod
A122: Ruby Bernal | B122: mandayrhoda30@gmail.com
A123: Ruby Bernal R | B123: mandayrhoda30@gmail.com
A124: Samjhana Chapagain | B124: samjhanachapa@gmail.com
A125: Samson Doca Asuncion | B125: sam_asuncion42@yahoo.com
A126: Sayeedah Hashimi | B126: Sayeedah.hashimi@gmail.com
A127: Sherilyn Taghoy | B127: valdez655@yahoo.com
A128: Sheryl Policarpio | B128: sheryl11taz@yahoo.com
A129: Simon Waweru | B129: S.chege18@yahoo.com
A130: Simranjit Kaur | B130: simrankaur77105@gmail.com
A131: Sumanpreet Kaur | B131: sumanpreet90d@gmail.com
A132: Suraj Paudel | B132: surajpoudel2525@gmail.com
A133: Suzan Bitici | B133: suzanbitici@gmail.com
... A137: Valia Deosingh | B137: sdeosingh44@gmail.com
A138: Vraj Soni
A139: William Gateru Ngure | B139: ngure44@gmail.com
A140: Yvonne Wanjiru (HK) | B140: ywagio@gmail.com
A141: Yvonne Wanjiru (SV) | B141: ywagio@gmail.com
...

Sheet PRINT (2)
B1: CLEANERS/HOUSEKEEPERS PAY PERIOD DECEMBER 03 - 16 | C1: HOURS | D1: TYPE | E1: RATE | F1: TOTAL | G1: HOTELS/OFFICES
A2: 1 | B2: Alberto | C2: =GTA!#REF! -> #REF! | D2: SUBCON | E2: 16 | F2: =C2*E2 -> #REF! | G2: HAMPTON INN (BURLINGTON)
A3: =A2+1 -> 2 | B3: Czarina | C3: =GTA!#REF! -> #REF! | D3: SUBCON | E3: 16 | F3: =C3*E3 -> #REF! | G3: HAMPTON INN (BURLINGTON)
A4: =A3+1 -> 3 | B4: Faith | C4: December 16 - 30 | D4: SALARY | G4: 2255 DUNDAS ST WEST
A5: =A4+1 -> 4 | B5: Jessica Erika Mae Sablas | C5: December 16 - 30 | D5: SALARY | G5: 2255 DUNDAS ST WEST
A6: =A5+1 -> 5 | B6: Junel Ibalig | C6: ='OUTSIDE GTA'!K233 -> 0 | D6: SUBCON | E6: 16 | F6: =C6*E6 -> 0 | G6: FOUR POINTS HAMILTON
A7: =A6+1 -> 6 | B7: Kirsten Carmel Ricacho | C7: December 16 - 30 | D7: SALARY | G7: 2255 DUNDAS ST WEST
A8: =A7+1 -> 7 | B8: Lesley Ann | C8: =GTA!#REF! -> #REF! | D8: SUBCON | E8: 16 | F8: =C8*E8 -> #REF! | G8: HAMPTON INN (BURLINGTON)
A9: =A8+1 -> 8 | B9: Maqueen | C9: =GTA!#REF! -> #REF! | D9: SUBCON | E9: 16 | F9: =C9*E9 -> #REF! | G9: HAMPTON INN (BURLINGTON)
A10: =A9+1 -> 9 | B10: Marilyn | C10: =GTA!#REF! -> #REF! | D10: SUBCON | E10: 17 | F10: =C10*E10 -> #REF! | G10: RADISSON (55 HALLCROWN PL, NORTH YORK)
A11: =A10+1 -> 10 | B11: Mary Jasmine Dalapo | C11: December 16 - 30 | D11: SALARY | G11: 2255 DUNDAS ST WEST
A12: =A11+1 -> 11 | B12: Miajoy | C12: December 16 - 30 | D12: SALARY | G12: 2255 DUNDAS ST WEST
A13: =A12+1 -> 12 | B13: Michael | C13: =GTA!#REF! -> #REF! | D13: SUBCON | E13: 16 | F13: =C13*E13 -> #REF! | G13: HAMPTON INN (BURLINGTON)
A14: =A13+1 -> 13 | B14: Nickson | C14: =GTA!#REF! -> #REF! | D14: SUBCON | E14: 16 | F14: =C14*E14 -> #REF! | G14: HOMEWOOD SUITES (MARKHAM)
A15: =A14+1 -> 14 | B15: Nickson | C15: =GTA!#REF! -> #REF! | D15: SUBCON | E15: 16 | F15: =C15*E15 -> #REF! | G15: SHERATON PARKWAY (RICHMOND HILL)
A16: =A15+1 -> 15 | B16: Patricia Mbombo Kapinga | C16: =OTTAWA!#REF!+OTTAWA!#REF!+OTTAWA!#REF! -> #REF! | D16: SUBCON | E16: 16 | F16: =C16*E16 -> #REF! | G16: BEST WESTERN PLUS OTTAWA
A17: =A16+1 -> 16 | B17: Sofiane Ismail | C17: =OTTAWA!#REF! -> #REF! | D17: SUBCON | E17: 16 | F17: =C17*E17 -> #REF! | G17: BEST WESTERN PLUS OTTAWA
A18: =A17+1 -> 17 | B18: Tara | C18: ='OUTSIDE GTA'!F544 -> 0 | D18: SUBCON | E18: 16.5 | F18: =C18*E18 -> 0 | G18: BEST WESTERN PLUS ORANGEVILLE
E19: TOTAL: | F19: =SUM(F2:F18) -> #REF!
F20: =ROUND(#REF!-#REF!-'PRINT (2)'!F19,5) -> #REF!

Sheet PRINT (3)
A1: Ace Magtulis | B1: 25.5 | C1: 16 | D1: 408 | E1: THE OAKES HOTEL
A2: Adonis Dial Vergara (for Don) | B2: 8 | C2: 16 | D2: 128 | E2: SHERATON PARKWAY (RICHMOND HILL)
A3: Adriana Michelle Vazquez Martinez | B3: 60 | C3: 19 | D3: 1140 | E3: RADISSON (640 DIXON RD, TORONTO AIRPORT)
A4: Akin Babalola | B4: 44.5 | C4: 16 | D4: 712 | E4: DAYS INN OTTAWA - WEST
A5: Andrew Verches | B5: 8 | C5: 16 | D5: 128 | E5: HOLIDAY INN EXPRESS - RICHMOND HILL
A6: Ange Marie Uwimana | B6: 15 | C6: 15.5 | D6: 232.5 | E6: DAYS INN OTTAWA - WEST
A7: Ange Marie Uwimana | B7: 38.5 | C7: 15.5 | D7: 596.75 | E7: BEST WESTERN PLUS OTTAWA
A8: Anjelo L. Olivar | B8: 24 | C8: 16 | D8: 384 | E8: THE OAKES HOTEL
A9: Anthony Frias | B9: 60 | C9: 18 | D9: 1080 | E9: KNIGHTS INN (22 METROPOLITAN RD, SCARBOROUGH)
A10: Arliz Salas | B10: 72 | C10: 16 | D10: 1152 | E10: SENECA 13980 DUFFERIN ST KING CITY
A11: Baldeep Singh Baring (for Rajdeep PLUS 45.54 Uber Orangeville PLUS 9hrs Nov 24) | B11: 41 | C11: 16 | D11: 701.54 | E11: COURTYARD | MARRIOTT TORONTO MISSISSAUGA WEST (290 DERRY ROAD W)
A12: Baldeep Singh Baring (for Rajdeep) | B12: 8 | C12: 16 | D12: 128 | E12: FOUR POINTS BY SHERATON
... A23: Deepakkumar Nanubhai Patel | B23: 45 | C23: 15.5 | D23: 697.5 | E23: DAYS INN OTTAWA - WEST
A24: Emily Mendoza | B24: January 1 - 15 | D24: 2250 | E24: CRH CANADA
A25: Emily Mendoza | B25: January 1 - 15 | D25: 1100 | E25: SKYWARD BUSINESS CENTER - CLEANER
A26: Ericka Marcuap | B26: 8 | C26: 16 | D26: 128 | E26: HOLIDAY INN EXPRESS - RICHMOND HILL
A27: Erwin Obico Uchi | B27: Dec 17 - 30 | D27: 200 | E27: EXP CAMBRIDGE
A28: Feluvin Macasiljig | B28: 8 | C28: 16 | D28: 128 | E28: RIVER RAPIDS INN
A29: Gemmalyn Dungca | B29: 8 | C29: 16 | D29: 128 | E29: RIVER RAPIDS INN
A30: Gerome Balote (PLUS $7.76 DOUBLE FARE,9 DAY/S) | B30: 72.75 | C30: 16 | D30: 1233.84 | E30: HOMEWOOD SUITES/HAMPTON INN (MARKHAM)
A31: Gia Angelica Pasion | B31: 48 | C31: 16 | D31: 768 | E31: RESIDENCE INN (MISSISSAUGA)
A32: Giladio Cafe (for Raynan) | B32: 8 | C32: 18 | D32: 144 | E32: KNIGHTS INN (22 METROPOLITAN RD, SCARBOROUGH)
A33: Giladio Cafe (for Raynan) | B33: 8 | C33: 16 | D33: 128 | E33: SHERATON PARKWAY (RICHMOND HILL)
A34: Gilbert Ada Ogaro | B34: 16 | C34: 16 | D34: 256 | E34: SENECA 13980 DUFFERIN ST KING CITY
A35: Girlie Casanova Diala | B35: 5.25 | C35: 16 | D35: 84 | E35: DAYS INN OTTAWA - WEST
A36: Glynnet D. Emata | B36: 42 | C36: 16 | D36: 672 | E36: THE OAKES HOTEL
A37: Gora Kane | B37: 4.25 | C37: 16 | D37: 68 | E37: DAYS INN OTTAWA - WEST
A38: Grace Araneta (for Rey) (PLUS $7.76 DOUBLE FARE, 9 DAY/S) | B38: 72 | C38: 16 | D38: 1221.84 | E38: HOMEWOOD SUITES/HAMPTON INN (MARKHAM)
A39: Gregorio Pleto | B39: 18 | C39: 16 | D39: 288 | E39: CLARKSON VILLAGE MOTEL
... A77: Lynsey Joy Arbolado | B77: 15.5 | C77: 16 | D77: 248 | E77: SHERATON FOUR POINTS (VAUGHAN)
A78: Mae Aragon | B78: January 1 - 15 | D78: 750 | E78: 2255 DUNDAS ST WEST
A79: Maria Rosario Meneses (PLUS $8.76/DAY DOUBLE FARE, 7 DAY/S) | B79: 56 | C79: 16 | D79: 957.32 | E79: HOLIDAY INN EXPRESS - RICHMOND HILL
A80: Marlou Busel (for Joy Raluta) | B80: 75.5 | C80: 18 | D80: 1359 | E80: KNIGHTS INN (22 METROPOLITAN RD, SCARBOROUGH)
A81: Marlyn Del Rosario | B81: 14 | C81: 16 | D81: 224 | E81: HOLIDAY INN EXPRESS KINGSTON W
A82: Michael Columbres (for Martie) | B82: 45 | C82: 16 | D82: 720 | E82: RIVER RAPIDS INN
A83: Mike Champion Ingabire | B83: 32.75 | C83: 16 | D83: 524 | E83: THE OAKES HOTEL
A84: Naveed John (for Mursal) | B84: 50.5 | C84: 16 | D84: 808 | E84: HOMEWOOD SUITES AJAX
A85: Nellie Dionio (PLUS $7.76/DAY DOUBLE FARE, 1 DAY/S) | B85: 8 | C85: 16 | D85: 135.76 | E85: HOMEWOOD SUITES/HAMPTON INN (MARKHAM)
A86: Norlie Allanic | B86: 48 | C86: 16 | D86: 768 | E86: SHERIDAN OAKVILLE
A87: Oscar Uribe (for Scarlett) | B87: 30.37 | C87: 16 | D87: 485.92 | E87: HAMPTON INN - BRANTFORD
A88: Oussena Issam Ferjani | B88: 8 | C88: 16 | D88: 128 | E88: HOMEWOOD SUITES/HAMPTON INN (MARKHAM)
A89: Paramjeet Kaur (PLUS 8hrs October 30) | B89: 16 | C89: 16 | D89: 256 | E89: THE OAKES HOTEL
A90: Patricia Mbombo Kapinga | B90: 50.75 | C90: 16 | D90: 812 | E90: BEST WESTERN PLUS OTTAWA
... A111: Veerpal Kaur | B111: 10.5 | C111: 16 | D111: 168 | E111: THE OAKES HOTEL
A112: Viendolyn Autor | B112: January 1 - 15 | D112: 500 | E112: UofT PRESS JOURNALS 5201 DUFFERIN ST
A113: Zeba Imtiyaj Hafiz | B113: 5.5 | C113: 16 | D113: 88 | E113: COURTYARD | MARRIOTT TORONTO MISSISSAUGA WEST (290 DERRY ROAD W)
A114: Sofia | B114: 56 | C114: 17.5 + HST | D114: 1107.4 | E114: SHERIDAN OAKVILLE
A115: Grecia | B115: 70 | C115: 17.5 + HST | D115: 1384.25 | E115: BEST WESTERN PREMIER CARLINGVIEW
A116: Karet | B116: 64 | C116: 17.5 + HST | D116: 1265.6 | E116: BEST WESTERN PREMIER CARLINGVIEW
A117: MC Painting and Cleaning Services | B117: 190hrs | C117: 17.5+HST | D117: 3757.25

Sheet Sheet1

Sheet Payroll Instructions
A1: Date | B1: Name | C1: Remarks | D1: OK?

Sheet DRAFT SUM
A1: NO. | B1: CLEANERS/HOUSEKEEPERS PAY PERIOD SEPTEMBER 10 - SEPTEMBER 23 | C1: HOURS | D1: RATE | E1: TOTAL | F1: HOTEL ASSIGNMENT
A2: 1 | B2: AIDEN - Melanie Garcia | E2: =C2*D2 -> 0 | F2: BEST WESTERN PLUS CAMBRIDGE
A3: =A2+1 -> 2 | B3: AILEEN | E3: =C3*D3 -> 0 | F3: HOLIDAY INN EXPRESS - RICHMOND HILL (10 East Pearce St.)
A4: =A3+1 -> 3 | B4: AKIN BABALOLA | D4: 16 | E4: =C4*D4 -> 0 | F4: DAYS INN OTTAWA WEST (350 MOODIE DR, OTTAWA)
A5: =A4+1 -> 4 | B5: ALBERTO | E5: =C5*D5 -> 0 | F5: HAMPTON INN - BURLINGTON (1215 APPLEBY LINE, BURLINGTON)
A6: =A5+1 -> 5 | B6: ALEJANDRA CRISTINA LUGO MARTINEZ | E6: =C6*D6 -> 0 | F6: RADISSON (55 HALLCROWN PL, NORTHYORK)
A7: =A6+1 -> 6 | B7: ALJHEN CHRISTINE MORENO | E7: =C7*D7 -> 0 | F7: SPRINGHILL SUITES - MARRIOTT (612 APPLEWOOD CRES, VAUGHAN)
A8: =A7+1 -> 7 | B8: AMAN | E8: =C8*D8 -> 0 | F8: FOUR POINTS BY SHERATON (6257 AIRPORT AIRPORT RD, MISSISSAUGA)
B9: AMAN | E9: =C9*D9 -> 0 | F9: HILTON GARDEN INN - AIRPORT / STEELES (2648 STEELES AVE E, BRAMPTON)
A10: =A8+1 -> 8 | B10: AMARY TOLENTINO | E10: =C10*D10 -> 0 | F10: COURTYARD | MARRIOTT TORONTO AIRPORT (231 CARLINGVIEW DR)
A11: =A10+1 -> 9 | B11: ANA | E11: =C11*D11 -> 0 | F11: RESIDENCE AND CONFERENCE CENTRE
A12: =A11+1 -> 10 | B12: ANDREIUS ABARA | E12: =C12*D12 -> 0 | F12: SHERATON PARKWAY (600 HIGHWAY 7, RICHMOND HILL)
A13: =A12+1 -> 11 | B13: ANDREW VERCHES | E13: =C13*D13 -> 0 | F13: SPRINGHILL SUITES - MARRIOTT (612 APPLEWOOD CRES, VAUGHAN)
A14: =A13+1 -> 12 | B14: ANGELICA | D14: 16 | E14: =C14*D14 -> 0 | F14: DAYS INN OTTAWA WEST (350 MOODIE DR, OTTAWA)
A15: =A14+1 -> 13 | B15: ANITA MADHAR | E15: =C15*D15 -> 0 | F15: HILTON GARDEN INN - TORONTO - BRAMPTON (TOMKEN & STEELES, 200 STEELWELL RD, BRAMPTON)
A16: =A15+1 -> 14 | B16: APRIL | E16: =C16*D16 -> 0 | F16: RESIDENCE INN (2145 N SHERIDAN WAY, MISSISSAUGA)
A17: =A16+1 -> 15 | B17: ARYS ALEKCI SULABO | E17: =C17*D17 -> 0 | F17: HOMEWOOD SUITES - HILTON (50 BODRINGTON CT, MARKHAM)
A18: =A17+1 -> 16 | B18: AWAIS - MARY ANN BARNUEVO | E18: =C18*D18 -> 0 | F18: SPRINGHILL SUITES - MARRIOTT (612 APPLEWOOD CRES, VAUGHAN)
A19: =A18+1 -> 17 | B19: BRYZZEL GERONIMO | E19: =C19*D19 -> 0 | F19: BEST WESTERN PLUS (38 ESTATE DRIVE, SCARBOROUGH)
B20: BRYZZEL GERONIMO | E20: =C20*D20 -> 0 | F20: HOLIDAY INN EXPRESS - RICHMOND HILL (10 East Pearce St.)
A21: =A19+1 -> 18 | B21: CARLOS HUMBERTO CAMELO RAMIREZ | D21: 16 | E21: =C21*D21 -> 0 | F21: DAYS INN OTTAWA WEST (350 MOODIE DR, OTTAWA)
A22: =A21+1 -> 19 | B22: CHARMAINE | E22: =C22*D22 -> 0 | F22: HOMEWOOD SUITES - HILTON (50 BODRINGTON CT, MARKHAM)
A23: =A22+1 -> 20 | B23: CIRSTY | E23: =C23*D23 -> 0 | F23: HOMEWOOD SUITES - HILTON (50 BODRINGTON CT, MARKHAM)
A24: =A23+1 -> 21 | B24: CORELIE - MARIA ANNA OBIEN CASTRO | E24: =C24*D24 -> 0 | F24: BEST WESTERN PLUS CAMBRIDGE
A25: =A24+1 -> 22 | B25: CZARINA | E25: =C25*D25 -> 0 | F25: HAMPTON INN - BURLINGTON (1215 APPLEBY LINE, BURLINGTON)
A26: =A25+1 -> 23 | B26: DANNY LEILA ITERITEKA | D26: 16 | E26: =C26*D26 -> 0 | F26: DAYS INN OTTAWA WEST (350 MOODIE DR, OTTAWA)
A27: =A26+1 -> 24 | B27: DAPHNE | D27: 16 | E27: =C27*D27 -> 0 | F27: DAYS INN OTTAWA WEST (350 MOODIE DR, OTTAWA)
A28: =A27+1 -> 25 | B28: DARYLL | E28: =C28*D28 -> 0 | F28: SANDMANN HAMILTON
A29: =A28+1 -> 26 | B29: DAVINDER | E29: =C29*D29 -> 0 | F29: CLARKSON VILLAGE MOTEL (1815 LAKESHORE RD, MISSISSAUGA)
B30: DAVINDER | E30: =C30*D30 -> 0 | F30: COURTYARD | MARRIOTT TORONTO MISSISSAUGA WEST (290 DERRY ROAD W)
A31: =A29+1 -> 27 | B31: DIANNA M. | D31: 16 | E31: =C31*D31 -> 0 | F31: HOMEWOOD SUITES - AJAX (600 BECK CRESCENT, AJAX)
B32: DIANNA M. | E32: =C32*D32 -> 0 | F32: SHERATON PARKWAY (600 HIGHWAY 7, RICHMOND HILL)
A33: =A31+1 -> 28 | B33: DIANNE H. | E33: =C33*D33 -> 0 | F33: SHERIDAN OAKVILLE
A34: =A33+1 -> 29 | B34: DIANNE P. - MELANIE GARCIA | E34: =C34*D34 -> 0 | F34: BEST WESTERN PLUS CAMBRIDGE
A35: =A34+1 -> 30 | B35: DIANE T - MELANIE GARCIA | E35: =C35*D35 -> 0 | F35: BEST WESTERN PLUS CAMBRIDGE
B36: DIANE T - MELANIE GARCIA | E36: =C36*D36 -> 0 | F36: SHERATON FOUR POINTS CAMBRIDGE
A37: =A35+1 -> 31 | B37: DIGVIJAYSINH B LADEJA | E37: =C37*D37 -> 0 | F37: FOUR POINTS BY SHERATON (6257 AIRPORT AIRPORT RD, MISSISSAUGA)
A38: =A37+1 -> 32 | B38: DIRK BRANDON LAPITAN | D38: 16 | E38: =C38*D38 -> 0 | F38: DAYS INN OTTAWA WEST (350 MOODIE DR, OTTAWA)
A39: =A38+1 -> 33 | B39: DIVYASH KAPUR | E39: =C39*D39 -> 0 | F39: RADISSON (55 HALLCROWN PL, NORTHYORK)
A40: =A39+1 -> 34 | B40: DONDON BERNABEE | E40: =C40*D40 -> 0 | F40: MAGNA 90 SNIDERCROFT
A41: =A40+1 -> 35 | B41: EDIA | E41: =C41*D41 -> 0 | F41: HAMPTON INN - BURLINGTON (1215 APPLEBY LINE, BURLINGTON)
A42: =A41+1 -> 36 | B42: EILEEN - WINNIELYN GARCIA | E42: =C42*D42 -> 0 | F42: BEST WESTERN PLUS CAMBRIDGE
A43: =A42+1 -> 37 | B43: ELLA ELLINE | D43: 16 | E43: =C43*D43 -> 0 | F43: DAYS INN OTTAWA WEST (350 MOODIE DR, OTTAWA)
A44: =A43+1 -> 38 | B44: EMILY MENDOZA | E44: =C44*D44 -> 0 | F44: CRH CANADA
A45: =A44+1 -> 39 | B45: EMMANUEL | D45: 16 | E45: =C45*D45 -> 0 | F45: DAYS INN OTTAWA WEST (350 MOODIE DR, OTTAWA)
A46: =A45+1 -> 40 | B46: ERWIN OBICO UCHI | E46: =C46*D46 -> 0 | F46: EXP CAMBRIDGE
A47: =A46+1 -> 41 | B47: EVER | E47: =C47*D47 -> 0 | F47: BEST WESTERN PLUS CAMBRIDGE
A48: =A47+1 -> 42 | B48: FAITH DELA CRUZ | E48: =C48*D48 -> 0 | F48: 2255 DUNDAS
B49: FAITH DELA CRUZ | E49: =C49*D49 -> 0 | F49: SKYWARD BUSINESS CENTER
A50: =A48+1 -> 43 | B50: FRANCISCA - Juan Pablo Gutierrez Sagredo | E50: =C50*D50 -> 0 | F50: DAYS INN OTTAWA - DOWNTOWN (319 RIDEAU ST, OTTAWA)
A51: =A50+1 -> 44 | B51: GAGANDEEP SINGH | E51: =C51*D51 -> 0 | F51: FOUR POINTS BY SHERATON (6257 AIRPORT AIRPORT RD, MISSISSAUGA)
A52: =A51+1 -> 45 | B52: OLADELE GBENGA | E52: =C52*D52 -> 0 | F52: FOUR POINTS BY SHERATON (6257 AIRPORT AIRPORT RD, MISSISSAUGA)
B53: OLADELE GBENGA | E53: =C53*D53 -> 0 | F53: HILTON GARDEN INN - AIRPORT / STEELES (2648 STEELES AVE E, BRAMPTON)
A54: =A52+1 -> 46 | B54: GEROME | E54: =C54*D54 -> 0 | F54: HOMEWOOD SUITES - HILTON (50 BODRINGTON CT, MARKHAM)
A55: =A54+1 -> 47 | B55: GIRLIE CASANOVA DIALA | E55: =C55*D55 -> 0 | F55: DAYS INN OTTAWA - DOWNTOWN (319 RIDEAU ST, OTTAWA)
B56: GIRLIE CASANOVA DIALA | D56: 16 | E56: =C56*D56 -> 0 | F56: DAYS INN OTTAWA WEST (350 MOODIE DR, OTTAWA)
A57: =A55+1 -> 48 | B57: GLORIA | D57: 16 | E57: =C57*D57 -> 0 | F57: HAMPTON INN - BURLINGTON (1215 APPLEBY LINE, BURLINGTON)
A58: =A57+1 -> 49 | B58: GREGORIO PLETO | E58: =C58*D58 -> 0 | F58: RESIDENCE INN (2145 N SHERIDAN WAY, MISSISSAUGA)
A59: =A58+1 -> 50 | B59: GURPINDER KAUR | E59: =C59*D59 -> 0 | F59: COMFORT HOTEL (445 REXDALE BLVD, ETOBICOKE)
A60: =A59+1 -> 51 | B60: HARLAN - KAREL JOHN GUMAPAS | E60: =C60*D60 -> 0 | F60: HOLIDAY INN EXPRESS - WHITBY (180 CONSUMERS DR, WHITBY)
B61: HARLAN - KAREL JOHN GUMAPAS | D61: 16 | E61: =C61*D61 -> 0 | F61: HOMEWOOD SUITES - AJAX (600 BECK CRESCENT, AJAX)
A62: =A60+1 -> 52 | B62: HERSY | E62: =C62*D62 -> 0 | F62: HAMPTON INN - BURLINGTON (1215 APPLEBY LINE, BURLINGTON)
A63: =A62+1 -> 53 | B63: JACKIE | D63: 16 | E63: =C63*D63 -> 0 | F63: HOMEWOOD SUITES - AJAX (600 BECK CRESCENT, AJAX)
B64: JACKIE | E64: =C64*D64 -> 0 | F64: SHERATON PARKWAY (600 HIGHWAY 7, RICHMOND HILL)
A65: =A63+1 -> 54 | B65: JANE | D65: 16 | E65: =C65*D65 -> 0 | F65: DAYS INN OTTAWA WEST (350 MOODIE DR, OTTAWA)
A66: =A65+1 -> 55 | B66: JASHAN TURNA - JASHANPREET KAUR | E66: =C66*D66 -> 0 | F66: SHERIDAN BRAMPTON
B67: JASHAN TURNA - JASHANPREET KAUR | E67: =C67*D67 -> 0 | F67: BEST WESTERN PREMIER CARLINGVIEW (135 CARLINGVIEW DR)
B68: JASHAN TURNA - JASHANPREET KAUR | E68: =C68*D68 -> 0 | F68: HILTON GARDEN INN - TORONTO - BRAMPTON (TOMKEN & STEELES, 200 STEELWELL RD, BRAMPTON)
B69: JASHAN TURNA - JASHANPREET KAUR | E69: =C69*D69 -> 0 | F69: SPRINGHILL SUITES - MARRIOTT (612 APPLEWOOD CRES, VAUGHAN)
A70: =A66+1 -> 56 | B70: JAY | E70: =C70*D70 -> 0 | F70: SPRINGHILL SUITES - MARRIOTT (612 APPLEWOOD CRES, VAUGHAN)
A71: =A70+1 -> 57 | B71: JAYDEV VAISHNAV | E71: =C71*D71 -> 0 | F71: GIVE AND GO 415 RAILSIDE DR BRAMPTON
B72: JAYDEV VAISHNAV | E72: =C72*D72 -> 0 | F72: COURTYARD | MARRIOTT TORONTO MISSISSAUGA WEST (290 DERRY ROAD W)
B73: JAYDEV VAISHNAV | E73: =C73*D73 -> 0 | F73: HILTON GARDEN INN - AIRPORT / STEELES (2648 STEELES AVE E, BRAMPTON)
A74: =A71+1 -> 58 | B74: JAYNA | E74: =C74*D74 -> 0 | F74: RESIDENCE INN (2145 N SHERIDAN WAY, MISSISSAUGA)
A75: =A74+1 -> 59 | B75: JEANIELYN JALLORINA | E75: =C75*D75 -> 0 | F75: COMFORT INN (8330 WOODBINE AVE)
B76: JEANIELYN JALLORINA | E76: =C76*D76 -> 0 | F76: HOMEWOOD SUITES - HILTON (50 BODRINGTON CT, MARKHAM)
A77: =A75+1 -> 60 | B77: JEFFREY | E77: =C77*D77 -> 0 | F77: SHERIDAN OAKVILLE
A78: =A77+1 -> 61 | B78: JENNY RULLODA | D78: 16 | E78: =C78*D78 -> 0 | F78: DAYS INN OTTAWA WEST (350 MOODIE DR, OTTAWA)
A79: =A78+1 -> 62 | B79: JENNYLYN - JASMIN R. PAJALLA | E79: =C79*D79 -> 0 | F79: DAYS INN OTTAWA - DOWNTOWN (319 RIDEAU ST, OTTAWA)
A80: =A79+1 -> 63 | B80: JEREMIE LEWIS LAMADELINE | D80: 16 | E80: =C80*D80 -> 0 | F80: DAYS INN OTTAWA WEST (350 MOODIE DR, OTTAWA)
A81: =A80+1 -> 64 | B81: JERICK PARASO | E81: =C81*D81 -> 0 | F81: HOMEWOOD SUITES - HILTON (50 BODRINGTON CT, MARKHAM)
A82: =A81+1 -> 65 | B82: JERONE DE VILLA | D82: 16 | E82: =C82*D82 -> 0 | F82: HOMEWOOD SUITES - AJAX (600 BECK CRESCENT, AJAX)
A83: =A82+1 -> 66 | B83: JESSICA ERIKA MAE SABLAS | E83: =C83*D83 -> 0 | F83: 2255 DUNDAS
B84: JESSICA ERIKA MAE SABLAS | E84: =C84*D84 -> 0 | F84: SKYWARD BUSINESS CENTER
A85: =A83+1 -> 67 | B85: JILIAN - JOCELYN REYNO | E85: =C85*D85 -> 0 | F85: BEST WESTERN PLUS CAMBRIDGE
A86: =A85+1 -> 68 | B86: JOANNA | E86: =C86*D86 -> 0 | F86: SHERIDAN OAKVILLE
A87: =A86+1 -> 69 | B87: JO-ANNE | E87: =C87*D87 -> 0 | F87: BEST WESTERN PLUS CAMBRIDGE
A88: =A87+1 -> 70 | B88: JOHN EDMAR MARTINEZ | E88: =C88*D88 -> 0 | F88: DAYS INN OTTAWA - DOWNTOWN (319 RIDEAU ST, OTTAWA)
A89: =A88+1 -> 71 | B89: JOHN NEIL CASANOVA | E89: =C89*D89 -> 0 | F89: DAYS INN OTTAWA - DOWNTOWN (319 RIDEAU ST, OTTAWA)
B90: JOHN NEIL CASANOVA | D90: 16 | E90: =C90*D90 -> 0 | F90: DAYS INN OTTAWA WEST (350 MOODIE DR, OTTAWA)
A91: =A89+1 -> 72 | B91: JOHN PATRICK - CHESTER VINCENT GONZALES | E91: =C91*D91 -> 0 | F91: DAYS INN OTTAWA - DOWNTOWN (319 RIDEAU ST, OTTAWA)
A92: =A91+1 -> 73 | B92: JONAN SALAS | E92: =C92*D92 -> 0 | F92: COURTYARD | MARRIOTT MARKHAM (65 MINTHORN BLVD, MARKHAM)
A93: =A92+1 -> 74 | B93: JOSE (JAY) | E93: =C93*D93 -> 0 | F93: SPRINGHILL SUITES - MARRIOTT (612 APPLEWOOD CRES, VAUGHAN)
A94: =A93+1 -> 75 | B94: NELLANE JOY DELA CRUZ | E94: =C94*D94 -> 0 | F94: HOMEWOOD SUITES - HILTON (50 BODRINGTON CT, MARKHAM)
A95: =A94+1 -> 76 | B95: JOY RALUTA - MARLOU BUSEL | E95: =C95*D95 -> 0 | F95: KNIGHTS INN (22 METROPOLITAN RD, SCARBOROUGH)
A96: =A95+1 -> 77 | B96: JOY RAMOS - LENY SALLUTAL | D96: 16 | E96: =C96*D96 -> 0 | F96: DAYS INN OTTAWA WEST (350 MOODIE DR, OTTAWA)
A97: =A96+1 -> 78 | B97: JUDY ANNE | D97: 16 | E97: =C97*D97 -> 0 | F97: DAYS INN OTTAWA WEST (350 MOODIE DR, OTTAWA)
A98: =A97+1 -> 79 | B98: JUN | E98: =C98*D98 -> 0 | F98: SANDMANN HAMILTON
A99: =A98+1 -> 80 | B99: JUSTINA ANDAL | E99: =C99*D99 -> 0 | F99: BEST WESTERN PLUS (38 ESTATE DRIVE, SCARBOROUGH)
B100: JUSTINA ANDAL | E100: =C100*D100 -> 0 | F100: HOMEWOOD SUITES - HILTON (50 BODRINGTON CT, MARKHAM)
...

Sheet FOR CHEQUE
A1: Employees | B1: Mode of Payment | D1: For e-transfer | E1: c/o Jasmine
A2: Aileen | B2: Etransfer
A3: Aira - Michael Leyva
A4: Alberto | B4: Etransfer
A5: Alejandra Cristina Lugo Martinez
A6: Alex
A7: Aljhen Christine Moreno
A8: Amary
A9: Analyn Tarroza (Danilo) | B9: DD
A10: Andreuis Abara
A11: Andrew Verches
A12: Anita Madhar
A13: Aradhika - NO PAY
A14: Arys
A15: Augusto - Maiylen Denolan
A16: Awais - Mary Ann Barnuevo
A17: Aydhen
A18: Banita - Loveleen Kaur
A19: Believe Tshamala
A20: Berna Sampang
A21: Bernitalyn | B21: Etransfer
A22: Bryzelle
A23: Carlo Martin Alfaro
A24: Carlos
A25: Carol | B25: Etransfer
A26: Charlie
A27: Christian
A28: Corelie
A29: Dale Gabriel Viado
A30: Danny
A31: Diane T Cambridge - Melanie Garcia
A32: Dianne Oakville - Russian Dan Rasco
A33: Digvijaysinh B Jadeja
A34: Dirk Brandon
A35: Divyash Kapur
A36: Edna - Marites Tolentino
A37: Eileen - Winnielyn Garcia
... A41: Gagandeep Singh
A42: Gerome | B42: cash
A43: Giddel Libranda
A44: Girlie
A45: Oluebube Gladys Ohizu
A46: Greg
A47: Gurpinder Kaur
A48: Gwendolyn | B48: Etransfer
A49: Harlan - Karel John Gumapas
A50: Harman
A51: Harpreet Kaur
A52: Henry
A53: Isha
A54: Jashan Turna
A55: Jasmin Lazaro
A56: Jasmine Dalapo
A57: Jaydev Vaishnav
A58: Jayson
A59: Jeanielyn Jallorina
A60: Jefferson
... A70: Joanna
A71: Jo-Anne Cambridge | B71: Etransfer
A72: John - Marites Tolentino
A73: John Neil
A74: John Patrick
A75: John Wesley
A76: Jonan Salas at 18/hr
A77: Nellane Joy Dela Cruz
A78: Joy Ramos
A79: Justina Andal
A80: Kameels
A81: Kathleen - Kristine Deleon
A82: Kean Joshua
A83: Ke-Ann Olarte
... A112: Nellie Dionio
A113: Nickson | B113: cash
A114: Nikki - Melanie Garcia
A115: Nino
A116: Onyinyechukwu Chukwuma
A117: Patricia
A118: Philogene
A119: Princess Ortiz - Melanie Garcia
A120: Rowena Virgo (Rachel and Romel)
A121: Rajdeep Kaur Baring
A122: Randeep
A123: Rea | B123: Etransfer
A124: Rey | B124: cash
A125: Cristopher Ubando - Rhodora
A126: Rojelisa | B126: Etransfer
A127: Reyna April Seduco - Rolando
A128: Rosa ???
A129: Maria Rosario Meneses
A130: Rudrax Joshi
A131: Rutul
A132: Mark Edzel Dela Rosa - Ruwe
A133: Sarah Bustamante
A134: Sasha Brown
A135: Sayeedah
A136: Scarlett
A137: Shakeriah Wheatle
A138: Shanna
... A169: Zidane Joel

Sheet NAMES
C1: NAME | D1: Remarks
B2: 1 | C2: AIDEN - Melanie Garcia
B3: 1 | C3: AKIN BABALOLA | D3: DONE | G3: AKIN BABALOLA | J3: 894 BASELINE ROAD OTTAWA, ON
B4: =B3+1 -> 2 | C4: ALEJANDRA CRISTINA LUGO MARTINEZ
B5: =B4+1 -> 3 | C5: ALJHEN CHRISTINE MORENO
B6: =B5+1 -> 4 | C6: AMAN | D6: DONE | G6: AMAN KIRITKUMAR SOLANKI
B7: =B6+1 -> 5 | C7: AMARY TOLENTINO
B8: =B7+1 -> 6 | C8: ANA | D8: DONE | G8: ANA CHAVEZ | J8: 1512 - 41 ANTRIM CRESCENT SCARBOROUGH ON M1P 4T1
B9: =B8+1 -> 7 | C9: ANDREIUS ABARA
B10: =B9+1 -> 8 | C10: ANDREW VERCHES
B11: =B10+1 -> 9 | C11: ANGELICA | D11: DONE | G11: ANGELICA MARTIN RAMOS | J11: 1233 WOODROFFE AVENUE, OTTAWA, ON K2C 2T2
B12: =B11+1 -> 10 | C12: ANITA MADHAR
B13: =B12+1 -> 11 | C13: APRIL | D13: DONE | G13: APRIL TING | J13: 666 GREYCEDAR CRESCENT MISSISSAUGA ON L4W 3J7
B14: =B13+1 -> 12 | C14: ARYS ALEKCI SULABO
B15: =B14+1 -> 13 | C15: AWAIS - MARY ANN BARNUEVO
B16: =B15+1 -> 14 | C16: BRYZZEL GERONIMO
B17: =B16+1 -> 15 | C17: CARLOS HUMBERTO CAMELO RAMIREZ
B18: =B17+1 -> 16 | C18: CHARMAINE | D18: DONE | G18: CHARMAINE EUSTAQUIO | J18: 536 BELLAMY NORTH ROAD
B19: =B18+1 -> 17 | C19: CIRSTY | D19: DONE | G19: CIRSTY AGUILAR | J19: 107 McALLISTER RD
B20: =B19+1 -> 18 | C20: CORELIE - MARIA ANNA OBIEN CASTRO
B21: =B20+1 -> 19 | C21: DANNY LEILA ITERITEKA
B22: =B21+1 -> 20 | C22: DAPHNE | D22: DONE | G22: DARREN MOSKITO | J22: 51 SPLINTER CRESCENT OTTAWA ONTARIO CANADA K2B 1B3
B23: =B22+1 -> 21 | C23: DARYLL | D23: DONE | G23: DARYLL GEORGE GABIANA DACAYANA | J23: 19 HOPEWELL CRESCENT STONEY CREEK L8J 1P3
B24: =B23+1 -> 22 | C24: DAVINDER | D24: DONE | G24: DAVINDER SINGH
B25: =B24+1 -> 23 | C25: DIANE T - MELANIE GARCIA
B26: =B25+1 -> 24 | C26: DIANNA M. | D26: DONE | G26: DIANA RUTH MORALES
B27: =B26+1 -> 25 | C27: DIANNE P. - MELANIE GARCIA
B28: =B27+1 -> 26 | C28: DIGVIJAYSINH B LADEJA
B29: =B28+1 -> 27 | C29: DIRK BRANDON LAPITAN
B30: =B29+1 -> 28 | C30: DIVYASH KAPUR
B31: =B30+1 -> 29 | C31: EILEEN - WINNIELYN GARCIA
B32: =B31+1 -> 30 | C32: ELLA ELLINE | D32: DONE | G32: MAE CONCEPCION MARQUEZ | J32: 59 RUE WRIGHT GATINEAU QUEBEC J8X 2G2
B33: =B32+1 -> 31 | C33: EMILY MENDOZA
B34: =B33+1 -> 32 | C34: EMMANUEL | D34: DONE | G34: EMMANUEL OKUMU | J34: 1889 CARLING AVE OTTAWA ON K2A
B35: =B34+1 -> 33 | C35: ERWIN OBICO UCHI
B36: =B35+1 -> 34 | C36: EVER | D36: DONE | G36: MELANIE GARCIA | J36: 425 STRASBURG ROAD, KITCHENER, N2E 1T3 ONTARIO
B37: =B36+1 -> 35 | C37: FAITH DELA CRUZ
B38: =B37+1 -> 36 | C38: GAGANDEEP SINGH
B39: =B38+1 -> 37 | C39: OLADELE GBENGA
B40: =B39+1 -> 38 | C40: GIRLIE CASANOVA DIALA
B41: =B40+1 -> 39 | C41: GREGORIO PLETO
B42: =B41+1 -> 40 | C42: GURPINDER KAUR
B43: =B42+1 -> 41 | C43: HARLAN - KAREL JOHN GUMAPAS
B44: =B43+1 -> 42 | C44: JACKIE | D44: DONE | G44: JACKIELYNE PENANO | J44: 215 BELLAMY RD N SCARBOROUGH ON M1J 2L7
B45: =B44+1 -> 43 | C45: JANE | D45: DONE | G45: JANE ETCOBANEZ ESMANA | J45: 91 MARKLAND CRESCENT NEPEAN OTTAWA K2G 5Z6
B46: =B45+1 -> 44 | C46: JASHAN TURNA - JASHANPREET KAUR
B47: =B46+1 -> 45 | C47: JAY | D47: DONE | G47: JAY GOMEZ | J47: PICKUP (W SOFIA)
B48: =B47+1 -> 46 | C48: JAYDEV VAISHNAV
B49: =B48+1 -> 47 | C49: JAYNA | D49: DONE | G49: JAYNA MARIE DE CASTRO | J49: 594 DOLLY BIRD LN MISSISSAUGA PN L5W 1G7
B50: =B49+1 -> 48 | C50: JEANIELYN JALLORINA
B51: =B50+1 -> 49 | C51: JENNY RULLODA
B52: =B51+1 -> 50 | C52: JEREMIE LEWIS LAMADELINE | G52: JEREMIE LEWIS LAMADELINE | J52: MOUNTSHANNON NAPEAN ONTARIO K2J 4B8
B53: =B52+1 -> 51 | C53: JERICK PARASO
B54: =B53+1 -> 52 | C54: JERONE DE VILLA
B55: =B54+1 -> 53 | C55: JESSICA ERIKA MAE SABLAS
B56: =B55+1 -> 54 | C56: JOHN EDMAR MARTINEZ
B57: =B56+1 -> 55 | C57: JOHN NEIL CASANOVA
B58: =B57+1 -> 56 | C58: JOHN PATRICK - CHESTER VINCENT GONZALES
B59: =B58+1 -> 57 | C59: JONAN SALAS
B60: =B59+1 -> 58 | C60: JOSE (JAY) | D60: DONE | G60: JOSE (JAY) RADAM | J60: 61 HUTCHERSON SQUARE SCARBOROUGH ON M1B 1C5
B61: =B60+1 -> 59 | C61: NELLANE JOY DELA CRUZ
B62: =B61+1 -> 60 | C62: JOY RALUTA - MARLOU BUSEL
B63: =B62+1 -> 61 | C63: JOY RAMOS - LENY SALLUTAL
B64: =B63+1 -> 62 | C64: JUDY ANNE | D64: DONE | G64: MAE CONCEPCION MARQUEZ | J64: 59 RUE WRIGHT GATINEAU QUEBEC J8X 2G2
B65: =B64+1 -> 63 | C65: JUN | D65: DONE | G65: JUNEL D IBALIG | J65: 19 HOPEWELL CRESCENT STONEY CREEK L8J 1P3
B66: =B65+1 -> 64 | C66: JUSTINA ANDAL
B67: =B66+1 -> 65 | C67: KAMALPREET | D67: DONE | G67: KAMALPREET KAUR | J67: 35 FAYWOOD DRIVE BRAMPTON L6Y 4K3 ONTARIO
B68: =B67+1 -> 66 | C68: KARL | D68: DONE | G68: KARL DREXLER CUIZON | J68: 129 KENNEVALE DRIVE NEPEAN ON K2J 3X7
B69: =B68+1 -> 67 | C69: KATHLEEN - KRISTINE DELEON
B70: =B69+1 -> 68 | C70: KEAN JOSHUA GARCIA
B71: =B70+1 -> 69 | C71: KE-ANN OLARTE
B72: =B71+1 -> 70 | C72: KIRSTEN CARMEL RICACHO
B73: =B72+1 -> 71 | C73: KOSISOCHUKWU CHUKWUMA
B74: =B73+1 -> 72 | C74: KOWSHALYAH ANURAGAVEN
B75: =B74+1 -> 73 | C75: LARA | D75: DONE | G75: JERUZ TEODORO | J75: PICKUP
B76: =B75+1 -> 74 | C76: LAURIE VIGNAUD
B77: =B76+1 -> 75 | C77: LENY SALLUTAL
B78: =B77+1 -> 76 | C78: LIBERTY | D78: DONE | G78: LIBERTY ABENOJA | K78: 91 MARKLAND CRESCENT NEPEAN OTTAWA K2G 5Z6
B79: =B78+1 -> 77 | C79: LILY AMOAH
B80: =B79+1 -> 78 | C80: LORENZO | D80: DONE | G80: LORENZO BACALTOS | K80: 287 BOULEVARD D'EUROPE GATINEAU QUEBEC J9J 0G4 APT2
B81: =B80+1 -> 79 | C81: LOVELEEN KAUR
B82: =B81+1 -> 80 | C82: LOVEPREET KAUR DHALIWAL
B83: =B82+1 -> 81 | C83: MADY | D83: DONE | G83: MADY CUSTODIO | K83: PICKUP (W SOFIA)
B84: =B83+1 -> 82 | C84: MAE | D84: DONE | G84: JEANIE MAY A JALLORINA | K84: REY WILL GET SALARY
B85: =B84+1 -> 83 | C85: MAE ARAGON
B86: =B85+1 -> 84 | C86: MANMOJIT - SHARANJIT KAUR
B87: =B86+1 -> 85 | C87: MANU MATTHEW
B88: =B87+1 -> 86 | C88: MARIE DUFOUR | D88: DONE | G88: JEREMIE LEWIS LAMADELINE | J88: MOUNTSHANNON NAPEAN ONTARIO K2J 4B8
B89: =B88+1 -> 87 | C89: MARIE MERCY INEZA
B90: =B89+1 -> 88 | C90: MARLENE - MARIA ELENA DELEON
B91: =B90+1 -> 89 | C91: MARY ANN VALDEHUEZA
B92: =B91+1 -> 90 | C92: MD NIZAM UDDIN
B93: =B92+1 -> 91 | C93: MICHAEL ANGELO | D93: DONE | G93: ANGELITA HARLEY | J93: 820 EAST 33RD VANCOUVER BC V5V 3A3
B94: =B93+1 -> 92 | C94: MINETTE BIARES
B95: =B94+1 -> 93 | C95: MURSAL - NAVEED JOHN
B96: =B95+1 -> 94 | C96: MYRNA ALCONTIN
B97: =B96+1 -> 95 | C97: NAVNEET KAUR
B98: =B97+1 -> 96 | C98: NELLIE DIONIO
B99: =B98+1 -> 97 | C99: NIKKI - MELANIE GARCIA
B100: =B99+1 -> 98 | C100: NIÑO | D100: SAME WITH CIRSTY | G100: NINOIL AGUILAR | J100: 107 MCALLISTER RD
...
